Workbook

Sheet LOI and Commissioning Master Sh
A1: Basis Information | W1: Information Shared with MSO | AF1: To be Filled By DO | AT1: To be Filled by FO | BK1: To be Filled by Engineers- for A sites SM(Engg) and for B sites by Area Engineer | BW1: by DO
A2: SN | B2: Name of Location | C2: Loi Holder Name | D2: Retail Sales Area | E2: SN of Location | F2: LOI Holder contact details | G2: Market Class | H2: Type | I2: RO/KSK | J2: TYPE OF SITE | K2: Letter of Intent Number | L2: Marketing Plan | M2: LOI Date | N2: LOI Age | O2: LOI Age Analysis | P2: District | Q2: Description | R2: Land Offer | S2: Motor Spirit Potential | T2: HSD Potential | U2: Total Potential | V2: Strategic | W2: Commissionable | X2: Comm. Plan in FY26-27 | Y2: IO Available/If not available target month (MMM-YY format) | Z2: Advanced Tender Approval Status | AA2: NA Available (Y/N) | AB2: PESO CA Available (Y/N) | AC2: NOC Available (Y/N) | AD2: NOC Month | AE2: Comm. Month | AF2: Commissionable | AG2: Case of Non-Commissionable | AH2: LOI cancellation | AI2: Valuation if applicable | AJ2: Negotiations if applicable | AK2: NOC Available | AL2: Expected Month of NOC | AM2: Concept Note | AN2: Estimate | AO2: Note Draft | AP2: IO Available | AQ2: IO NO | AR2: IO Reamrk | AS2: Expected Month of commissioning-Actual | AT2: LOI Collected (Yes/No) | AU2: LOI Commissionable (Yes/Yes but in next FY/No) | AV2: Reason for Non Commissionable and Commissionable in Next FY | AW2: If Non Commissionabl, whether recommended for Cancellation (Yes/No) | AX2: NOC Applied | AY2: Mojnai (Yet to Apply/Applied/Received/NA) | AZ2: Building Plan Approval and NA (Yet to Apply/Applied/Received/NA) | BA2: Police (Yet to Apply/Applied/Received/NA) | BB2: NH/PWD (Yet to Apply/Applied/Received/NA) | BC2: MSEB (Yet to Apply/Applied/Received/NA) | BD2: Dy Dir Industrial safety (Yet to Apply/Applied/Received/NA) | BE2: Wild Life (Yet to Apply/Applied/Received/NA) | BF2: Forest (Yet to Apply/Applied/Received/NA) | BG2: LSR only (Yet to Assign/In Process/Received) | BH2: Site Readiness (Yes/No/WIP) | BI2: Expected Month of NOC (MMM-YY) | BJ2: Expected Month of Commg (MMM-YY) | BK2: Layout Drawing (Yes/No/Moujani Awaited) | BL2: PESO Prior (Yet to Apply/Applied/Received) | BM2: BOQ Sent for Approved Cases (Yes/No/NA) | BN2: Advance Tender Status(Yet to Publish/Published/Awarded/NA/Approval Awaited) | BO2: Tender Publication by RCC Date | BP2: WO Number (NOC/IO Awaited) | BQ2: WO Date | BR2: Name of Contractor | BS2: WO Completion Target Date Date | BT2: Date of Site Handing Over | BU2: Expected Date of Commissioning | BV2: PESO Final License Status (Applied/Received/Yet to Apply) | BW2: Final Commissioning Status | BX2: SAP Code | BY2: RO Name | BZ2: LSR assigned to | CA2: Valuation assigned to | CB2: SRMP | CC2: LOI as on 01.04.2026 | CD2: MOU Target | CE2: LOA No | CF2: SAP Code | CG2: Name of RO | CH2: WIP | CI2: LOI Month | CJ2: Category | CK2: MOU | CL2: Committed to SO | CM2: Admin Approval reference NO | CN2: Pending With
A3: 119 | B3: Village Yelse on MDR (Pawna lake to Kamshet Road) | C3: DIKSHA SACHIN SONAWANE | D3: Pune Tathawade RSA | E3: 2112 | F3: 9767902929 | G3: E | H3: A | I3: KSK | J3: KSK-A w/o Reco | K3: R/2023/IN003356/MAH/000373/3203/00114 | L3: 2023-24 | M3: 45315 | N3: =+TODAY()-M3 -> 862 | O3: =+IF(N3<180,"0-6M",IF(N3<365,"6-12M",IF(N3<730,"1-2Y",IF(N3<1095,"2-3Y",IF(N3<1460,"3-4Y",IF(N3<1825,"4-5Y",IF(N3>1825,">5Y"))))))) -> 2-3Y | P3: PUNE | Q3: SC | R3: Group 1: Owned land | S3: 30 | T3: 90 | U3: =+S3+T3 -> 120 | W3: Yes | X3: Yes | Y3: =+AP3 -> Yes | Z3: Approved | AC3: Yes | AD3: =+AL3 -> 46082 | AE3: =+AS3 -> 46113 | AF3: Yes | AG3: NA | AH3: NA | AI3: Yes | AJ3: Yes | AK3: Available | AL3: 46082 | AM3: Yes | AN3: Yes | AO3: Approved | AP3: Yes | AQ3: 4337839 | AS3: 46113 | AT3: Yes | AU3: Yes | AV3: LOI holder asking for recon at LOI stage, LSR has come dtd 24.07.24 | AW3: NA | AX3: Yes | AY3: Yes | AZ3: Yes | BA3: Received | BB3: Not Required | BC3: Received | BD3: Received | BE3: NA | BF3: NA | BG3: Received | BH3: Yes | BI3: 46113 | BJ3: 46113 | BK3: Yes | BL3: Received | BN3: Yes | BW3: Commissioned | BX3: 391546 | BY3: Sai Veenit Petroleum | CB3: SRMP 2023-24 | CC3: Yes | CD3: Yes | CF3: 391546 | CG3: Sai Veenit Petroleum | CH3: Yes | CI3: =TEXT(M3,"MMM'YY") -> Jan'24 | CJ3: SC | CK3: Yes | CL3: Yes
A4: 70 | B4: From Kalas to Rui Village on MDR via Gosaviwadi | C4: VIJAY BABAN KALE | D4: Pune Saswad RSA | E4: 2110 | F4: 7499292270 | G4: E | H4: B | I4: KSK | J4: KSK-B w/o Reco | K4: R/2023/IN000625/MAH/000058/3203/00018 | L4: 2023-24 | M4: 45249 | N4: =+TODAY()-M4 -> 928 | O4: =+IF(N4<180,"0-6M",IF(N4<365,"6-12M",IF(N4<730,"1-2Y",IF(N4<1095,"2-3Y",IF(N4<1460,"3-4Y",IF(N4<1825,"4-5Y",IF(N4>1825,">5Y"))))))) -> 2-3Y | P4: PUNE | Q4: OPEN | R4: Group 1: Owned land | S4: 30 | T4: 51 | U4: =+S4+T4 -> 81 | W4: Yes | X4: Yes | Y4: =+AP4 -> Yes | Z4: NA | AC4: Yes | AD4: =+AL4 -> 46143 | AE4: =+AS4 -> 46143 | AF4: Yes | AG4: NA | AH4: NA | AI4: Not Required | AJ4: Not Required | AK4: Available | AL4: 46143 | AM4: Yes | AN4: Yes | AO4: Approved | AP4: Yes | AQ4: 4337720 | AS4: 46143 | AT4: Yes | AU4: Yes | AW4: NA | AX4: Yes | AY4: Yes | AZ4: Received | BA4: Received | BB4: Received | BC4: Received | BD4: Received | BE4: NA | BF4: NA | BG4: Received | BH4: Yes | BI4: 46168 | BJ4: 46168 | BK4: Yes | BL4: Received | BM4: NA | BN4: NA | BO4: Not Required | BP4: 72293969 | BQ4: 18.05.2026 | BR4: PC ENGINEERING CONTRACTORS | BS4: 29.06.2026 | BT4: 19.05.2026 | BV4: Applied | BW4: Commissioned | BX4: 393129 | BY4: Vijayraj Petroleum | CB4: SRMP 2023-24 | CC4: Yes | CD4: Yes | CI4: =TEXT(M4,"MMM'YY") -> Nov'23 | CJ4: Open | CK4: Yes | CL4: Yes
A5: 75 | B5: From KM stone 33 to 35 on LHS of Khandala Lonand Road | C5: SHEKHAR HANAMANT YADAV | D5: Satara East RSA | E5: 2109 | F5: 7387890252 | G5: E | H5: B | I5: KSK | J5: KSK-B w/o Reco | K5: R/2023/IN001265/MAH/000090/3203/00031 | L5: 2023-24 | M5: 45264 | N5: =+TODAY()-M5 -> 913 | O5: =+IF(N5<180,"0-6M",IF(N5<365,"6-12M",IF(N5<730,"1-2Y",IF(N5<1095,"2-3Y",IF(N5<1460,"3-4Y",IF(N5<1825,"4-5Y",IF(N5>1825,">5Y"))))))) -> 2-3Y | P5: SATARA | Q5: OPEN | R5: Group 1: Owned land | S5: 20 | T5: 80 | U5: =+S5+T5 -> 100 | W5: Yes | X5: Yes | Z5: NA | AC5: Yes | AD5: 46143 | AE5: 46143 | AF5: Yes | AG5: NA | AH5: NA | AI5: Not Required | AJ5: Not Required | AK5: Available | AL5: 46143 | AM5: Yes | AN5: Yes | AO5: Approved | AP5: Yes | AQ5: 4338576 | AS5: 46143 | AT5: Yes | AU5: Yes | AV5: NA | AW5: NA | AX5: Yes | AY5: Received | AZ5: Received | BA5: Received | BB5: Received | BC5: Received | BD5: NA | BE5: NA | BF5: NA | BG5: Received | BH5: WIP | BI5: 46148 | BJ5: 46143 | BK5: Yes | BL5: Received | BM5: NA | BN5: NA | BO5: Not Required | BW5: Commissioned | BX5: 392992 | BY5: Bhairavnath Petroleum | CB5: SRMP 2023-24 | CC5: Yes | CD5: Yes | CI5: =TEXT(M5,"MMM'YY") -> Dec'23 | CJ5: Open | CK5: Yes | CL5: Yes
A6: 79 | B6: WITHIN 5 KM FROM DHEBEWADI PHATA KARAD TOWARDS SATARA ON LHS OF KARAD TO SATARA ROAD | C6: CHINMAY ARVIND GHATE | D6: Satara West RSA | E6: 1925 | F6: 9604101182 | G6: D1 | H6: B | I6: RO | J6: RO B Site | K6: R/2023/IN001436/MAH/000103/3203/00039 | L6: 2023-24 | M6: 45271 | N6: =+TODAY()-M6 -> 906 | O6: =+IF(N6<180,"0-6M",IF(N6<365,"6-12M",IF(N6<730,"1-2Y",IF(N6<1095,"2-3Y",IF(N6<1460,"3-4Y",IF(N6<1825,"4-5Y",IF(N6>1825,">5Y"))))))) -> 2-3Y | P6: SATARA | Q6: OPEN | R6: Group 1: Owned land | S6: 30 | T6: 120 | U6: =+S6+T6 -> 150 | W6: Yes | X6: Yes | Y6: =+AP6 -> Yes | Z6: NA | AC6: Yes | AD6: =+AL6 -> 46143 | AE6: =+AS6 -> 46143 | AF6: Yes | AG6: NA | AH6: NA | AI6: Not Required | AJ6: Not Required | AK6: Available | AL6: 46143 | AM6: Yes | AN6: Yes | AO6: Approved | AP6: Yes | AQ6: 4337806 | AS6: 46143 | AT6: YES | AU6: YES | AV6: NA | AW6: NA | AX6: YES | AY6: Received | AZ6: Received | BA6: Received | BB6: Applied | BC6: Received | BD6: NA | BE6: NA | BF6: NA | BG6: Received | BH6: WIP | BI6: 46168 | BJ6: 46199 | BK6: Yes | BL6: Received | BM6: NA | BN6: NA | BO6: Not Required | BW6: Commissioned | BX6: 393128 | BY6: Krishna Petroleum and Energy Hub | CB6: SRMP 2023-24 | CC6: Yes | CD6: Yes | CI6: =TEXT(M6,"MMM'YY") -> Dec'23 | CJ6: Open | CK6: Yes | CL6: Yes
A7: 123 | B7: From Jadhavwadi to Laxmi Chowk on DP Road | C7: MAYUR SUNIL BORATE | D7: Pimpri Chinchwad RSA | E7: 1801 | F7: 7720000414 | G7: A | H7: A | I7: RO | J7: RO A Site | K7: R/2023/IN003596/MAH/000399/3203/00122 | L7: 2023-24 | M7: 45322 | N7: =+TODAY()-M7 -> 855 | O7: =+IF(N7<180,"0-6M",IF(N7<365,"6-12M",IF(N7<730,"1-2Y",IF(N7<1095,"2-3Y",IF(N7<1460,"3-4Y",IF(N7<1825,"4-5Y",IF(N7>1825,">5Y"))))))) -> 2-3Y | P7: PUNE | Q7: OPEN | R7: Group 1: Owned land | S7: 150 | T7: 50 | U7: =+S7+T7 -> 200 | W7: Yes | X7: Yes | Y7: =+AP7 -> Yes | Z7: Approved | AA7: Yes | AB7: Yes | AC7: Yes | AD7: =+AL7 -> 46113 | AE7: =+AS7 -> 46143 | AF7: Yes | AG7: NA | AH7: NA | AI7: Yes | AJ7: Yes | AK7: Available | AL7: 46113 | AM7: Yes | AN7: Yes | AO7: Approved | AP7: Yes | AQ7: 4337869 | AS7: 46143 | AT7: Yes | AU7: Yes | AV7: NA | AW7: NA | AX7: Yes | AY7: Received | AZ7: Received | BA7: Received | BB7: Not Required | BC7: Received | BD7: Received | BE7: NA | BF7: NA | BG7: Received | BH7: Yes | BI7: 46113 | BJ7: 46143 | BK7: Yes | BL7: Received | BN7: Yes | BW7: Commissioned | BX7: 392301 | BY7: S N Borate Petroleum | CB7: SRMP 2023-24 | CC7: Yes | CD7: Yes | CH7: Yes | CI7: =TEXT(M7,"MMM'YY") -> Jan'24 | CJ7: Open | CK7: Yes | CL7: Yes
A8: 172 | B8: Within 6 Km from Atmaram Baba Mandir,Mandali towards Solapur on Ahmednagar-Solapur NH | C8: RAMAN PANDHARINATH KHULE | D8: Ahmednagar West RSA | E8: 1721 | F8: 8329858727 | G8: D1 | H8: B | I8: RO | J8: RO B Site | K8: R/2024/IN002364/MAH/000194/3203/00029 | L8: 2023-24 | M8: 45460 | N8: =+TODAY()-M8 -> 717 | O8: =+IF(N8<180,"0-6M",IF(N8<365,"6-12M",IF(N8<730,"1-2Y",IF(N8<1095,"2-3Y",IF(N8<1460,"3-4Y",IF(N8<1825,"4-5Y",IF(N8>1825,">5Y"))))))) -> 1-2Y | P8: AHMADNAGAR | Q8: OPEN | R8: Group 1: Owned land | S8: 30 | T8: 123 | U8: =+S8+T8 -> 153 | W8: Yes | X8: Yes | Y8: =+AP8 -> Yes | Z8: NA | AD8: =+AL8 -> 46143 | AE8: =+AS8 -> 46143 | AF8: Yes | AG8: NA | AH8: NA | AI8: Not Required | AJ8: Not Required | AK8: Available | AL8: 46143 | AM8: Yes | AN8: Yes | AO8: Approved | AP8: Yes | AQ8: 4338116 | AS8: 46143 | AT8: Yes | AU8: Yes | AV8: NA | AW8: NA | AX8: Yes | AY8: Received | AZ8: Received | BA8: Received | BB8: Received | BC8: NA | BD8: NA | BE8: Received | BF8: Received | BG8: Received | BH8: Yes | BI8: 46082 | BJ8: 46143 | BK8: Yes | BL8: Received | BM8: NA | BN8: NA | BO8: Not Required | BW8: Commissioned | BX8: 392938 | BY8: Gangagiri Petroleum | CB8: SRMP 2023-24 | CC8: Yes | CD8: Yes | CH8: Yes | CI8: =TEXT(M8,"MMM'YY") -> Jun'24 | CJ8: Open | CK8: Yes | CL8: Yes
A9: 203 | B9: From Bhigwan Circle to Dalaj Phata on RHS of Pune- Solapur Highway | C9: KUNDALIK UTTAM KAMBLE | D9: Pune Saswad RSA | E9: 1665 | F9: 9960252231 | G9: D1 | H9: A | I9: RO | J9: RO A Site-Corpu | K9: R/2024/IN002520/MAH/000255/3203/00078 | L9: 2023-24 | M9: 45463 | N9: =+TODAY()-M9 -> 714 | O9: =+IF(N9<180,"0-6M",IF(N9<365,"6-12M",IF(N9<730,"1-2Y",IF(N9<1095,"2-3Y",IF(N9<1460,"3-4Y",IF(N9<1825,"4-5Y",IF(N9>1825,">5Y"))))))) -> 1-2Y | P9: PUNE | Q9: SC | R9: Group 2: Firm Offer | S9: 30 | T9: 130 | U9: =+S9+T9 -> 160 | W9: Yes | X9: Yes | Y9: =+AP9 -> Yes | Z9: Approved | AC9: Yes | AD9: =+AL9 -> 46113 | AE9: =+AS9 -> 46143 | AF9: Yes | AG9: NA | AH9: NA | AI9: Yes | AJ9: Yes | AK9: Available | AL9: 46113 | AM9: Yes | AN9: Yes | AO9: Approved | AP9: Yes | AQ9: 4338194 | AS9: 46143 | AT9: Yes | AU9: Yes | AV9: NA | AW9: NA | AX9: Yes | AY9: Yes | AZ9: Received | BA9: Received | BB9: Received | BC9: Received | BD9: Received | BE9: NA | BF9: NA | BG9: Received | BH9: Yes | BI9: 46107 | BJ9: 46168 | BK9: Yes | BL9: Received | BN9: Yes | BW9: Commissioned | BX9: 392994 | BY9: Mauli Petroleum | CB9: SRMP 2023-24 | CC9: Yes | CD9: Yes | CE9: R/2026/IN000139/3203/00004 | CI9: =TEXT(M9,"MMM'YY") -> Jun'24 | CJ9: SC | CK9: Yes | CL9: Yes
A10: 218 | B10: At Village Karhavagaj on Jejuri-Morgaon-Baramati Road | C10: BALASAHEB LIMBAJI AGAWANE | D10: Pune Tathawade RSA | E10: 1736 | F10: 9922414802 | G10: D2 | H10: A | I10: RO | J10: RO A Site-Corpu | K10: R/2024/IN003547/MAH/000391/3203/00107 | L10: 2023-24 | M10: 45547 | N10: =+TODAY()-M10 -> 630 | O10: =+IF(N10<180,"0-6M",IF(N10<365,"6-12M",IF(N10<730,"1-2Y",IF(N10<1095,"2-3Y",IF(N10<1460,"3-4Y",IF(N10<1825,"4-5Y",IF(N10>1825,">5Y"))))))) -> 1-2Y | P10: PUNE | Q10: SC | R10: Group 1: Owned land | S10: 30 | T10: 80 | U10: =+S10+T10 -> 110 | W10: Yes | X10: Yes | Y10: =+IF(AO10="Approved","Yes",AS10) -> Yes | Z10: Approved | AA10: Yes | AB10: No | AC10: Yes | AD10: =+AL10 -> 46143 | AE10: =+AS10 -> 46143 | AF10: Yes | AG10: NA | AH10: NA | AI10: Yes | AJ10: Yes | AK10: Available | AL10: 46143 | AM10: Yes | AN10: Yes | AO10: Approved | AP10: Yes | AQ10: 4338515 | AS10: 46143 | AT10: Yes | AU10: Yes | AV10: DM NOC received on 08.05.2026 | AW10: NA | AX10: Yes | AY10: Yes | AZ10: Yes | BA10: Received | BB10: Received | BC10: Received | BD10: Received | BE10: NA | BF10: NA | BG10: Received | BH10: WIP | BI10: 46054 | BJ10: 46327 | BK10: Yes | BL10: Received | BN10: Yes | BW10: Commissioned | BX10: 393015 | BY10: Ahilya Petroleum | CB10: SRMP 2023-24 | CC10: Yes | CD10: Yes | CE10: R/2026/IN000141/3203/00005 | CI10: =TEXT(M10,"MMM'YY") -> Sep'24 | CJ10: SC | CK10: Yes | CL10: Yes
A11: 62 | B11: AT VADAPURI ON LHS OF INDAPUR-AKLUJ ROAD , | C11: VISHRAM MORE | D11: Pune Saswad RSA | F11: 9850601522 | G11: D1 | H11: A | I11: RO | J11: RO A Site-Corpu | K11: M/2022/IN001731/MAH/000117/3203/00043 | L11: 2018-19 | M11: 45012 | N11: =+TODAY()-M11 -> 1165 | O11: =+IF(N11<180,"0-6M",IF(N11<365,"6-12M",IF(N11<730,"1-2Y",IF(N11<1095,"2-3Y",IF(N11<1460,"3-4Y",IF(N11<1825,"4-5Y",IF(N11>1825,">5Y"))))))) -> 3-4Y | P11: PUNE | Q11: ST | R11: Group 2: Firm Offer | S11: 40 | T11: 110 | U11: =+S11+T11 -> 150 | W11: Yes | X11: Yes | Y11: =+IF(AO11="Approved","Yes",AS11) -> 46174 | Z11: Approved | AD11: =+AL11 -> 46174 | AE11: =+AS11 -> 46174 | AF11: Yes | AG11: NA | AH11: NA | AI11: Yes | AJ11: Yes | AL11: 46174 | AM11: Yes | AN11: Yes | AO11: Sent | AP11: No | AS11: 46174 | AT11: Yes | AU11: Yes | AV11: LSR dtd 11.05.2023. Supple LSR dtd 29.07.24 has come- IO to be taken | AW11: NA | AX11: Yes | AY11: Yes | AZ11: Received | BA11: Received | BB11: Applied | BC11: Received | BD11: Received | BE11: NA | BF11: NA | BG11: Received | BH11: Yes | BI11: 46199 | BJ11: 46199 | BK11: Yes | BL11: Received | BN11: Pending | BW11: Pending | CB11: SRMP 2018-19 | CC11: Yes | CD11: Yes | CI11: =TEXT(M11,"MMM'YY") -> Mar'23 | CJ11: st | CK11: Yes | CL11: Yes | CM11: Administrative Approval/3203/SL01/2025-2026/138315
A12: 72 | B12: Within 3 KM from Akshata Mangal Karyalaya towards Taklibhan on Shrirampur Nevasa SH | C12: PRASAD BALASAHEB CHAUDHARI | D12: Ahmednagar East RSA | E12: 1818 | F12: 9822603682 | G12: D2 | H12: B | I12: RO | J12: RO B Site | K12: R/2023/IN000927/MAH/000071/3203/00022 | L12: 2023-24 | M12: 45257 | N12: =+TODAY()-M12 -> 920 | O12: =+IF(N12<180,"0-6M",IF(N12<365,"6-12M",IF(N12<730,"1-2Y",IF(N12<1095,"2-3Y",IF(N12<1460,"3-4Y",IF(N12<1825,"4-5Y",IF(N12>1825,">5Y"))))))) -> 2-3Y | P12: AHMADNAGAR | Q12: OBC | R12: Group 1: Owned land | S12: 30 | T12: 85 | U12: =+S12+T12 -> 115 | W12: Yes | X12: Yes | Y12: =+AP12 -> Yes | Z12: NA | AD12: =+AL12 -> 46143 | AE12: 46174 | AF12: Yes | AG12: NA | AH12: NA | AI12: Not Required | AJ12: Not Required | AL12: 46143 | AM12: Yes | AN12: Yes | AO12: Approved | AP12: Yes | AQ12: 4337692 | AS12: 46174 | AT12: Yes | AU12: Yes | AV12: NA | AW12: NA | AX12: Yes | AY12: Received | AZ12: Applied | BA12: Received | BB12: Received | BC12: Received | BD12: NA | BE12: Received | BF12: Received | BG12: Received | BH12: Yes | BI12: 46174 | BJ12: 46174 | BK12: Yes | BL12: Received | BM12: NA | BN12: NA | BO12: Not Required | BW12: Pending | CB12: SRMP 2023-24 | CC12: Yes | CD12: Yes | CI12: =TEXT(M12,"MMM'YY") -> Nov'23 | CJ12: OBC | CK12: Yes | CL12: Yes
A13: 96 | B13: From Kasar-Dumala to Chikhali on Sangamner Akole SH | C13: MADHURI RAVINDRA SHENKAR | D13: Shirdi RSA | E13: 1954 | F13: 9156559088 | G13: D2 | H13: A | I13: RO | J13: RO A Site-Corpu | K13: R/2023/IN001869/MAH/000198/3203/00074 | L13: 2023-24 | M13: 45279 | N13: =+TODAY()-M13 -> 898 | O13: =+IF(N13<180,"0-6M",IF(N13<365,"6-12M",IF(N13<730,"1-2Y",IF(N13<1095,"2-3Y",IF(N13<1460,"3-4Y",IF(N13<1825,"4-5Y",IF(N13>1825,">5Y"))))))) -> 2-3Y | P13: AHMADNAGAR | Q13: ST | R13: Group 1: Owned land | S13: 30 | T13: 85 | U13: =+S13+T13 -> 115 | W13: Yes | X13: Yes | Y13: =+AP13 -> Yes | Z13: Approved | AD13: =+AL13 -> 46143 | AE13: =+AS13 -> 46174 | AF13: Yes | AG13: NA | AH13: NA | AI13: Yes | AJ13: Yes | AL13: 46143 | AM13: Yes | AN13: Yes | AO13: Approved | AP13: Yes | AQ13: 4338093 | AS13: 46174 | AT13: Yes | AU13: Yes | AV13: NA | AW13: NA | AX13: Yes | AY13: Recieved | AZ13: Applied | BA13: Recieved | BB13: Recieved | BC13: Recived | BD13: NA | BE13: Recived | BF13: Recived | BG13: Received | BH13: WIP | BI13: 46193 | BJ13: 46265 | BK13: Yes | BL13: Received | BN13: Pending | BW13: Pending | CB13: SRMP 2023-24 | CC13: Yes | CD13: Yes | CI13: =TEXT(M13,"MMM'YY") -> Dec'23 | CJ13: st | CK13: Yes | CL13: Yes
A14: 103 | B14: On RHS of Pune-Solapur NH, From Vangali to intersection of Indapur Bypass & Baramati Highway | C14: OMKAR GIRISH SHAH | D14: Pune Saswad RSA | E14: 1897 | F14: 9730606767 | G14: D1 | H14: A | I14: RO | J14: RO A Site | K14: R/2023/IN002958/MAH/000314/3203/00093 | L14: 2023-24 | M14: 45307 | N14: =+TODAY()-M14 -> 870 | O14: =+IF(N14<180,"0-6M",IF(N14<365,"6-12M",IF(N14<730,"1-2Y",IF(N14<1095,"2-3Y",IF(N14<1460,"3-4Y",IF(N14<1825,"4-5Y",IF(N14>1825,">5Y"))))))) -> 2-3Y | P14: PUNE | Q14: OPEN | R14: Group 1: Owned land | S14: 30 | T14: 120 | U14: =+S14+T14 -> 150 | W14: Yes | X14: Yes | Y14: =+AP14 -> Yes | Z14: Approved | AD14: =+AL14 -> 46143 | AE14: =+AS14 -> 46174 | AF14: Yes | AG14: NA | AH14: NA | AI14: Yes | AJ14: Yes | AL14: 46143 | AM14: Yes | AN14: Yes | AO14: Approved | AP14: Yes | AQ14: 4337433 | AS14: 46174 | AT14: Yes | AU14: Yes | AV14: All NOCs are send for revalidation and awaited | AW14: NA | AX14: Yes | AY14: Yes | AZ14: Received | BA14: Received | BB14: Received | BC14: Received | BD14: Received | BE14: NA | BF14: NA | BG14: Received | BH14: Yes | BI14: 46174 | BJ14: 46199 | BK14: Yes | BL14: Received | BN14: Yes | BW14: Pending | CB14: SRMP 2023-24 | CC14: Yes | CD14: Yes | CI14: =TEXT(M14,"MMM'YY") -> Jan'24 | CJ14: Open | CK14: Yes | CL14: Yes
A15: 140 | B15: FROM SHITPUR PHATA TO NIMBODI PHATA ON SHRIGONDA - JAMKHED ROAD | C15: PRASHANT BAPURAO GAIKWADE | D15: Ahmednagar West RSA | E15: 1738 | F15: 9960968999 | G15: D1 | H15: B | I15: RO | J15: RO B Site | K15: R/2023/IN004897/MAH/000498/3203/00150 | L15: 2023-24 | M15: 45349 | N15: =+TODAY()-M15 -> 828 | O15: =+IF(N15<180,"0-6M",IF(N15<365,"6-12M",IF(N15<730,"1-2Y",IF(N15<1095,"2-3Y",IF(N15<1460,"3-4Y",IF(N15<1825,"4-5Y",IF(N15>1825,">5Y"))))))) -> 2-3Y | P15: AHMADNAGAR | Q15: OPEN | R15: Group 1: Owned land | S15: 30 | T15: 120 | U15: =+S15+T15 -> 150 | W15: Yes | X15: Yes | Y15: =+AP15 -> Yes | Z15: NA | AD15: =+AL15 -> 46143 | AE15: =+AS15 -> 46174 | AF15: Yes | AG15: NA | AH15: NA | AI15: Not Required | AJ15: Not Required | AK15: Available | AL15: 46143 | AM15: Yes | AN15: Yes | AO15: Approved | AP15: Yes | AQ15: 4338435 | AR15: NHAI Access Pending | AS15: 46174 | AT15: Yes | AU15: Yes | AV15: NA | AW15: NA | AX15: Yes | AY15: Received | AZ15: Received | BA15: Received | BB15: Applied | BC15: NA | BD15: NA | BE15: Received | BF15: Received | BG15: Received | BH15: Yes | BI15: 46143 | BJ15: 46143 | BK15: Yes | BL15: Received | BM15: NA | BN15: NA | BO15: Not Required | BR15: PVT. LTD. | BW15: Pending | CB15: SRMP 2023-24 | CC15: Yes | CD15: Yes | CI15: =TEXT(M15,"MMM'YY") -> Feb'24 | CJ15: Open | CK15: Yes | CL15: Yes
A16: 139 | B16: From Navnagapur to Shendi on Shendi Bypass | C16: AKSHAY PRAKASH CHAVAN | D16: Ahmednagar East RSA | E16: 1754 | F16: 9923563624 | G16: D2 | H16: A | I16: RO | J16: RO A Site-Corpu | K16: R/2023/IN004910/MAH/000499/3203/00151 | L16: 2023-24 | M16: 45349 | N16: =+TODAY()-M16 -> 828 | O16: =+IF(N16<180,"0-6M",IF(N16<365,"6-12M",IF(N16<730,"1-2Y",IF(N16<1095,"2-3Y",IF(N16<1460,"3-4Y",IF(N16<1825,"4-5Y",IF(N16>1825,">5Y"))))))) -> 2-3Y | P16: AHMADNAGAR | Q16: ST | R16: Group 1: Owned land | S16: 30 | T16: 100 | U16: =+S16+T16 -> 130 | W16: Yes | X16: Yes | Z16: Approved | AC16: Yes | AD16: 46143 | AE16: 46174 | AF16: Yes | AG16: NA | AH16: NA | AI16: Yes | AJ16: Yes | AK16: Available | AL16: 46143 | AM16: Yes | AN16: Yes | AO16: Sent | AP16: Yes | AQ16: 4338635 | AS16: 46174 | AT16: Yes | AU16: Yes | AV16: NA | AW16: NA | AX16: Yes | AY16: Received | AZ16: Recieved | BA16: Received | BB16: Received | BC16: Received | BD16: NA | BE16: Received | BF16: Received | BG16: Received | BH16: Yes | BI16: 46143 | BJ16: 46174 | BK16: Yes | BL16: Received | BN16: Yes | BW16: Pending | CB16: SRMP 2023-24 | CC16: Yes | CD16: Yes | CI16: =TEXT(M16,"MMM'YY") -> Feb'24 | CJ16: st | CK16: Yes | CL16: Yes | CM16: Administrative Approval/3203/SL01/2025-2026/141407
A17: 141 | B17: Within 2 Km from DBM English Medium School on either side on Parner to Pune Highway (SH) | C17: SANDIP BHASKAR NIKAM | D17: Ahmednagar West RSA | E17: 1976 | F17: 7875162400 | G17: D2 | H17: A | I17: RO | J17: RO A Site-Corpu | K17: R/2023/IN005327/MAH/000515/3203/00154 | L17: 2023-24 | M17: 45357 | N17: =+TODAY()-M17 -> 820 | O17: =+IF(N17<180,"0-6M",IF(N17<365,"6-12M",IF(N17<730,"1-2Y",IF(N17<1095,"2-3Y",IF(N17<1460,"3-4Y",IF(N17<1825,"4-5Y",IF(N17>1825,">5Y"))))))) -> 2-3Y | P17: AHMADNAGAR | Q17: PHP ( ST ) | R17: Group 1: Owned land | S17: 20 | T17: 80 | U17: =+S17+T17 -> 100 | W17: Yes | X17: Yes | Z17: Approved | AC17: Yes | AD17: =+AL17 -> 46113 | AE17: =+AS17 -> 46174 | AF17: Yes | AG17: NA | AH17: NA | AI17: Yes | AJ17: Yes | AK17: Available | AL17: 46113 | AM17: Yes | AN17: Yes | AO17: Sent | AP17: No | AS17: 46174 | AT17: Yes | AU17: Yes | AV17: NA | AW17: NA | AX17: Yes | AY17: Received | AZ17: Received | BA17: Received | BB17: Received | BC17: NA | BD17: NA | BE17: Received | BF17: Received | BG17: Received | BH17: Yes | BI17: 46113 | BJ17: 46174 | BK17: Yes | BL17: Received | BW17: Pending | CB17: SRMP 2023-24 | CC17: Yes | CD17: Yes | CI17: =TEXT(M17,"MMM'YY") -> Mar'24 | CJ17: st | CK17: Yes | CL17: Yes | CM17: Administrative Approval/3203/SL01/2025-2026/130023
A18: 157 | B18: From Bahul to Sablewadi on LHS on NH (Chakan-Shikrapur Road) | C18: PRAKASH SHANKAR LIMBHORE | D18: Pune Wagholi RSA | E18: 1842 | F18: 8668477069 | G18: D1 | H18: B | I18: RO | J18: RO B Site | K18: R/2024/IN002040/MAH/000089/3203/00004 | L18: 2023-24 | M18: 45456 | N18: =+TODAY()-M18 -> 721 | O18: =+IF(N18<180,"0-6M",IF(N18<365,"6-12M",IF(N18<730,"1-2Y",IF(N18<1095,"2-3Y",IF(N18<1460,"3-4Y",IF(N18<1825,"4-5Y",IF(N18>1825,">5Y"))))))) -> 1-2Y | P18: PUNE | Q18: OPEN | R18: Group 1: Owned land | S18: 40 | T18: 181 | U18: =+S18+T18 -> 221 | W18: Yes | X18: Yes | Y18: =+AP18 -> Yes | Z18: NA | AD18: =+AL18 -> 46023 | AE18: =+AS18 -> 46174 | AF18: Yes | AG18: NA | AH18: NA | AI18: Not Required | AJ18: Not Required | AK18: Yes(P) | AL18: 46023 | AM18: Yes | AN18: Yes | AO18: Approved | AP18: Yes | AQ18: 4337666 | AS18: 46174 | AT18: Yes | AU18: Yes | AV18: NA | AW18: No | AX18: Yes | AY18: yes | AZ18: Yes | BA18: Yes | BB18: Yes | BC18: Yes | BD18: Yes | BE18: NA | BF18: NA | BG18: Received | BH18: Yes | BI18: 46174 | BJ18: 46174 | BK18: Yes | BL18: Received | BM18: NA | BN18: NA | BO18: Not Required | BW18: Pending | CB18: SRMP 2023-24 | CC18: Yes | CD18: Yes | CH18: Yes | CI18: =TEXT(M18,"MMM'YY") -> Jun'24 | CJ18: Open | CK18: Yes | CL18: Yes
A19: 161 | B19: From Km Stone 8 to Km Stone 12 on Ahmednagar-Daund NH | C19: AMRUTA VISHAL LOTAKE | D19: Ahmednagar West RSA | E19: 1716 | F19: 9273739191 | G19: D1 | H19: B | I19: RO | J19: RO B Site | K19: R/2024/IN002247/MAH/000179/3203/00014 | L19: 2023-24 | M19: 45458 | N19: =+TODAY()-M19 -> 719 | O19: =+IF(N19<180,"0-6M",IF(N19<365,"6-12M",IF(N19<730,"1-2Y",IF(N19<1095,"2-3Y",IF(N19<1460,"3-4Y",IF(N19<1825,"4-5Y",IF(N19>1825,">5Y"))))))) -> 1-2Y | P19: AHMADNAGAR | Q19: OPEN | R19: Group 1: Owned land | S19: 35 | T19: 120 | U19: =+S19+T19 -> 155 | W19: Yes | X19: Yes | Y19: =+AP19 -> Yes | Z19: NA | AD19: =+AL19 -> 46143 | AE19: =+AS19 -> 46174 | AF19: Yes | AG19: NA | AH19: NA | AI19: Not Required | AJ19: Not Required | AL19: 46143 | AM19: Yes | AN19: Yes | AO19: Approved | AP19: Yes | AQ19: 4337973 | AS19: 46174 | AT19: Yes | AU19: Yes | AV19: NA | AW19: NA | AX19: Yes | AY19: Received | AZ19: Yes | BA19: Received | BB19: Received | BC19: NA | BD19: NA | BE19: Received | BF19: Received | BG19: Received | BH19: Yes | BI19: 46174 | BJ19: 46199 | BK19: Yes | BL19: Received | BM19: NA | BN19: NA | BO19: Not Required | BW19: Pending | CB19: SRMP 2023-24 | CC19: Yes | CD19: Yes | CI19: =TEXT(M19,"MMM'YY") -> Jun'24 | CJ19: Open | CK19: Yes | CL19: Yes
A20: 200 | B20: From Pingali Budruk To Gondawale Budruk on RHS on Satara Pandharpur Road | C20: AKSHAYKUMAR RAOSAHEB BABAR | D20: Satara East RSA | E20: 1988 | F20: 9765191946 | G20: D1 | H20: B | I20: RO | J20: RO B Site | K20: R/2024/IN002500/MAH/000244/3203/00072 | L20: 2023-24 | M20: 45462 | N20: =+TODAY()-M20 -> 715 | O20: =+IF(N20<180,"0-6M",IF(N20<365,"6-12M",IF(N20<730,"1-2Y",IF(N20<1095,"2-3Y",IF(N20<1460,"3-4Y",IF(N20<1825,"4-5Y",IF(N20>1825,">5Y"))))))) -> 1-2Y | P20: SATARA | Q20: OPEN | R20: Group 1: Owned land | S20: 40 | T20: 110 | U20: =+S20+T20 -> 150 | W20: Yes | X20: Yes | Y20: =+IF(AO20="Approved","Yes",AS20) -> Yes | Z20: NA | AD20: =+AL20 -> 46204 | AE20: =+AS20 -> 46174 | AF20: Yes | AI20: Not Required | AJ20: Not Required | AK20: Available | AL20: 46204 | AM20: 46478 | AN20: Yes | AO20: Approved | AP20: Yes | AQ20: 4338611 | AR20: NHAI Access Pending | AS20: 46174 | AT20: Yes | AU20: Yes | AV20: NA | AW20: NA | AX20: Yes | AY20: Received | AZ20: Received | BA20: Received | BB20: Applied | BC20: Received | BD20: NA | BE20: NA | BF20: NA | BG20: Received | BH20: Yes | BI20: 46143 | BJ20: 46174 | BK20: Yes | BL20: Received | BM20: NA | BN20: NA | BO20: Not Required | BW20: Pending | CB20: SRMP 2023-24 | CC20: Yes | CI20: =TEXT(M20,"MMM'YY") -> Jun'24 | CJ20: Open
A21: 233 | B21: Within 3km From Jawakhede Khalsa Primary Health Sub Centre Towards Miri on Miri-Tisgaon Road (MDR) | C21: CHARUDATTA UDDHAVRAO WAGH | D21: Ahmednagar West RSA | E21: 2106 | F21: 9881916750 | G21: E | H21: B | I21: KSK | J21: KSK-B w/o Reco | K21: R/2024/IN004699/MAH/000470/3203/00129 | L21: 2023-24 | M21: 45699 | N21: =+TODAY()-M21 -> 478 | O21: =+IF(N21<180,"0-6M",IF(N21<365,"6-12M",IF(N21<730,"1-2Y",IF(N21<1095,"2-3Y",IF(N21<1460,"3-4Y",IF(N21<1825,"4-5Y",IF(N21>1825,">5Y"))))))) -> 1-2Y | P21: AHMADNAGAR | Q21: OPEN | R21: Group 1: Owned land | S21: 28 | T21: 80 | U21: =+S21+T21 -> 108 | W21: Yes | X21: Yes | Z21: NA | AD21: =+AL21 -> 46143 | AE21: =+AS21 -> 46174 | AF21: Yes | AG21: NA | AH21: NA | AI21: Not Required | AJ21: Not Required | AL21: 46143 | AM21: Yes | AN21: Yes | AO21: Sent | AP21: No | AR21: LSR received | AS21: 46174 | AT21: Yes | AU21: Yes | AV21: NA | AW21: NA | AX21: Yes | AY21: Received | AZ21: Applied | BA21: Received | BB21: Applied | BC21: NA | BD21: NA | BE21: Received | BF21: Received | BG21: In Process | BH21: Yes | BI21: 46174 | BJ21: 46174 | BK21: Yes | BL21: Received | BM21: NA | BN21: NA | BO21: Not Required | BW21: Pending | CB21: SRMP 2023-24 | CC21: Yes | CD21: Yes | CI21: =TEXT(M21,"MMM'YY") -> Feb'25 | CJ21: Open | CK21: Yes | CL21: Yes | CM21: Administrative Approval/3203/SL01/2026-2027/18664
A22: 253 | B22: From Talegaon Damdhere to Dhanore within 2km on SH (Talegaon Dhamdere - Pimpri Sandas Road) | C22: MANOHAR VISHNU DHAMDHERE | D22: Pune Wagholi RSA | E22: 1783 | F22: 9921224142 | G22: D2 | H22: B | I22: RO | J22: RO B Site | K22: R/2025/IN000578/MAH/000077/3203/00018 | L22: 2023-24 | M22: 45964 | N22: =+TODAY()-M22 -> 213 | O22: =+IF(N22<180,"0-6M",IF(N22<365,"6-12M",IF(N22<730,"1-2Y",IF(N22<1095,"2-3Y",IF(N22<1460,"3-4Y",IF(N22<1825,"4-5Y",IF(N22>1825,">5Y"))))))) -> 6-12M | P22: Pune | Q22: OPEN | R22: Group 1: Owned land | S22: 30 | T22: 77 | U22: =+S22+T22 -> 107 | W22: Yes | X22: Yes | Z22: NA | AC22: Yes | AD22: =+AL22 -> 46143 | AE22: =+AS22 -> 46174 | AF22: Yes | AG22: NA | AH22: NA | AI22: Not Required | AJ22: Not Required | AK22: Available | AL22: 46143 | AM22: Yes | AN22: Yes | AO22: Approved | AP22: Yes | AQ22: 4338612 | AS22: 46174 | AT22: Yes | AU22: yes | AV22: NA | AW22: no | AX22: Yes | AY22: Yes | AZ22: yes | BA22: yes | BB22: Received | BC22: Yes | BD22: Yes | BE22: NA | BF22: NA | BG22: Received | BH22: WIP | BI22: 46167 | BJ22: 46199 | BK22: Yes | BL22: Received | BW22: Pending | CB22: SRMP 2023-24 | CC22: Yes | CD22: Yes | CI22: =TEXT(M22,"MMM'YY") -> Nov'25 | CJ22: Open | CK22: Yes | CL22: Yes
A23: 120 | B23: On RHS From Lohare to Talegaon Dighe on Talegaon Dighe-Loni NH | C23: BHAGWAN RAMESH MUTADAK | D23: Shirdi RSA | E23: 1881 | F23: 9260271806 | G23: D1 | H23: B | I23: RO | J23: RO B Site | K23: R/2023/IN003357/MAH/000374/3203/00115 | L23: 2023-24 | M23: 45315 | N23: =+TODAY()-M23 -> 862 | O23: =+IF(N23<180,"0-6M",IF(N23<365,"6-12M",IF(N23<730,"1-2Y",IF(N23<1095,"2-3Y",IF(N23<1460,"3-4Y",IF(N23<1825,"4-5Y",IF(N23>1825,">5Y"))))))) -> 2-3Y | P23: AHMADNAGAR | Q23: OBC | R23: Group 1: Owned land | S23: 40 | T23: 120 | U23: =+S23+T23 -> 160 | W23: Yes | X23: Yes | Y23: =+AP23 -> Yes | Z23: NA | AD23: =+AL23 -> 46174 | AE23: =+AS23 -> 46204 | AF23: Yes | AG23: NA | AH23: NA | AI23: Not Required | AJ23: Not Required | AL23: 46174 | AN23: Yes | AO23: Approved | AP23: Yes | AQ23: 4337686 | AS23: 46204 | AT23: Yes | AU23: Yes | AV23: NA | AW23: NA | AX23: Yes | AY23: Recieved | AZ23: Applied | BA23: Recieved | BB23: Applied | BC23: Recived | BD23: NA | BE23: Recived | BF23: Recived | BG23: Received | BH23: WIP | BI23: 46234 | BJ23: 46265 | BK23: Yes | BL23: To be applied | BM23: NA | BN23: NA | BO23: Not Required | BW23: Pending | CB23: SRMP 2023-24 | CC23: Yes | CD23: Yes | CI23: =TEXT(M23,"MMM'YY") -> Jan'24 | CJ23: OBC | CK23: Yes | CL23: Yes
A24: 195 | B24: Dehu Phata to Moshi Chowk on RHS on Dehu - Alandi Road | C24: VINOD MARUTI PARANDE | D24: Pimpri Chinchwad RSA | E24: 1949 | F24: 9881999678 | G24: A | H24: B | I24: RO | J24: RO B Site | K24: R/2024/IN002478/MAH/000232/3203/00061 | L24: 2023-24 | M24: 45462 | N24: =+TODAY()-M24 -> 715 | O24: =+IF(N24<180,"0-6M",IF(N24<365,"6-12M",IF(N24<730,"1-2Y",IF(N24<1095,"2-3Y",IF(N24<1460,"3-4Y",IF(N24<1825,"4-5Y",IF(N24>1825,">5Y"))))))) -> 1-2Y | P24: PUNE | Q24: OPEN | R24: Group 2: Firm Offer | S24: 150 | T24: 50 | U24: =+S24+T24 -> 200 | W24: Yes | X24: Yes | Y24: =+AP24 -> Yes | Z24: NA | AA24: Yes | AB24: Yes | AD24: 46204 | AE24: 46204 | AF24: Yes | AI24: Not Required | AJ24: Not Required | AK24: Yes(P) | AL24: 46539 | AN24: Yes | AO24: Approved | AP24: Yes | AQ24: 4337491 | AR24: There is complaint related to Land, Mojani has been cancelled. Matter is subjudiced. Court orders are in our favor. PCMC commissioner has suspended the NOC temporarily.Meeting planned in We expect ervoke of suspension and remojani by Feb'26. | AS24: =+AL24+31 -> 46570 | AT24: Yes | AU24: Yes | AV24: There is court case Going on at Site, hence Commissioning will get delayted. NOC and Mojani has been canc elled by administration based on complaint received for the locaiton | AW24: NA | AX24: Yes | AY24: Received | AZ24: Received | BA24: Received | BB24: Not Required | BC24: Received | BD24: Received | BE24: NA | BF24: NA | BG24: Received | BH24: Yes | BI24: 46266 | BJ24: 46266 | BK24: Yes | BL24: Received | BM24: NA | BN24: NA | BO24: Not Required | BW24: Pending | CB24: SRMP 2023-24 | CC24: Yes | CI24: =TEXT(M24,"MMM'YY") -> Jun'24 | CJ24: Open | CL24: Yes
A25: 208 | B25: Within 4km from Within 4 km from M.M.Nirhali College, Pathardi towards baramat on Baramati-Amrapur SH | C25: VAISHALI RAMESH BARDE | D25: Ahmednagar West RSA | E25: 1837 | F25: 9763122772 | G25: D2 | H25: B | I25: RO | J25: RO B Site | K25: R/2024/IN002781/MAH/000309/3203/00093 | L25: 2023-24 | M25: 45479 | N25: =+TODAY()-M25 -> 698 | O25: =+IF(N25<180,"0-6M",IF(N25<365,"6-12M",IF(N25<730,"1-2Y",IF(N25<1095,"2-3Y",IF(N25<1460,"3-4Y",IF(N25<1825,"4-5Y",IF(N25>1825,">5Y"))))))) -> 1-2Y | P25: AHMADNAGAR | Q25: OBC | R25: Group 1: Owned land | S25: 30 | T25: 70 | U25: =+S25+T25 -> 100 | W25: Yes | X25: Yes | Y25: =+AP25 -> Yes | Z25: NA | AD25: =+AL25 -> 46174 | AE25: =+AS25 -> 46204 | AF25: Yes | AG25: NA | AH25: NA | AI25: Not Required | AJ25: Not Required | AL25: 46174 | AM25: Yes | AN25: Yes | AO25: Approved | AP25: Yes | AQ25: 4337805 | AS25: 46204 | AT25: Yes | AU25: Yes | AV25: NA | AW25: NA | AX25: Yes | AY25: Received | AZ25: Yes | BA25: Received | BB25: Yet to apply | BC25: NA | BD25: NA | BE25: Received | BF25: Received | BG25: Received | BH25: No | BI25: 46291 | BJ25: 46321 | BK25: Yes | BL25: Received | BM25: NA | BN25: NA | BO25: Not Required | BW25: Pending | CB25: SRMP 2023-24 | CC25: Yes | CD25: Yes | CI25: =TEXT(M25,"MMM'YY") -> Jul'24 | CJ25: OBC | CK25: Yes | CL25: Yes
A26: 22 | B26: ON NH-4 BETWEEN KM STONE 760 TO 755 LHS OF PUNE TO SATARA ROAD | C26: Yashodhan Shinde | D26: Satara West RSA | E26: 2018-129 | F26: 9881321999 | G26: D1 | H26: B | I26: RO | J26: RO B Site | K26: M/2018/IN002023/MAH/000207/3203/00064 | L26: 2018-19 | M26: 43536 | N26: =+TODAY()-M26 -> 2641 | O26: =+IF(N26<180,"0-6M",IF(N26<365,"6-12M",IF(N26<730,"1-2Y",IF(N26<1095,"2-3Y",IF(N26<1460,"3-4Y",IF(N26<1825,"4-5Y",IF(N26>1825,">5Y"))))))) -> >5Y | P26: SATARA | Q26: OPEN | R26: Group 2: Firm Offer | S26: 40 | T26: 110 | U26: =+S26+T26 -> 150 | W26: Yes | X26: Yes | Y26: =+AP26 -> Yes | Z26: NA | AD26: =+AL26 -> 46204 | AE26: =+AS26 -> 46235 | AF26: Yes | AG26: NA | AH26: NA | AI26: Not Required | AJ26: Not Required | AL26: 46204 | AM26: Yes | AN26: Yes | AO26: Approved | AP26: Yes | AR26: LSR Awaited | AS26: 46235 | AT26: YES | AU26: YES | AV26: NA | AW26: NA | AX26: YES | AY26: Received | AZ26: Received | BA26: Applied | BB26: Applied | BC26: Received | BD26: NA | BE26: NA | BF26: NA | BG26: In process | BH26: WIP | BI26: 46229 | BJ26: 46260 | BK26: Moujani Awaited | BL26: Yet to Apply | BM26: NA | BN26: NA | BO26: Not Required | BW26: Pending | CB26: SRMP 2018-19 | CC26: Yes | CD26: Yes | CI26: =TEXT(M26,"MMM'YY") -> Mar'19 | CJ26: Open | CK26: Yes | CL26: Yes
A27: 74 | B27: Within 2 km from Chapadgaon Junction towards koregaon on Chapadgaon-Koregaon Road MDR Tal- Karjat | C27: DNYANESHWAR RAMDAS SHINDE | D27: Ahmednagar West RSA | E27: 2095 | F27: 9960927710 | G27: E | H27: B | I27: KSK | J27: KSK-B w/o Reco | K27: R/2023/IN001195/MAH/000083/3203/00024 | L27: 2023-24 | M27: 45261 | N27: =+TODAY()-M27 -> 916 | O27: =+IF(N27<180,"0-6M",IF(N27<365,"6-12M",IF(N27<730,"1-2Y",IF(N27<1095,"2-3Y",IF(N27<1460,"3-4Y",IF(N27<1825,"4-5Y",IF(N27>1825,">5Y"))))))) -> 2-3Y | P27: AHMADNAGAR | Q27: OPEN | R27: Group 1: Owned land | S27: 38 | T27: 70 | U27: =+S27+T27 -> 108 | W27: Yes | X27: Yes | Z27: NA | AD27: =+AL27 -> 46204 | AE27: =+AS27 -> 46235 | AF27: Yes | AG27: NA | AH27: NA | AI27: Not Required | AJ27: Not Required | AL27: 46204 | AM27: Yes | AN27: Yes | AO27: To be Initiated | AP27: No | AR27: LSR Awaited, land change case | AS27: 46235 | AT27: Yes | AU27: Yes | AV27: NA | AW27: NA | AX27: Yes | AY27: Received | AZ27: Applied | BA27: Applied | BB27: Not Required | BC27: NA | BD27: NA | BE27: Applied | BF27: Applied | BG27: In process | BH27: No | BI27: 46291 | BJ27: 46321 | BK27: Yes | BL27: To be applied | BM27: NA | BN27: NA | BO27: Not Required | BW27: Pending | CB27: SRMP 2023-24 | CC27: Yes | CD27: Yes | CI27: =TEXT(M27,"MMM'YY") -> Dec'23 | CJ27: Open | CK27: Yes | CL27: Yes
A28: 162 | B28: Within 3 KM from Varunji Phata Karad Towards Chiplun On Karad Chiplun Road | C28: NITIN DINKAR PATIL | D28: Satara West RSA | E28: 1608 | F28: 8805000393 | G28: D1 | H28: B | I28: RO | J28: RO B Site | K28: R/2024/IN002258/MAH/000183/3203/00018 | L28: 2023-24 | M28: 45458 | N28: =+TODAY()-M28 -> 719 | O28: =+IF(N28<180,"0-6M",IF(N28<365,"6-12M",IF(N28<730,"1-2Y",IF(N28<1095,"2-3Y",IF(N28<1460,"3-4Y",IF(N28<1825,"4-5Y",IF(N28>1825,">5Y"))))))) -> 1-2Y | P28: SATARA | Q28: OPEN | R28: Group 1: Owned land | S28: 80 | T28: 90 | U28: =+S28+T28 -> 170 | W28: Yes | X28: Yes | Y28: =+IF(AO28="Approved","Yes",AS28) -> 46235 | Z28: NA | AD28: =+AL28 -> 46204 | AE28: =+AS28 -> 46235 | AF28: Yes | AG28: NA | AH28: NA | AI28: Not Required | AJ28: Not Required | AL28: 46204 | AM28: Yes | AN28: Yes | AO28: To be Initiated | AP28: No | AR28: LSR Awaited | AS28: 46235 | AT28: YES | AU28: YES | AV28: NA | AW28: NA | AX28: YES | AY28: Received | AZ28: Applied | BA28: Received | BB28: Applied | BC28: Received | BD28: NA | BE28: NA | BF28: NA | BG28: In Process | BH28: WIP | BI28: 46229 | BJ28: 46260 | BK28: Yes | BL28: Received | BM28: NA | BN28: NA | BO28: Not Required | BW28: Pending | BZ28: BS | CB28: SRMP 2023-24 | CC28: Yes | CD28: Yes | CI28: =TEXT(M28,"MMM'YY") -> Jun'24 | CJ28: Open | CK28: Yes | CL28: Yes
A29: 201 | B29: Within 5 Km from Tasawde Toll plaza towards Karad On RHS of Pune to Satara NH | C29: SWATI VIKRAM SHIVDAS | D29: Satara West RSA | E29: 1581 | F29: 9822303957 | G29: D1 | H29: A | I29: RO | J29: RO A Site-Corpu | K29: R/2024/IN002508/MAH/000251/3203/00075 | L29: 2023-24 | M29: 45462 | N29: =+TODAY()-M29 -> 715 | O29: =+IF(N29<180,"0-6M",IF(N29<365,"6-12M",IF(N29<730,"1-2Y",IF(N29<1095,"2-3Y",IF(N29<1460,"3-4Y",IF(N29<1825,"4-5Y",IF(N29>1825,">5Y"))))))) -> 1-2Y | P29: SATARA | Q29: SC | R29: Group 1: Owned land | S29: 40 | T29: 110 | U29: =+S29+T29 -> 150 | W29: Yes | X29: Yes | Z29: Yet to Initiate | AD29: =+AL29 -> 46204 | AE29: =+AS29 -> 46235 | AF29: Yes | AG29: NA | AH29: NA | AI29: Yes | AJ29: Pending | AL29: 46204 | AM29: Yes | AN29: Pending | AO29: To be Initiated | AP29: No | AR29: LSR Awaited | AS29: 46235 | AT29: YES | AU29: YES | AV29: NA | AW29: NA | AX29: YES | AY29: Received | AZ29: Applied | BA29: Received | BB29: Applied | BC29: Received | BD29: NA | BE29: NA | BF29: NA | BG29: In Process | BH29: No | BI29: 46229 | BJ29: 46291 | BK29: Yes | BL29: Received | BN29: Pending | BW29: Pending | BZ29: BS | CA29: Received | CB29: SRMP 2023-24 | CC29: Yes | CD29: Yes | CI29: =TEXT(M29,"MMM'YY") -> Jun'24 | CJ29: SC | CK29: Yes | CL29: Yes
A30: 265 | B30: From Sawarchol to Nimgoan bk. on Sangamer-Kotul SH | C30: HOUSHIRAM MARUTI MECHKAR | D30: Shirdi RSA | E30: 104 | F30: 8805752023 | G30: D2 | H30: A | I30: RO | J30: RO A Site-Corpu | K30: R/2025/IN000872/MAH/000099/3203/00030 | L30: 2023-24 | M30: 46099 | N30: =+TODAY()-M30 -> 78 | O30: =+IF(N30<180,"0-6M",IF(N30<365,"6-12M",IF(N30<730,"1-2Y",IF(N30<1095,"2-3Y",IF(N30<1460,"3-4Y",IF(N30<1825,"4-5Y",IF(N30>1825,">5Y"))))))) -> 0-6M | P30: AHMADNAGAR | Q30: ST | R30: Group 1: Owned land | S30: 25 | T30: 75 | U30: =+S30+T30 -> 100 | W30: Yes | X30: Yes | Z30: Yet to Initiate | AD30: 46204 | AE30: 46235 | AF30: Yes | AI30: In Process | AJ30: Pending | AL30: 46204 | AM30: Pending | AN30: Pending | AO30: To be Initiated | AR30: LSR Awaited | AS30: 46235 | AT30: Yes | AU30: Yes | AV30: LOI given in March 26 and need to see candidate progress for some time to conclude. | AW30: NA | AX30: Yes | AY30: Recieved | AZ30: Yet to Apply | BA30: Yet to Apply | BB30: Yet to Apply | BC30: Yet to Apply | BD30: NA | BE30: Yet to Apply | BF30: Yet to Apply | BG30: In Process | BH30: No | BI30: 46387 | BJ30: 46476 | BK30: Moujani Awaited | BL30: Yet to Apply | BW30: Pending | BZ30: AG on 14.05.2026 | CA30: Ellen and Gosavi on 180526 | CB30: SRMP 2023-24 | CC30: Yes | CI30: =TEXT(M30,"MMM'YY") -> Mar'26 | CJ30: st
A31: 66 | B31: WITH IN 5 KM FROM MORGAON ON LHS OF MORGAON -BARAMATI ROAD , | C31: PURUSHOTTAM KADAM | D31: Pune Tathawade RSA | E31: 54 | F31: 9665080752 | G31: D2 | H31: A | I31: RO | J31: RO A Site-Corpu | K31: M/2023/IN000132/MAH/000015/3203/00009 | L31: 2018-19 | M31: 45047 | N31: =+TODAY()-M31 -> 1130 | O31: =+IF(N31<180,"0-6M",IF(N31<365,"6-12M",IF(N31<730,"1-2Y",IF(N31<1095,"2-3Y",IF(N31<1460,"3-4Y",IF(N31<1825,"4-5Y",IF(N31>1825,">5Y"))))))) -> 3-4Y | P31: PUNE | Q31: SC | R31: Group 1: Owned land | S31: 30 | T31: 90 | U31: =+S31+T31 -> 120 | W31: Yes | X31: Yes | Y31: =+IF(AO31="Approved","Yes",AS31) -> 46266 | Z31: Approved | AD31: =+AL31 -> 46204 | AE31: =+AS31 -> 46266 | AF31: Yes | AG31: NA | AH31: NA | AI31: Yes | AJ31: Yes | AL31: 46204 | AM31: Yes | AO31: Sent | AP31: No | AS31: 46266 | AT31: Yes | AU31: Yes | AV31: PWD NOC pending | AW31: NA | AX31: Yes | AY31: Yes | AZ31: Yes | BA31: Received | BB31: Applied | BC31: Received | BD31: Received | BE31: NA | BF31: NA | BG31: Received | BH31: WIP | BI31: 46204 | BJ31: 46327 | BK31: Yes | BL31: Received | BN31: Pending | BW31: Pending | CB31: SRMP 2018-19 | CC31: Yes | CD31: Yes | CI31: =TEXT(M31,"MMM'YY") -> May'23 | CJ31: SC | CK31: Yes | CL31: Yes | CM31: Administrative Approval/3203/SL01/2025-2026/172925
A32: 90 | B32: Within 3 Km from Ghodegaon Sonai Chowk towards Ahmednagar on Pune-Aurangabad NH | C32: PRITI ATMARAM PAWAR | D32: Ahmednagar East RSA | E32: 96 | F32: 8668904185 | G32: D1 | H32: A | I32: RO | J32: RO A Site-Corpu | K32: R/2023/IN001620/MAH/000160/3203/00058 | L32: 2023-24 | M32: 45274 | N32: =+TODAY()-M32 -> 903 | O32: =+IF(N32<180,"0-6M",IF(N32<365,"6-12M",IF(N32<730,"1-2Y",IF(N32<1095,"2-3Y",IF(N32<1460,"3-4Y",IF(N32<1825,"4-5Y",IF(N32>1825,">5Y"))))))) -> 2-3Y | P32: AHMADNAGAR | Q32: ST | R32: Group 1: Owned land | S32: 40 | T32: 135 | U32: =+S32+T32 -> 175 | W32: Yes | X32: Yes | Y32: =+IF(AO32="Approved","Yes",AS32) -> 46266 | Z32: Yet to Initiate | AD32: =+AL32 -> 46204 | AE32: =+AS32 -> 46266 | AF32: Yes | AG32: NA | AH32: NA | AI32: Yes | AJ32: Yes | AL32: 46204 | AM32: Yes | AN32: Pending | AO32: Sent | AP32: No | AS32: 46266 | AT32: Yes | AU32: Yes | AV32: NA | AW32: NA | AX32: Yes | AY32: Received | AZ32: Applied | BA32: Received | BB32: Applied | BC32: Received | BD32: NA | BE32: Received | BF32: Received | BG32: Received | BH32: WIP | BI32: 46204 | BJ32: 46266 | BK32: Yes | BL32: Received | BN32: Pending | BW32: Pending | CB32: SRMP 2023-24 | CC32: Yes | CD32: Yes | CI32: =TEXT(M32,"MMM'YY") -> Dec'23 | CJ32: st | CK32: Yes | CL32: Yes | CM32: Administrative Approval/3203/SL01/2026-2027/18041
A33: 93 | B33: From Village Walwane to Village Raytale on Supe Sarolakasar Road SH | C33: AKASH SHANTILAL PATHARE | D33: Ahmednagar West RSA | E33: 1592 | F33: 8530744612 | G33: D2 | H33: B | I33: RO | J33: RO B Site | K33: R/2023/IN001673/MAH/000169/3203/00062 | L33: 2023-24 | M33: 45275 | N33: =+TODAY()-M33 -> 902 | O33: =+IF(N33<180,"0-6M",IF(N33<365,"6-12M",IF(N33<730,"1-2Y",IF(N33<1095,"2-3Y",IF(N33<1460,"3-4Y",IF(N33<1825,"4-5Y",IF(N33>1825,">5Y"))))))) -> 2-3Y | P33: AHMADNAGAR | Q33: OBC | R33: Group 1: Owned land | S33: 25 | T33: 80 | U33: =+S33+T33 -> 105 | W33: Yes | X33: Yes | Z33: NA | AD33: 46235 | AE33: 46266 | AF33: Yes | AG33: NA | AH33: NA | AI33: Not Required | AJ33: Not Required | AL33: 46266 | AM33: Yes | AN33: Yes | AO33: To be Initiated | AP33: No | AR33: LSR Awaited | AS33: 46296 | AT33: Yes | AU33: Yes | AV33: NA | AW33: NA | AX33: Yes | AY33: Received | AZ33: Applied | BA33: Applied | BB33: Yet to Apply | BC33: NA | BD33: NA | BE33: Applied | BF33: Applied | BG33: In process | BH33: No | BI33: 46291 | BJ33: 46321 | BK33: Yes | BL33: To be applied | BM33: NA | BN33: NA | BO33: Not Required | BW33: Pending | CB33: SRMP 2023-24 | CC33: Yes | CD33: Yes | CI33: =TEXT(M33,"MMM'YY") -> Dec'23 | CJ33: OBC | CK33: Yes | CL33: Yes
A34: 109 | B34: From Village Pargaon Shingave to Village Manjarwadi on RHS on SH | C34: RAMKRUSHNA RAMCHANDRA JANBHOR | D34: Pune Wagholi RSA | E34: 2076 | F34: 9860520267 | G34: D2 | H34: B | I34: RO | J34: RO B Site | K34: R/2023/IN003093/MAH/000338/3203/00098 | L34: 2023-24 | M34: 45309 | N34: =+TODAY()-M34 -> 868 | O34: =+IF(N34<180,"0-6M",IF(N34<365,"6-12M",IF(N34<730,"1-2Y",IF(N34<1095,"2-3Y",IF(N34<1460,"3-4Y",IF(N34<1825,"4-5Y",IF(N34>1825,">5Y"))))))) -> 2-3Y | P34: PUNE | Q34: OPEN | R34: Group 1: Owned land | S34: 40 | T34: 80 | U34: =+S34+T34 -> 120 | W34: Yes | X34: Yes | Y34: =+IF(AO34="Approved","Yes",AS34) -> Yes | Z34: NA | AD34: 46235 | AE34: 46266 | AF34: Yes | AG34: NA | AH34: NA | AI34: Not Required | AJ34: Not Required | AL34: 46266 | AM34: Yes | AN34: Yes | AO34: Approved | AP34: Yes | AQ34: 4338613 | AR34: PWD junction issue. Land comes within 300 Mt of junction. PWQD file sent for relaxation approval | AS34: 46296 | AT34: Yes | AU34: Yes but in next FY | AV34: PWD junction issue. Land comes within 300 Mt of junction. PWQD file sent for relaxation approval | AW34: No | AX34: Yes | AY34: Yes | AZ34: Yes | BA34: Yes | BB34: Applies | BC34: Yes | BD34: yes | BE34: NA | BF34: NA | BG34: Received | BH34: No | BI34: 46143 | BJ34: 46174 | BK34: Yes | BL34: Received | BM34: NA | BN34: NA | BO34: Not Required | BW34: Pending | CB34: SRMP 2023-24 | CC34: Yes | CD34: Yes | CI34: =TEXT(M34,"MMM'YY") -> Jan'24 | CJ34: Open | CK34: Yes | CL34: Yes
A35: 124 | B35: Moshi Chowk on Pune Nashik Road to Talwade Chowk on LHS on Dehu Alandi Road (within PCMC Limits) | C35: SACHIN PANDURANG BORATE | D35: Pimpri Chinchwad RSA | E35: 1672 | F35: 9356705562 | G35: A | H35: A | I35: RO | J35: RO A Site | K35: R/2023/IN003662/MAH/000405/3203/00125 | L35: 2023-24 | M35: 45323 | N35: =+TODAY()-M35 -> 854 | O35: =+IF(N35<180,"0-6M",IF(N35<365,"6-12M",IF(N35<730,"1-2Y",IF(N35<1095,"2-3Y",IF(N35<1460,"3-4Y",IF(N35<1825,"4-5Y",IF(N35>1825,">5Y"))))))) -> 2-3Y | P35: PUNE | Q35: OPEN | R35: Group 1: Owned land | S35: 150 | T35: 50 | U35: =+S35+T35 -> 200 | W35: Yes | X35: Yes | Y35: =+AP35 -> No | Z35: Approved | AD35: 46235 | AE35: 46266 | AF35: Yes | AG35: NA | AH35: NA | AI35: Yes | AJ35: Yes | AK35: Yes(P) | AL35: 46357 | AM35: Yes | AN35: Yes | AO35: Sent | AP35: No | AS35: 46296 | AT35: Yes | AU35: Yes | AV35: NA | AW35: NA | AX35: Yes | AY35: Received | AZ35: Received | BA35: Received | BB35: Not Required | BC35: Received | BD35: Received | BE35: NA | BF35: NA | BG35: Received | BH35: WIP | BI35: 46296 | BJ35: 46327 | BK35: Yes | BL35: Received | BN35: Yes | BW35: Pending | CB35: SRMP 2023-24 | CC35: Yes | CD35: Yes | CI35: =TEXT(M35,"MMM'YY") -> Feb'24 | CJ35: Open | CK35: Yes | CL35: Yes | CM35: Administrative Approval/3203/SL01/2026-2027/19224
A36: 173 | B36: From Kapurhol to Kikvi on RHS on NH (Pune-Bangalore Highway) | C36: SWAPNIL RAMDAS CHARWAD | D36: Pune Tathawade RSA | E36: 1712 | F36: 9766110001 | G36: D1 | H36: B | I36: RO | J36: RO B Site | K36: R/2024/IN002366/MAH/000196/3203/00030 | L36: 2023-24 | M36: 45460 | N36: =+TODAY()-M36 -> 717 | O36: =+IF(N36<180,"0-6M",IF(N36<365,"6-12M",IF(N36<730,"1-2Y",IF(N36<1095,"2-3Y",IF(N36<1460,"3-4Y",IF(N36<1825,"4-5Y",IF(N36>1825,">5Y"))))))) -> 1-2Y | P36: PUNE | Q36: OPEN | R36: Group 1: Owned land | S36: 40 | T36: 120 | U36: =+S36+T36 -> 160 | W36: Yes | X36: Yes | Y36: =+AP36 -> Yes | Z36: NA | AD36: =+AL36 -> 46204 | AE36: =+AS36 -> 46266 | AF36: Yes | AG36: NA | AH36: NA | AI36: Not Required | AJ36: Not Required | AL36: 46204 | AM36: Yes | AN36: Yes | AO36: Approved | AP36: Yes | AQ36: 4338053 | AS36: 46266 | AT36: Yes | AU36: Yes | AV36: Provisional NH NOC pending and SP NOC pending | AW36: NA | AX36: Yes | AY36: Yes | AZ36: Yes | BA36: Applied | BB36: Applied | BC36: Received | BD36: Received | BE36: NA | BF36: NA | BG36: Received | BH36: WIP | BI36: 46204 | BJ36: 46327 | BK36: Yes | BL36: Received | BM36: NA | BN36: NA | BO36: Not Required | BW36: Pending | CB36: SRMP 2023-24 | CC36: Yes | CD36: Yes | CI36: =TEXT(M36,"MMM'YY") -> Jun'24 | CJ36: Open | CK36: Yes | CL36: Yes
A37: 229 | B37: Bhose to Shelpimpalgaon on LHS on Chakan Shikrapur Road | C37: RAJABHAU MOTIRAM BANSODE | D37: Pimpri Chinchwad RSA | E37: 2030 | F37: 7030954444 | G37: D1 | H37: A | I37: RO | J37: RO A Site-Corpu | K37: R/2024/IN004518/MAH/000463/3203/00124 | L37: 2023-24 | M37: 45659 | N37: =+TODAY()-M37 -> 518 | O37: =+IF(N37<180,"0-6M",IF(N37<365,"6-12M",IF(N37<730,"1-2Y",IF(N37<1095,"2-3Y",IF(N37<1460,"3-4Y",IF(N37<1825,"4-5Y",IF(N37>1825,">5Y"))))))) -> 1-2Y | P37: PUNE | Q37: SC | R37: Group 1: Owned land | S37: 30 | T37: 120 | U37: =+S37+T37 -> 150 | W37: Yes | X37: Yes | Y37: =+IF(AO37="Approved","Yes",AS37) -> Yes | Z37: Approved | AA37: NA | AD37: =+AL37 -> 46023 | AE37: =+AS37 -> 46266 | AF37: Yes | AG37: NA | AH37: NA | AI37: Yes | AJ37: Yes | AK37: Yes(P) | AL37: 46023 | AM37: Yes | AN37: Yes | AO37: Approved | AP37: Yes | AS37: 46266 | AT37: Yes | AU37: Yes | AV37: NA | AW37: NA | AX37: Yes | AY37: Received | AZ37: Received | BA37: Received | BB37: Received | BC37: Received | BD37: Received | BE37: NA | BF37: NA | BG37: Received | BH37: Yes | BI37: 46266 | BJ37: 46296 | BK37: Yes | BL37: Received | BN37: Yes | BW37: Pending | CB37: SRMP 2023-24 | CC37: Yes | CD37: Yes | CI37: =TEXT(M37,"MMM'YY") -> Jan'25 | CJ37: SC | CK37: Yes | CL37: Yes | CM37: Administrative Approval/3203/SL01/2025-2026/130494
A38: 104 | B38: Within 3 Km From Dr Ambedkar Chowk (Kakadi) towards Korhale on RHS of Airport-Shirdi Road (MDR) | C38: YASRAJ HARISHCHANDRA BHUSHARI | D38: Shirdi RSA | E38: 2111 | F38: 9112735899 | G38: E | H38: A | I38: KSK | J38: KSK-A w/o Reco | K38: R/2023/IN002952/MAH/000313/3203/00092 | L38: 2023-24 | M38: 45307 | N38: =+TODAY()-M38 -> 870 | O38: =+IF(N38<180,"0-6M",IF(N38<365,"6-12M",IF(N38<730,"1-2Y",IF(N38<1095,"2-3Y",IF(N38<1460,"3-4Y",IF(N38<1825,"4-5Y",IF(N38>1825,">5Y"))))))) -> 2-3Y | P38: AHMADNAGAR | Q38: OBC | R38: Group 1: Owned land | S38: 30 | T38: 120 | U38: =+S38+T38 -> 150 | W38: Yes | X38: Yes | Y38: =+IF(AO38="Approved","Yes",AS38) -> Yes | Z38: Approved | AD38: 46266 | AE38: 46296 | AF38: Yes | AI38: Yes | AJ38: Yes | AL38: 46266 | AM38: Pending | AN38: Yes | AO38: Approved | AP38: Yes | AQ38: 4338490 | AR38: frontage is 30 M against PWD requirement of 35 Mt. | AS38: 46296 | AT38: Yes | AU38: Yes | AV38: NA | AW38: NA | AX38: Yes | AY38: Recieved | AZ38: Applied | BA38: Recieved | BB38: Applied | BC38: Recived | BD38: NA | BE38: Recived | BF38: Recived | BG38: Received | BH38: No | BI38: 46265 | BJ38: 46387 | BK38: Yes | BL38: Received | BN38: Pending | BW38: Pending | CB38: SRMP 2023-24 | CC38: Yes | CI38: =TEXT(M38,"MMM'YY") -> Jan'24 | CJ38: OBC
A39: 122 | B39: AT JEUR ON AHMEDNAGAR-AURANGABAD ROAD | C39: RANJANA RAJIV SALVE | D39: Ahmednagar East RSA | E39: 2018-766 | F39: 9309939919 | G39: D1 | H39: A | I39: RO | J39: RO A Site-Corpu | K39: M/2023/IN003549/MAH/000389/3203/00121 | L39: 2018-19 | M39: 45321 | N39: =+TODAY()-M39 -> 856 | O39: =+IF(N39<180,"0-6M",IF(N39<365,"6-12M",IF(N39<730,"1-2Y",IF(N39<1095,"2-3Y",IF(N39<1460,"3-4Y",IF(N39<1825,"4-5Y",IF(N39>1825,">5Y"))))))) -> 2-3Y | P39: AHMADNAGAR | Q39: SC | R39: Group 1: Owned land | S39: 30 | T39: 120 | U39: =+S39+T39 -> 150 | W39: Yes | X39: Yes | Z39: Yet to Initiate | AD39: 46266 | AE39: 46296 | AF39: Yes | AG39: NA | AH39: NA | AI39: Yes | AJ39: Pending | AL39: 46266 | AM39: Yes | AN39: Pending | AO39: To be Initiated | AP39: No | AR39: Negotiation Pending | AS39: 46296 | AT39: Yes | AU39: Yes | AV39: NA | AW39: NA | AX39: Yes | AY39: Received | AZ39: Yet to Apply | BA39: Received | BB39: Applied | BC39: Received | BD39: NA | BE39: Received | BF39: Received | BG39: Received | BH39: No | BI39: 46388 | BJ39: 46419 | BK39: Yes | BW39: Pending | BZ39: Received | CA39: Received | CB39: SRMP 2018-19 | CC39: Yes | CI39: =TEXT(M39,"MMM'YY") -> Jan'24 | CJ39: SC
A40: 132 | B40: Within 2 KM from Medha Bus Stand towards Satara on Mahabaleshwar Satara Road | C40: RUPALI KISAN SABLE | D40: Satara West RSA | E40: 97 | F40: 8788144518 | G40: D2 | H40: A | I40: RO | J40: RO A Site-Corpu | K40: R/2023/IN004334/MAH/000466/3203/00142 | L40: 2023-24 | M40: 45338 | N40: =+TODAY()-M40 -> 839 | O40: =+IF(N40<180,"0-6M",IF(N40<365,"6-12M",IF(N40<730,"1-2Y",IF(N40<1095,"2-3Y",IF(N40<1460,"3-4Y",IF(N40<1825,"4-5Y",IF(N40>1825,">5Y"))))))) -> 2-3Y | P40: SATARA | Q40: ST | R40: Group 1: Owned land | S40: 22 | T40: 90 | U40: =+S40+T40 -> 112 | W40: Yes | X40: Yes | Y40: =+IF(AO40="Approved","Yes",AS40) -> 46296 | Z40: Yet to Initiate | AD40: =+AL40 -> 46266 | AE40: =+AS40 -> 46296 | AF40: Yes | AG40: NA | AH40: NA | AI40: Yes | AJ40: Pending | AL40: 46266 | AM40: Pending | AN40: Pending | AO40: To be Initiated | AP40: No | AR40: LSR Awaited, Financially week | AS40: 46296 | AT40: YES | AU40: YES | AV40: NA | AW40: NA | AX40: YES | AY40: Received | AZ40: Applied | BA40: Applied | BB40: NA | BC40: Received | BD40: NA | BE40: NA | BF40: NA | BG40: In Process | BI40: 46291 | BJ40: 46352 | BK40: Yes | BL40: Received | BN40: Pending | BW40: Pending | BZ40: BS | CA40: Received | CB40: SRMP 2023-24 | CC40: Yes | CD40: Yes | CI40: =TEXT(M40,"MMM'YY") -> Feb'24 | CJ40: st | CK40: Yes | CL40: Yes
A41: 156 | B41: From km stone 56 to 58 on RHS on SH (Belhe -Jejuri road) | C41: CHETAN NAMDEV DESHMUKH | D41: Pune Wagholi RSA | E41: 1805 | F41: 8956677327 | G41: D2 | H41: B | I41: RO | J41: RO B Site | K41: R/2024/IN002109/MAH/000114/3203/00005 | L41: 2023-24 | M41: 45456 | N41: =+TODAY()-M41 -> 721 | O41: =+IF(N41<180,"0-6M",IF(N41<365,"6-12M",IF(N41<730,"1-2Y",IF(N41<1095,"2-3Y",IF(N41<1460,"3-4Y",IF(N41<1825,"4-5Y",IF(N41>1825,">5Y"))))))) -> 1-2Y | P41: PUNE | Q41: OPEN | R41: Group 1: Owned land | S41: 20 | T41: 84 | U41: =+S41+T41 -> 104 | W41: Yes | X41: Yes | Y41: =+IF(AO41="Approved","Yes",AS41) -> 46296 | Z41: NA | AD41: =+AL41 -> 46266 | AE41: =+AS41 -> 46296 | AF41: Yes | AG41: NA | AH41: NA | AI41: Not Required | AJ41: Not Required | AL41: 46266 | AM41: Yes | AN41: Yes | AO41: To be Initiated | AP41: No | AR41: LSR Awaited | AS41: 46296 | AT41: Yes | AU41: Yes | AV41: Commissionable | AW41: No | AX41: Yes | AY41: Yes | AZ41: No | BA41: Yes | BB41: Yet to Apply | BC41: Applied | BD41: Yes | BE41: NA | BF41: NA | BG41: Received | BH41: WIP | BI41: 46229 | BJ41: 46229 | BK41: Yes | BL41: Received | BM41: NA | BN41: NA | BO41: Not Required | BW41: Pending | CB41: SRMP 2023-24 | CC41: Yes | CD41: Yes | CI41: =TEXT(M41,"MMM'YY") -> Jun'24 | CJ41: Open | CK41: Yes | CL41: Yes
A42: 155 | B42: On LHS From Lohare to Talegaon Dighe on Talegaon Dighe-Loni NH | C42: GAURAV GORAKSHA SANAP | D42: Shirdi RSA | E42: 1618 | F42: 8693000910 | G42: D1 | H42: B | I42: RO | J42: RO B Site | K42: R/2024/IN002007/MAH/000078/3203/00001 | L42: 2023-24 | M42: 45456 | N42: =+TODAY()-M42 -> 721 | O42: =+IF(N42<180,"0-6M",IF(N42<365,"6-12M",IF(N42<730,"1-2Y",IF(N42<1095,"2-3Y",IF(N42<1460,"3-4Y",IF(N42<1825,"4-5Y",IF(N42>1825,">5Y"))))))) -> 1-2Y | P42: AHMADNAGAR | Q42: OBC | R42: Group 1: Owned land | S42: 40 | T42: 120 | U42: =+S42+T42 -> 160 | W42: Yes | X42: Yes | Y42: =+IF(AO42="Approved","Yes",AS42) -> 46296 | Z42: NA | AD42: =+AL42 -> 46266 | AE42: =+AS42 -> 46296 | AF42: Yes | AG42: NA | AH42: NA | AI42: Not Required | AJ42: Not Required | AL42: 46266 | AM42: Yes | AN42: Yes | AO42: To be Initiated | AP42: No | AS42: 46296 | AT42: Yes | AU42: Yes | AV42: NA | AW42: NA | AX42: Yes | AY42: Recieved | AZ42: Applied | BA42: Recieved | BB42: Applied | BC42: Recived | BD42: NA | BE42: Recived | BF42: Recived | BG42: Yet to Assign | BH42: No | BI42: 46295 | BJ42: 46326 | BK42: Yes | BL42: Applied but not received | BM42: NA | BN42: NA | BO42: Not Required | BW42: Pending | CB42: SRMP 2023-24 | CC42: Yes | CD42: Yes | CI42: =TEXT(M42,"MMM'YY") -> Jun'24 | CJ42: OBC | CK42: Yes | CL42: Yes
A43: 165 | B43: Village Koradgaon Taluka Pathardi | C43: NILESH PANDURANG GHULE | D43: Ahmednagar West RSA | E43: 2104 | F43: 9011668400 | G43: E | H43: B | I43: KSK | J43: KSK-B w/o Reco | K43: R/2024/IN002245/MAH/000177/3203/00012 | L43: 2023-24 | M43: 45458 | N43: =+TODAY()-M43 -> 719 | O43: =+IF(N43<180,"0-6M",IF(N43<365,"6-12M",IF(N43<730,"1-2Y",IF(N43<1095,"2-3Y",IF(N43<1460,"3-4Y",IF(N43<1825,"4-5Y",IF(N43>1825,">5Y"))))))) -> 1-2Y | P43: AHMADNAGAR | Q43: OBC | R43: Group 1: Owned land | S43: 20 | T43: 40 | U43: =+S43+T43 -> 60 | W43: Yes | X43: Yes | Y43: =+AP43 -> No | Z43: NA | AD43: =+AL43 -> 46266 | AE43: =+AS43 -> 46296 | AF43: Yes | AG43: NA | AH43: NA | AI43: Not Required | AJ43: Not Required | AL43: 46266 | AM43: Yes | AN43: Yes | AO43: To be Initiated | AP43: No | AR43: LSR Awaited | AS43: 46296 | AT43: Yes | AU43: Yes | AV43: NA | AW43: NA | AX43: Yes | AY43: Received | AZ43: Yes | BA43: Applied | BB43: Not Required | BC43: NA | BD43: NA | BE43: Applied | BF43: Applied | BG43: In process | BH43: No | BI43: 46291 | BJ43: 46321 | BK43: Yes | BL43: To be applied | BM43: NA | BN43: NA | BO43: Not Required | BW43: Pending | CB43: SRMP 2023-24 | CC43: Yes | CD43: Yes | CI43: =TEXT(M43,"MMM'YY") -> Jun'24 | CJ43: OBC | CK43: Yes | CL43: Yes
A44: 174 | B44: From Vadapuri to Vakilwasti on LHS of Indapur-Akluj NH | C44: VIJAYSINH DATTATRAYA SHIRKE | D44: Pune Saswad RSA | E44: 1686 | F44: 7709553333 | G44: D1 | H44: B | I44: RO | J44: RO B Site | K44: R/2024/IN002360/MAH/000190/3203/00025 | L44: 2023-24 | M44: 45460 | N44: =+TODAY()-M44 -> 717 | O44: =+IF(N44<180,"0-6M",IF(N44<365,"6-12M",IF(N44<730,"1-2Y",IF(N44<1095,"2-3Y",IF(N44<1460,"3-4Y",IF(N44<1825,"4-5Y",IF(N44>1825,">5Y"))))))) -> 1-2Y | P44: PUNE | Q44: OPEN | R44: Group 2: Firm Offer | S44: 40 | T44: 130 | U44: =+S44+T44 -> 170 | W44: Yes | X44: Yes | Y44: =+IF(AO44="Approved","Yes",AS44) -> 46296 | Z44: NA | AD44: =+AL44 -> 46266 | AE44: =+AS44 -> 46296 | AF44: Yes | AG44: NA | AH44: NA | AI44: Not Required | AJ44: Not Required | AL44: 46266 | AM44: Yes | AN44: Yes | AO44: To be Initiated | AP44: No | AR44: TSR is not clear | AS44: 46296 | AT44: Yes | AU44: Yes | AW44: NA | AX44: Yes | AY44: Yes | AZ44: Applied | BA44: Applied | BB44: Applied | BC44: Received | BD44: Received | BE44: NA | BF44: NA | BG44: In process | BH44: No | BI44: 46291 | BJ44: 46321 | BK44: Yes | BL44: Received | BM44: NA | BN44: NA | BO44: Not Required | BW44: Pending | CB44: SRMP 2023-24 | CC44: Yes | CD44: Yes | CI44: =TEXT(M44,"MMM'YY") -> Jun'24 | CJ44: Open | CK44: Yes | CL44: Yes
A45: 77 | B45: From ALAGUDEWADI To SOMANTHALI ON PHALTAN BARAMATI ROAD | C45: ROHIT MAHADEV POKALE | D45: Satara East RSA | E45: 1961 | F45: 9975251537 | G45: D1 | H45: B | I45: RO | J45: RO B Site | K45: R/2023/IN001291/MAH/000094/3203/00035 | L45: 2023-24 | M45: 45265 | N45: =+TODAY()-M45 -> 912 | O45: =+IF(N45<180,"0-6M",IF(N45<365,"6-12M",IF(N45<730,"1-2Y",IF(N45<1095,"2-3Y",IF(N45<1460,"3-4Y",IF(N45<1825,"4-5Y",IF(N45>1825,">5Y"))))))) -> 2-3Y | P45: SATARA | Q45: OPEN | R45: Group 1: Owned land | S45: 30 | T45: 120 | U45: =+S45+T45 -> 150 | W45: Yes | X45: Yes | Y45: =+AP45 -> Yes | Z45: NA | AD45: =+AL45 -> 46296 | AE45: =+AS45 -> 46327 | AF45: Yes | AG45: NA | AH45: NA | AI45: Not Required | AJ45: Not Required | AL45: 46296 | AM45: Yes | AN45: Yes | AO45: Approved | AP45: Yes | AQ45: 4337974 | AS45: 46327 | AT45: Yes | AU45: Yes | AV45: NA | AW45: NA | AX45: Yes | AY45: Received | AZ45: Applied | BA45: Received | BB45: Applied | BC45: Received | BD45: NA | BE45: NA | BF45: NA | BG45: Received | BH45: WIP | BI45: 46325 | BJ45: 46356 | BK45: Yes | BL45: Received | BM45: NA | BN45: NA | BO45: Not Required | BW45: Pending | CB45: SRMP 2023-24 | CC45: Yes | CD45: Yes | CI45: =TEXT(M45,"MMM'YY") -> Dec'23 | CJ45: Open | CK45: Yes | CL45: Yes
A46: 206 | B46: On RHS From Venavadi to Ambeghar on National Highway (Bhor-Shirwal Road) | C46: VISHWAJIT VIKRAM CHAVAN | D46: Pune Tathawade RSA | E46: 1873 | F46: 9130821872 | G46: D1 | H46: B | I46: RO | J46: RO B Site | K46: R/2024/IN002552/MAH/000261/3203/00081 | L46: 2023-24 | M46: 45464 | N46: =+TODAY()-M46 -> 713 | O46: =+IF(N46<180,"0-6M",IF(N46<365,"6-12M",IF(N46<730,"1-2Y",IF(N46<1095,"2-3Y",IF(N46<1460,"3-4Y",IF(N46<1825,"4-5Y",IF(N46>1825,">5Y"))))))) -> 1-2Y | P46: PUNE | Q46: OBC | R46: Group 1: Owned land | S46: 50 | T46: 110 | U46: =+S46+T46 -> 160 | W46: Yes | X46: Yes | Z46: NA | AD46: =+AL46 -> 46296 | AE46: =+AS46 -> 46327 | AF46: Yes | AG46: NA | AH46: NA | AI46: Not Required | AJ46: Not Required | AL46: 46296 | AM46: Yes | AN46: Yes | AO46: To be Initiated | AP46: No | AR46: LSR Awaited | AS46: 46327 | AT46: Yes | AU46: Yes | AV46: TP plan to be applied online and Provisional NH NOC pending, LSR pending , candidate to complete lease with the Land owner | AW46: NA | AX46: Yes | AY46: Yes | AZ46: Yet to apply | BA46: Applied | BB46: Applied | BC46: Received | BD46: Received | BE46: NA | BF46: NA | BG46: In Process | BH46: No | BI46: 46296 | BJ46: 46327 | BK46: Yes | BL46: Received | BM46: NA | BN46: NA | BO46: Not Required | BW46: Pending | CB46: SRMP 2023-24 | CC46: Yes | CD46: Yes | CI46: =TEXT(M46,"MMM'YY") -> Jun'24 | CJ46: OBC | CK46: Yes | CL46: Yes
A47: 217 | B47: within 2 km on Either side of Zilla parishad Primary school, Sakat on Jamkhed-Patoda Road NH | C47: RUSHIKESH MOHAN LAHANE | D47: Ahmednagar West RSA | E47: 1819 | F47: 7272909666 | G47: D1 | H47: B | I47: RO | J47: RO B Site | K47: R/2024/IN003519/MAH/000387/3203/00105 | L47: 2023-24 | M47: 45541 | N47: =+TODAY()-M47 -> 636 | O47: =+IF(N47<180,"0-6M",IF(N47<365,"6-12M",IF(N47<730,"1-2Y",IF(N47<1095,"2-3Y",IF(N47<1460,"3-4Y",IF(N47<1825,"4-5Y",IF(N47>1825,">5Y"))))))) -> 1-2Y | P47: AHMADNAGAR | Q47: OPEN | R47: Group 1: Owned land | S47: 30 | T47: 120 | U47: =+S47+T47 -> 150 | W47: Yes | X47: Yes | Y47: =+IF(AO47="Approved","Yes",AS47) -> 46327 | Z47: NA | AD47: 46296 | AE47: 46327 | AF47: Yes | AI47: Not Required | AJ47: Not Required | AL47: 46296 | AM47: Yes | AN47: Yes | AO47: To be Initiated | AR47: Very Slow Candidate | AS47: =+AL47+31 -> 46327 | AT47: Yes | AU47: Yes | AV47: NA | AW47: NA | AX47: Yes | AY47: Received | AZ47: In process | BA47: Yet to apply | BB47: Yet to Apply | BC47: NA | BD47: NA | BE47: Yet to apply | BF47: Yet to apply | BG47: Yet to assign | BH47: No | BI47: 46296 | BJ47: 46327 | BK47: Yes | BM47: NA | BN47: NA | BO47: Not Required | BW47: Pending | CB47: SRMP 2023-24 | CC47: Yes | CI47: =TEXT(M47,"MMM'YY") -> Sep'24 | CJ47: Open
A48: 240 | B48: From Jejuri MIDC to Nira on LHS on Pune - Pandharpur Road (NH) | C48: PRANJAL PANKAJ GHONE | D48: Pune Saswad RSA | E48: 102 | F48: 8237342043 | G48: D1 | H48: A | I48: RO | J48: RO A Site-Corpu | K48: R/2025/IN000092/MAH/000013/3203/00005 | L48: 2023-24 | M48: 45783 | N48: =+TODAY()-M48 -> 394 | O48: =+IF(N48<180,"0-6M",IF(N48<365,"6-12M",IF(N48<730,"1-2Y",IF(N48<1095,"2-3Y",IF(N48<1460,"3-4Y",IF(N48<1825,"4-5Y",IF(N48>1825,">5Y"))))))) -> 1-2Y | P48: PUNE | Q48: SC | R48: Group 1: Owned land | S48: 30 | T48: 120 | U48: =+S48+T48 -> 150 | W48: Yes | X48: Yes | Z48: Yet to Initiate | AD48: =+AL48 -> 46266 | AE48: =+AS48 -> 46327 | AF48: Yes | AG48: NA | AH48: NA | AI48: Yes | AJ48: Pending | AL48: 46266 | AM48: Pending | AN48: Pending | AO48: To be Initiated | AP48: No | AR48: LSR Awaited | AS48: 46327 | AT48: Yes | AU48: Yes | AW48: NA | AX48: Yes | AY48: Yes | AZ48: Received | BA48: Applied | BB48: Applied | BC48: Received | BD48: Received | BE48: NA | BF48: NA | BG48: In Process | BH48: WIP | BI48: 46291 | BJ48: 46321 | BK48: Yes | BL48: Received | BN48: Pending | BW48: Pending | BZ48: AN on 02.04.2026 | CA48: Received | CB48: SRMP 2023-24 | CC48: Yes | CD48: Yes | CI48: =TEXT(M48,"MMM'YY") -> May'25 | CJ48: SC | CK48: Yes | CL48: Yes
A49: 24 | B49: VILLAGE KAPADGAON ON NH-965 LONAND PHALTAN ROAD | C49: GANESH GALINDE | D49: Satara East RSA | G49: D1 | H49: A | I49: RO | J49: RO A Site-Corpu | K49: M/2018/IN002081/MAH/000216/3203/00066 | L49: 2018-19 | M49: 43547 | N49: =+TODAY()-M49 -> 2630 | O49: =+IF(N49<180,"0-6M",IF(N49<365,"6-12M",IF(N49<730,"1-2Y",IF(N49<1095,"2-3Y",IF(N49<1460,"3-4Y",IF(N49<1825,"4-5Y",IF(N49>1825,">5Y"))))))) -> >5Y | P49: SATARA | Q49: SC | R49: Group 1: Owned land | S49: 25 | T49: 135 | U49: =+S49+T49 -> 160 | W49: Yes | X49: Yes | Y49: =+AP49 -> Yes | Z49: Approved | AA49: Yes | AB49: Yes | AC49: Yes | AD49: =+AL49 -> 45809 | AE49: =+AS49 -> 46357 | AF49: Yes | AG49: NA | AH49: NA | AI49: Yes | AJ49: Yes | AK49: Available | AL49: 45809 | AM49: Yes | AN49: Yes | AO49: Approved | AP49: Yes | AQ49: 4327589 | AR49: NOC is available for the site. However there are 4 landowners in undivided land in 7/12 extract out of which 2 sisters are not giving consent for lease deed execution. 2 tanks lowered. Lease pending, moreover traffic will be shifted from the location to lonand bypass | AS49: 46357 | AT49: Yes | AU49: Yes | AV49: Court case pending on land and because of that land lease is pending | AW49: NA | AX49: Yes | AY49: Received | AZ49: Received | BA49: Received | BB49: Received | BC49: Received | BD49: NA | BE49: NA | BF49: NA | BG49: Received | BH49: Yes | BI49: 45838 | BJ49: 46538 | BK49: Yes | BL49: Received | BN49: Yes | BW49: Pending | CB49: SRMP 2018-19 | CC49: Yes | CD49: Yes | CI49: =TEXT(M49,"MMM'YY") -> Mar'19 | CJ49: SC | CL49: Yes
A50: 107 | B50: Gharkul Chowk to Jadhav Sarkar Chowk on Spine Road | C50: GOVARDHAN SOMNATH KHANDAGALE | D50: Pimpri Chinchwad RSA | E50: 1667 | F50: 7776079495 | G50: A | H50: A | I50: RO | J50: RO A Site | K50: R/2023/IN002975/MAH/000315/3203/00094 | L50: 2023-24 | M50: 45307 | N50: =+TODAY()-M50 -> 870 | O50: =+IF(N50<180,"0-6M",IF(N50<365,"6-12M",IF(N50<730,"1-2Y",IF(N50<1095,"2-3Y",IF(N50<1460,"3-4Y",IF(N50<1825,"4-5Y",IF(N50>1825,">5Y"))))))) -> 2-3Y | P50: PUNE | Q50: OPEN | R50: Group 2: Firm Offer | S50: 120 | T50: 80 | U50: =+S50+T50 -> 200 | W50: Yes | X50: Yes | Z50: Yet to Initiate | AD50: =+AL50 -> 46357 | AE50: 46357 | AF50: Yes | AG50: NA | AH50: NA | AI50: Yes | AJ50: Pending | AL50: 46357 | AM50: Yes | AN50: Pending | AO50: To be Initiated | AP50: No | AR50: Negotiation Pending | AS50: 46447 | AT50: Yes | AU50: Yes | AV50: NA | AW50: NA | AX50: Yes | AY50: Yes | AZ50: Applied | BA50: Applied | BB50: Not Required | BC50: Applied | BD50: Yes | BE50: NA | BF50: NA | BG50: Received | BH50: Yes | BI50: 46174 | BJ50: 46327 | BK50: Yes | BL50: Received | BN50: Pending | BW50: Pending | BZ50: Received | CA50: Received | CB50: SRMP 2023-24 | CC50: Yes | CD50: Yes | CI50: =TEXT(M50,"MMM'YY") -> Jan'24 | CJ50: Open | CK50: Yes | CL50: Yes
A51: 115 | B51: From Nhavare to Nirvi on NH (Nhavare-Shrigonda Road) | C51: ANIL BALASAHEB WABLE | D51: Pune Wagholi RSA | E51: 1575 | F51: 9890034141 | G51: D1 | H51: B | I51: RO | J51: RO B Site | K51: R/2023/IN003314/MAH/000366/3203/00112 | L51: 2023-24 | M51: 45314 | N51: =+TODAY()-M51 -> 863 | O51: =+IF(N51<180,"0-6M",IF(N51<365,"6-12M",IF(N51<730,"1-2Y",IF(N51<1095,"2-3Y",IF(N51<1460,"3-4Y",IF(N51<1825,"4-5Y",IF(N51>1825,">5Y"))))))) -> 2-3Y | P51: PUNE | Q51: OPEN | R51: Group 1: Owned land | S51: 40 | T51: 153 | U51: =+S51+T51 -> 193 | W51: Yes | X51: Yes | Y51: =+IF(AO51="Approved","Yes",AS51) -> 46357 | Z51: NA | AD51: =+AL51 -> 46327 | AE51: =+AS51 -> 46357 | AF51: Yes | AG51: NA | AH51: NA | AI51: Not Required | AJ51: Not Required | AL51: 46327 | AM51: Yes | AN51: Yes | AO51: To be Initiated | AP51: No | AR51: Very Slow Candidate | AS51: 46357 | AT51: Yes | AU51: Yes but in next FY | AV51: SLOW CANDIDATE | AX51: Yes | AY51: Yes | AZ51: No | BA51: No | BB51: Yet to Apply | BC51: No | BD51: Na | BE51: na | BF51: NA | BG51: Yet to Assign | BH51: No | BI51: 46388 | BJ51: 45992 | BK51: Yes | BL51: Received | BM51: NA | BN51: NA | BO51: Not Required | BW51: Pending | CB51: SRMP 2023-24 | CC51: Yes | CD51: Yes | CI51: =TEXT(M51,"MMM'YY") -> Jan'24 | CJ51: Open | CK51: Yes | CL51: Yes
A52: 158 | B52: From Dahigaon Ne. to Khamgaon on Dahigaon-Khamgaon Road | C52: DNYANESHWAR NAMDEV KALE | D52: Ahmednagar East RSA | E52: 2107 | F52: 9011604232 | G52: E | H52: B | I52: KSK | J52: KSK-B w/o Reco | K52: R/2024/IN002143/MAH/000133/3203/00007 | L52: 2023-24 | M52: 45456 | N52: =+TODAY()-M52 -> 721 | O52: =+IF(N52<180,"0-6M",IF(N52<365,"6-12M",IF(N52<730,"1-2Y",IF(N52<1095,"2-3Y",IF(N52<1460,"3-4Y",IF(N52<1825,"4-5Y",IF(N52>1825,">5Y"))))))) -> 1-2Y | P52: AHMADNAGAR | Q52: OBC | R52: Group 1: Owned land | S52: 20 | T52: 40 | U52: =+S52+T52 -> 60 | W52: Yes | X52: Yes | Z52: NA | AD52: =+AL52 -> 46327 | AE52: =+AS52 -> 46357 | AF52: Yes | AG52: NA | AH52: NA | AI52: Not Required | AJ52: Not Required | AL52: 46327 | AM52: Yes | AN52: Yes | AO52: Approved | AP52: Yes | AQ52: 4338619 | AS52: 46357 | AT52: Yes | AU52: Yes | AV52: NA | AW52: NA | AX52: Yes | AY52: Received | AZ52: Yet to Apply | BA52: Applied | BB52: Applied | BC52: Applied | BD52: NA | BE52: Applied | BF52: Applied | BG52: Received | BH52: No | BI52: 46327 | BJ52: 46357 | BK52: Moujani Awaited | BL52: Yet to Apply | BM52: NA | BN52: NA | BO52: Not Required | BW52: Pending | CB52: SRMP 2023-24 | CC52: Yes | CD52: Yes | CI52: =TEXT(M52,"MMM'YY") -> Jun'24 | CJ52: OBC | CK52: Yes | CL52: Yes
A53: 225 | B53: From Sus-Pashan Bridge to Bavdhan on RHS on NH (Pune-Bangalore Highway) | C53: YOGESH SRIKANT MOKATE | D53: Pune Tathawade RSA | E53: 1605 | F53: 9850837586 | G53: A | H53: A | I53: RO | J53: RO A Site | K53: R/2024/IN003851/MAH/000424/3203/00115 | L53: 2023-24 | M53: 45580 | N53: =+TODAY()-M53 -> 597 | O53: =+IF(N53<180,"0-6M",IF(N53<365,"6-12M",IF(N53<730,"1-2Y",IF(N53<1095,"2-3Y",IF(N53<1460,"3-4Y",IF(N53<1825,"4-5Y",IF(N53>1825,">5Y"))))))) -> 1-2Y | P53: PUNE | Q53: OPEN | R53: Group 1: Owned land | S53: 250 | T53: 100 | U53: =+S53+T53 -> 350 | W53: Yes | X53: Yes | Y53: =+IF(AO53="Approved","Yes",AS53-90) -> 46267 | Z53: Yet to Initiate | AA53: No | AB53: Yes | AD53: 46266 | AE53: =+AS53 -> 46357 | AF53: Yes | AI53: Yes | AJ53: Pending | AL53: 46266 | AM53: Yes | AN53: Pending | AO53: To be Initiated | AP53: No | AR53: LSR, Negotiaiton Pending | AS53: 46357 | AT53: Yes | AU53: Yes | AV53: LSR pending , Negotiation to be done for the location, File pending at MOD ( Lohegaon with inward number- 302624), Final PMC NOC after receiving the MOD | AW53: NA | AX53: Yes | AY53: Yes | AZ53: Applied | BA53: Applied | BB53: Applied | BC53: Received | BD53: Received | BE53: NA | BF53: NA | BG53: In Process | BH53: WIP | BI53: 46419 | BJ53: 46447 | BK53: Yes | BL53: Received | BN53: Pending | BW53: Pending | BZ53: BS assigned by FO | CA53: Received | CB53: SRMP 2023-24 | CC53: Yes | CD53: Yes | CI53: =TEXT(M53,"MMM'YY") -> Oct'24 | CJ53: Open | CK53: Yes | CL53: Yes
A54: 227 | B54: On RHS from Chandni Chowk to Bhugaon Gram Panchayat on National Highway | C54: ANAND SHANKAR MOKATE | D54: Pune City RSA | E54: 1838 | F54: 9850958511 | G54: A | H54: A | I54: RO | J54: RO A Site | K54: R/2024/IN004282/MAH/000437/3203/00121 | L54: 2023-24 | M54: 45632 | N54: =+TODAY()-M54 -> 545 | O54: =+IF(N54<180,"0-6M",IF(N54<365,"6-12M",IF(N54<730,"1-2Y",IF(N54<1095,"2-3Y",IF(N54<1460,"3-4Y",IF(N54<1825,"4-5Y",IF(N54>1825,">5Y"))))))) -> 1-2Y | P54: PUNE | Q54: OPEN | R54: Group 1: Owned land | S54: 125 | T54: 150 | U54: =+S54+T54 -> 275 | W54: Yes | X54: Yes | Y54: =+AP54 -> Yes | Z54: Approved | AA54: Yes | AB54: Yes | AD54: =+AL54 -> 46266 | AE54: =+AS54 -> 46357 | AF54: Yes | AG54: NA | AH54: NA | AI54: Yes | AJ54: Yes | AK54: Pending | AL54: 46266 | AM54: Yes | AN54: Yes | AO54: Approved | AP54: Yes | AQ54: 4338222 | AS54: 46357 | AT54: YES | AU54: YES | AV54: NA | AW54: NA | AX54: YES | AY54: Received | AZ54: Applied | BA54: Received | BB54: Not Required | BC54: Received | BD54: NA | BE54: NA | BF54: NA | BG54: Received | BH54: Yes | BI54: 46419 | BJ54: 46447 | BK54: Yes | BL54: Received | BN54: Yes | BW54: Pending | CB54: SRMP 2023-24 | CC54: Yes | CD54: Yes | CI54: =TEXT(M54,"MMM'YY") -> Dec'24 | CJ54: Open | CK54: Yes | CL54: Yes
A55: 258 | B55: Within 2km from Shivaji Maharaj Square to Narayangaon on SH | C55: ROHIDAS PUNAJI BULE | D55: Pune Wagholi RSA | E55: 1634 | F55: 9881643987 | G55: D2 | H55: A | I55: RO | J55: RO A Site-Corpu | K55: R/2025/IN000817/MAH/000091/3203/00023 | L55: 2023-24 | M55: 46070 | N55: =+TODAY()-M55 -> 107 | O55: =+IF(N55<180,"0-6M",IF(N55<365,"6-12M",IF(N55<730,"1-2Y",IF(N55<1095,"2-3Y",IF(N55<1460,"3-4Y",IF(N55<1825,"4-5Y",IF(N55>1825,">5Y"))))))) -> 0-6M | P55: PUNE | Q55: ST | R55: Group 2: Firm Offer | S55: 25 | T55: 110 | U55: =+S55+T55 -> 135 | W55: Yes | X55: Yes | Z55: Yet to Initiate | AD55: =+AL55 -> 46296 | AE55: =+AS55 -> 46357 | AF55: Yes | AG55: NA | AH55: NA | AI55: Yes | AJ55: Pending | AL55: 46296 | AM55: Yes | AN55: Pending | AO55: To be Initiated | AP55: No | AR55: LSR, Negotiaiton Pending | AS55: 46357 | AT55: Yes | AU55: Yes | AX55: No | AY55: Applied | AZ55: Yet to applied | BA55: Yet to applied | BB55: Yet to applied | BC55: Yet to applied | BD55: Yet to applied | BE55: NA | BF55: NA | BG55: In Process | BH55: No | BI55: 46381 | BJ55: 46447 | BK55: Moujani Awaited | BL55: Yet to Apply | BN55: Pending | BW55: Pending | BZ55: AN on 08.04.2026 | CA55: Received | CB55: SRMP 2023-24 | CC55: Yes | CD55: Yes | CI55: =TEXT(M55,"MMM'YY") -> Feb'26 | CJ55: st | CK55: Yes | CL55: Yes
A56: 261 | B56: Vilage Modhave on National Highway (Nira Supe Road) | C56: SHRI SHIVLING DNYANDEO JAGTAP | D56: Pune Tathawade RSA | E56: 1967 | F56: 7499213190 | G56: D1 | H56: A | I56: RO | J56: RO A Site-Corpu | K56: R/2025/IN000821/MAH/000094/3203/00026 | L56: 2023-24 | M56: 46071 | N56: =+TODAY()-M56 -> 106 | O56: =+IF(N56<180,"0-6M",IF(N56<365,"6-12M",IF(N56<730,"1-2Y",IF(N56<1095,"2-3Y",IF(N56<1460,"3-4Y",IF(N56<1825,"4-5Y",IF(N56>1825,">5Y"))))))) -> 0-6M | P56: PUNE | Q56: SC | R56: Group 1: Owned land | S56: 50 | T56: 100 | U56: =+S56+T56 -> 150 | W56: No | X56: Non-Commissionable | Z56: Yet to Initiate | AD56: =+AL56 -> 46266 | AE56: =+AS56 -> 46357 | AF56: Yes | AG56: NA | AH56: NA | AI56: Pending | AJ56: Pending | AL56: 46266 | AO56: To be Initiated | AP56: No | AS56: 46357 | AT56: No | AU56: No | AV56: The LOI is recommended for cancellation , as the lease deed was cancelled by the candidate and the candidate does not have hold of the land | AW56: No | AX56: No | AY56: Yet to apply | AZ56: Yet to apply | BA56: Yet to apply | BB56: Yet to apply | BC56: Yet to apply | BD56: Yet to apply | BE56: NA | BF56: NA | BH56: No | BI56: NA | BJ56: NA | BK56: Moujani Awaited | BL56: Yet to Apply | BN56: Pending | BW56: Pending | BZ56: AN on 08.04.2026 | CB56: SRMP 2023-24 | CC56: Yes | CD56: Yes | CI56: =TEXT(M56,"MMM'YY") -> Feb'26 | CJ56: SC | CL56: Yes
A57: 9 | B57: WATLUJ | C57: MANOJ KISAN LONDHE | D57: Pune Hadapsar RSA | F57: 9860366892 | G57: E | H57: A | I57: KSK | J57: KSK-A w/o Reco | K57: N/2015/IN001130/MAH/000146/3203/00031 | L57: KSK 2014-15 | M57: 42441 | N57: =+TODAY()-M57 -> 3736 | O57: =+IF(N57<180,"0-6M",IF(N57<365,"6-12M",IF(N57<730,"1-2Y",IF(N57<1095,"2-3Y",IF(N57<1460,"3-4Y",IF(N57<1825,"4-5Y",IF(N57>1825,">5Y"))))))) -> >5Y | P57: PUNE | Q57: SC | R57: Group 2: Firm Offer | S57: 10 | T57: 44 | U57: =+S57+T57 -> 54 | W57: Yes | X57: Yes | Z57: Yet to Initiate | AD57: 46357 | AE57: 46388 | AF57: Yes | AI57: In Process | AJ57: Pending | AL57: 46357 | AM57: Pending | AN57: Pending | AO57: To be Initiated | AR57: LSR Awaited, land change case | AS57: 46388 | AT57: Yes | AU57: Yes | AV57: NA | AW57: NA | AX57: No | BG57: In Process | BI57: 46357 | BJ57: 46388 | BK57: No | BL57: Yet to Apply | BW57: Pending | BZ57: AN on 08.04.2026 | CA57: Gosavi and VAC on 25.05.2026 | CB57: Pre 2018/Govt | CC57: Yes | CI57: =TEXT(M57,"MMM'YY") -> Mar'16 | CJ57: SC
A58: 168 | B58: On LHS, From Najik Babhulgaon to Rakshi On Shevgaon Georai SH | C58: SHUBHAM BHAGNATH KATE | D58: Ahmednagar East RSA | E58: 1811 | F58: 9404972337 | G58: D2 | H58: B | I58: RO | J58: RO B Site | K58: R/2024/IN002256/MAH/000181/3203/00016 | L58: 2023-24 | M58: 45458 | N58: =+TODAY()-M58 -> 719 | O58: =+IF(N58<180,"0-6M",IF(N58<365,"6-12M",IF(N58<730,"1-2Y",IF(N58<1095,"2-3Y",IF(N58<1460,"3-4Y",IF(N58<1825,"4-5Y",IF(N58>1825,">5Y"))))))) -> 1-2Y | P58: PUNE | Q58: OBC | R58: Group 1: Owned land | S58: 40 | T58: 80 | U58: =+S58+T58 -> 120 | W58: Yes | X58: Yes | Z58: NA | AD58: 46357 | AE58: 46388 | AF58: Yes | AG58: NA | AH58: NA | AI58: Not Required | AJ58: Not Required | AL58: 46357 | AM58: Yes | AN58: Yes | AO58: To be Initiated | AR58: Alternate land offered. Candidate is arranging NOC | AS58: =+AL58+31 -> 46388 | AT58: Yes | AU58: Yes | AV58: Candidate requested alternater land due to rejection by PWD. Alternate ladn offer is in Progress | AW58: NA | AX58: No | AY58: Applied | AZ58: Yet to apply | BA58: Yet to apply | BB58: Yet to apply | BC58: Yet to apply | BD58: NA | BE58: Yet to apply | BF58: Yet to apply | BG58: Yet to Assign | BH58: Yet to apply | BI58: 46447 | BJ58: 46447 | BK58: Yes | BM58: NA | BN58: NA | BO58: Not Required | BW58: Pending | BZ58: AN on 08.04.2026 | CB58: SRMP 2023-24 | CC58: Yes | CI58: =TEXT(M58,"MMM'YY") -> Jun'24 | CJ58: OBC
A59: 185 | B59: From Kanheri-Katewadi to Junction on RHS on Baramati-Indapur NH | C59: SIDDHANT GANESH RASKAR | D59: Pune Saswad RSA | E59: 1895 | F59: 7588277374 | G59: D1 | H59: B | I59: RO | J59: RO B Site | K59: R/2024/IN002441/MAH/000220/3203/00049 | L59: 2023-24 | M59: 45461 | N59: =+TODAY()-M59 -> 716 | O59: =+IF(N59<180,"0-6M",IF(N59<365,"6-12M",IF(N59<730,"1-2Y",IF(N59<1095,"2-3Y",IF(N59<1460,"3-4Y",IF(N59<1825,"4-5Y",IF(N59>1825,">5Y"))))))) -> 1-2Y | P59: PUNE | Q59: OBC | R59: Group 1: Owned land | S59: 30 | T59: 127 | U59: =+S59+T59 -> 157 | W59: Yes | X59: Yes | Y59: =+IF(AO59="Approved","Yes",AS59) -> 46388 | Z59: NA | AD59: =+AL59 -> 46357 | AE59: =+AS59 -> 46388 | AF59: Yes | AG59: NA | AH59: NA | AI59: Not Required | AJ59: Not Required | AL59: 46357 | AM59: Yes | AN59: Yes | AO59: To be Initiated | AP59: No | AR59: Slow Candidate, Family land dispute. | AS59: 46388 | AT59: Yes | AU59: Yes | AW59: NA | AX59: Yes | AY59: Yes | AZ59: Received | BA59: Applied | BB59: Applied | BC59: Received | BD59: Received | BE59: NA | BF59: NA | BG59: In Process | BH59: WIP | BI59: 46382 | BJ59: 46388 | BK59: Yes | BL59: Received | BM59: NA | BN59: NA | BO59: Not Required | BW59: Pending | BZ59: AN on 08.04.2026 | CB59: SRMP 2023-24 | CC59: Yes | CD59: Yes | CI59: =TEXT(M59,"MMM'YY") -> Jun'24 | CJ59: OBC | CK59: Yes | CL59: Yes
A60: 194 | B60: From Chanda to Fattepur on Ghodegaon-Kukana SH | C60: NILKANTH MARUTRAO KHARADE | D60: Ahmednagar East RSA | E60: 1933 | F60: 9527297676 | G60: D2 | H60: B | I60: RO | J60: RO B Site | K60: R/2024/IN002462/MAH/000228/3203/00057 | L60: 2023-24 | M60: 45461 | N60: =+TODAY()-M60 -> 716 | O60: =+IF(N60<180,"0-6M",IF(N60<365,"6-12M",IF(N60<730,"1-2Y",IF(N60<1095,"2-3Y",IF(N60<1460,"3-4Y",IF(N60<1825,"4-5Y",IF(N60>1825,">5Y"))))))) -> 1-2Y | P60: AHMADNAGAR | Q60: OBC | R60: Group 2: Firm Offer | S60: 55 | T60: 100 | U60: =+S60+T60 -> 155 | W60: Yes | X60: Yes | Z60: NA | AD60: =+AL60 -> 46357 | AE60: =+AS60 -> 46388 | AF60: Yes | AG60: NA | AH60: NA | AI60: Not Required | AJ60: Not Required | AL60: 46357 | AM60: Yes | AN60: Yes | AO60: To be Initiated | AP60: No | AR60: LSR Awaited, land change case | AS60: 46388 | AT60: Yes | AU60: Yes | AV60: NA | AW60: NA | AX60: Yes | AY60: Applied | AZ60: Yet to apply | BA60: Applied | BB60: Applied | BC60: Applied | BD60: NA | BE60: Applied | BF60: Applied | BG60: In Process | BH60: No | BI60: 46357 | BJ60: 46419 | BK60: Yes | BL60: Yet to Apply | BM60: NA | BN60: NA | BO60: Not Required | BW60: Pending | BZ60: AN on 08.04.2026 | CB60: SRMP 2023-24 | CC60: Yes | CD60: Yes | CI60: =TEXT(M60,"MMM'YY") -> Jun'24 | CJ60: OBC | CK60: Yes | CL60: Yes
A61: 196 | B61: From Kasari to Kodhapuri on RHS on NH (Pune-Ahmednagar Road) | C61: SACHIN VITHALRAO MANTAWAR | D61: Pune Wagholi RSA | E61: 1821 | F61: 7875061656 | G61: D1 | H61: A | I61: RO | J61: RO A Site-Corpu | K61: R/2024/IN002491/MAH/000239/3203/00068 | L61: 2023-24 | M61: 45462 | N61: =+TODAY()-M61 -> 715 | O61: =+IF(N61<180,"0-6M",IF(N61<365,"6-12M",IF(N61<730,"1-2Y",IF(N61<1095,"2-3Y",IF(N61<1460,"3-4Y",IF(N61<1825,"4-5Y",IF(N61>1825,">5Y"))))))) -> 1-2Y | P61: PUNE | Q61: ST | R61: Group 1: Owned land | S61: 30 | T61: 120 | U61: =+S61+T61 -> 150 | W61: Yes | X61: Yes | Y61: =+IF(AO61="Approved","Yes",AS61) -> 46388 | Z61: Yet to Initiate | AD61: =+AL61 -> 46327 | AE61: =+AS61 -> 46388 | AF61: Yes | AG61: NA | AH61: NA | AI61: Yes | AJ61: Pending | AL61: 46327 | AM61: Pending | AN61: Pending | AO61: To be Initiated | AP61: No | AR61: LSR Awaited, land change case | AS61: 46388 | AT61: Yes | AU61: Yes | AV61: Alternate land case | AX61: NO | AY61: Applied | AZ61: Yet to applied | BA61: Yet to applied | BB61: Yet to Apply | BC61: Yet to applied | BD61: Yet to applied | BE61: NA | BF61: NA | BG61: In Process | BH61: NO | BI61: 46414 | BJ61: 46473 | BK61: Yes | BL61: Received | BN61: Pending | BW61: Pending | BZ61: AN on 08.04.2026 | CA61: Received | CB61: SRMP 2023-24 | CC61: Yes | CD61: Yes | CI61: =TEXT(M61,"MMM'YY") -> Jun'24 | CJ61: st | CK61: Yes | CL61: Yes
A62: 209 | B62: Within 5 Km from Hotel Smile Stone towards Pune on Pune -Ahmednagar NH | C62: AKSHATA RAJENDRA ROKADE | D62: Ahmednagar East RSA | E62: 1905 | F62: 8275613407 | G62: D1 | H62: A | I62: RO | J62: RO A Site-Corpu | K62: R/2024/IN002780/MAH/000308/3203/00092 | L62: 2023-24 | M62: 45479 | N62: =+TODAY()-M62 -> 698 | O62: =+IF(N62<180,"0-6M",IF(N62<365,"6-12M",IF(N62<730,"1-2Y",IF(N62<1095,"2-3Y",IF(N62<1460,"3-4Y",IF(N62<1825,"4-5Y",IF(N62>1825,">5Y"))))))) -> 1-2Y | P62: AHMADNAGAR | Q62: SC | R62: Group 1: Owned land | S62: 50 | T62: 105 | U62: =+S62+T62 -> 155 | W62: Yes | X62: Yes | Y62: =+IF(AO62="Approved","Yes",AS62) -> 46388 | Z62: Approved | AD62: 46357 | AE62: 46388 | AF62: Yes | AG62: NA | AH62: NA | AI62: Yes | AJ62: Yes | AL62: 46357 | AM62: Yes | AN62: Yes | AO62: To be Initiated | AR62: Land title is not clear. Will take some time to get TSR cleared | AS62: 46388 | AT62: Yes | AU62: Yes | AV62: NA | AW62: NA | AX62: Yes | AY62: Received | AZ62: Applied | BA62: Received | BB62: Received | BC62: Received | BD62: NA | BE62: Received | BF62: Received | BG62: Received | BH62: WIP | BI62: 46266 | BJ62: 46327 | BK62: Yes | BN62: Pending | BW62: Pending | BZ62: AN on 08.04.2026 | CA62: Received | CB62: SRMP 2023-24 | CC62: Yes | CI62: =TEXT(M62,"MMM'YY") -> Jul'24 | CJ62: SC
A63: 220 | B63: From Theur Phata to Urlikanchan Police Station on LHS on NH (Pune-Solapur Road) | C63: VIKRANT VIJAY SADAKALE | D63: Pune Hadapsar RSA | E63: 1914 | F63: 9657892449 | G63: D1 | H63: A | I63: RO | J63: RO A Site-Corpu | K63: R/2024/IN003782/MAH/000410/3203/00111 | L63: 2023-24 | M63: 45573 | N63: =+TODAY()-M63 -> 604 | O63: =+IF(N63<180,"0-6M",IF(N63<365,"6-12M",IF(N63<730,"1-2Y",IF(N63<1095,"2-3Y",IF(N63<1460,"3-4Y",IF(N63<1825,"4-5Y",IF(N63>1825,">5Y"))))))) -> 1-2Y | P63: PUNE | Q63: SC | R63: Group 2: Firm Offer | S63: 30 | T63: 125 | U63: =+S63+T63 -> 155 | W63: Yes | X63: Yes | Y63: =+IF(AO63="Approved","Yes",AS63) -> 46388 | Z63: Yet to Initiate | AD63: 46357 | AE63: 46388 | AF63: Yes | AI63: Yes | AJ63: Pending | AL63: 46357 | AM63: Pending | AN63: Pending | AO63: To be Initiated | AR63: LSR Awaited, negoatiation pending | AS63: 46388 | AT63: Yes | AU63: Yes | AV63: NA | AW63: NA | AX63: Yes | AY63: Yes | AZ63: Yet to apply | BA63: Applied | BB63: Applied | BC63: Received | BD63: Received | BE63: NA | BF63: NA | BG63: In Process | BH63: WIP | BI63: 46265 | BJ63: 46387 | BK63: Yes | BL63: Received | BW63: Pending | BZ63: AN on 08.04.2026 | CA63: Received | CB63: SRMP 2023-24 | CC63: Yes | CI63: =TEXT(M63,"MMM'YY") -> Oct'24 | CJ63: SC
A64: 223 | B64: Within 3 KM from Lonand Bus Stand Towards Satara on Satara Lonand Road | C64: VIJAY MALHARI SHELKE | D64: Satara East RSA | E64: 1600 | F64: 9604685831 | G64: D1 | H64: B | I64: RO | J64: RO B Site | K64: R/2024/IN003803/MAH/000416/3203/00114 | L64: 2023-24 | M64: 45575 | N64: =+TODAY()-M64 -> 602 | O64: =+IF(N64<180,"0-6M",IF(N64<365,"6-12M",IF(N64<730,"1-2Y",IF(N64<1095,"2-3Y",IF(N64<1460,"3-4Y",IF(N64<1825,"4-5Y",IF(N64>1825,">5Y"))))))) -> 1-2Y | P64: SATARA | Q64: CC-1 DEFENCE | R64: Group 2: Firm Offer | S64: 30 | T64: 120 | U64: =+S64+T64 -> 150 | W64: Yes | X64: Yes | Z64: NA | AD64: 46357 | AE64: 46388 | AF64: Yes | AI64: Not Required | AJ64: Not Required | AL64: 46357 | AM64: Yes | AN64: Yes | AO64: Approved | AP64: Yes | AQ64: 4338620 | AS64: =+AL64+31 -> 46388 | AT64: Yes | AU64: Yes but in next FY | AV64: Slow condidate,NA applied but yet to be done | AW64: NA | AX64: Yes | AY64: Received | AZ64: Applied | BA64: Applied | BB64: Applied | BC64: Applied | BD64: NA | BE64: NA | BF64: NA | BG64: In Process | BH64: No | BI64: 46568 | BJ64: 46595 | BK64: Yes | BL64: Received | BM64: NA | BN64: NA | BO64: Not Required | BW64: Pending | BZ64: AN on 08.04.2026 | CB64: SRMP 2023-24 | CC64: Yes | CI64: =TEXT(M64,"MMM'YY") -> Oct'24 | CJ64: OBC
A65: 243 | B65: Village Hivere zare, On Ahmednagar Daund Road (NH) | C65: SATISH BHAGWANT HARAL | D65: Ahmednagar West RSA | E65: 2064 | F65: 9326796545 | G65: D1 | H65: B | I65: RO | J65: RO B Site | K65: R/2025/IN000254/MAH/000033/3203/00009 | L65: 2023-24 | M65: 45839 | N65: =+TODAY()-M65 -> 338 | O65: =+IF(N65<180,"0-6M",IF(N65<365,"6-12M",IF(N65<730,"1-2Y",IF(N65<1095,"2-3Y",IF(N65<1460,"3-4Y",IF(N65<1825,"4-5Y",IF(N65>1825,">5Y"))))))) -> 6-12M | P65: AHMADNAGAR | Q65: CC-1 DEFENCE | R65: Group 2: Firm Offer | S65: 30 | T65: 125 | U65: =+S65+T65 -> 155 | W65: Yes | X65: Yes | Z65: NA | AD65: =+AL65 -> 46357 | AE65: =+AS65 -> 46388 | AF65: Yes | AG65: NA | AH65: NA | AI65: Not Required | AJ65: Not Required | AL65: 46357 | AO65: To be Initiated | AP65: No | AS65: 46388 | AT65: Yes | AU65: Yes | AV65: NA | AW65: NA | AX65: Yes | AY65: Applied | AZ65: Yet to apply | BA65: Yet to apply | BB65: Yet to Apply | BC65: NA | BD65: NA | BE65: Yet to apply | BF65: Yet to apply | BG65: Yet to assign | BH65: No | BI65: 46357 | BJ65: 46388 | BK65: Moujani Awaited | BL65: Yet to Apply | BW65: Pending | BZ65: AN on 08.04.2026 | CB65: SRMP 2023-24 | CC65: Yes | CD65: Yes | CI65: =TEXT(M65,"MMM'YY") -> Jul'25 | CJ65: Open | CK65: Yes | CL65: Yes
A66: 56 | B66: ON NASIK-PUNE BYPASS ROAD | C66: SONALI SUNIL RUPAWATE | D66: Shirdi RSA | F66: 9011533440 | G66: D1 | H66: A | I66: RO | J66: RO A Site-Corpu | K66: N/2022/IN001409/MAH/000092/3203/00033 | L66: SRMP 2014-15 | M66: 44907 | N66: =+TODAY()-M66 -> 1270 | O66: =+IF(N66<180,"0-6M",IF(N66<365,"6-12M",IF(N66<730,"1-2Y",IF(N66<1095,"2-3Y",IF(N66<1460,"3-4Y",IF(N66<1825,"4-5Y",IF(N66>1825,">5Y"))))))) -> 3-4Y | P66: AHMADNAGAR | Q66: SC | R66: Group 2: Firm Offer | S66: 30 | T66: 130 | U66: =+S66+T66 -> 160 | W66: Yes | X66: Yes | Y66: =+IF(AO66="Approved","Yes",AS66) -> 46419 | Z66: Yet to Initiate | AD66: =+AL66 -> 46357 | AE66: =+AS66 -> 46419 | AF66: Yes | AG66: NA | AH66: NA | AI66: Yes | AJ66: Yes | AL66: 46357 | AM66: Yes | AN66: Yes | AO66: To be Initiated | AP66: No | AR66: There is charge on landwhich needs to be cleard. LSR has huge charge on land | AS66: 46419 | AT66: Yes | AU66: Yes | AV66: LSR due with CHarge on land | AW66: NA | AX66: Yes | AY66: Recieved | AZ66: Applied | BA66: Recieved | BB66: Applied | BC66: Recived | BD66: NA | BE66: Recived | BF66: Recived | BG66: In Process | BH66: WIP | BI66: 46234 | BJ66: 46295 | BK66: Moujani Awaited | BL66: Yet to Apply | BN66: Pending | BW66: Pending | BZ66: AN on 08.04.2026 | CA66: Received | CB66: Pre 2018/Govt | CC66: Yes | CD66: Yes | CI66: =TEXT(M66,"MMM'YY") -> Dec'22 | CJ66: SC | CL66: Yes
A67: 71 | B67: Within 4 kms from Warje Bridge towards Takalwadi in Shivane , Pune | C67: CHAITRALI RAOSAHEB DANGAT | D67: Pune City RSA | E67: 1579 | F67: 7030622003 | G67: A | H67: B | I67: RO | J67: RO B Site | K67: R/2023/IN000870/MAH/000067/3203/00020 | L67: 2023-24 | M67: 45253 | N67: =+TODAY()-M67 -> 924 | O67: =+IF(N67<180,"0-6M",IF(N67<365,"6-12M",IF(N67<730,"1-2Y",IF(N67<1095,"2-3Y",IF(N67<1460,"3-4Y",IF(N67<1825,"4-5Y",IF(N67>1825,">5Y"))))))) -> 2-3Y | P67: PUNE | Q67: OPEN | R67: Group 1: Owned land | S67: 200 | T67: 125 | U67: =+S67+T67 -> 325 | W67: Yes | X67: Yes | Y67: =+IF(AO67="Approved","Yes",AS67) -> 46419 | Z67: NA | AD67: 46352 | AE67: =+AS67 -> 46419 | AF67: Yes | AG67: NA | AH67: NA | AI67: Not Required | AJ67: Not Required | AK67: Pending | AL67: 46266 | AM67: Yes | AN67: Yes | AO67: To be Initiated | AP67: No | AR67: Site requiresd MOD Approval, which is main reason for delay | AS67: 46419 | AT67: YES | AU67: YES | AV67: NA | AW67: NA | AX67: YES | AY67: Received | AZ67: Applied | BA67: Applied | BB67: Not Required | BC67: Received | BD67: NA | BE67: NA | BF67: NA | BG67: In Process | BH67: NO | BI67: 46419 | BJ67: 46419 | BK67: Yes | BL67: Received | BM67: NA | BN67: NA | BO67: Not Required | BW67: Pending | CB67: SRMP 2023-24 | CC67: Yes | CD67: Yes | CI67: =TEXT(M67,"MMM'YY") -> Nov'23 | CJ67: Open | CK67: Yes | CL67: Yes
A68: 86 | B68: From Ghusalkhamb Naka to Muleshwar temple on Lonavala Ambey Valley Road | C68: SWAPNIL PRAKASH PAWAR | D68: Pune Tathawade RSA | E68: 2113 | F68: 9545478686 | G68: E | H68: B | I68: KSK | J68: KSK-B w/o Reco | K68: R/2023/IN001556/MAH/000128/3203/00052 | L68: 2023-24 | M68: 45273 | N68: =+TODAY()-M68 -> 904 | O68: =+IF(N68<180,"0-6M",IF(N68<365,"6-12M",IF(N68<730,"1-2Y",IF(N68<1095,"2-3Y",IF(N68<1460,"3-4Y",IF(N68<1825,"4-5Y",IF(N68>1825,">5Y"))))))) -> 2-3Y | P68: PUNE | Q68: OPEN | R68: Group 1: Owned land | S68: 30 | T68: 90 | U68: =+S68+T68 -> 120 | W68: Yes | X68: Yes | Y68: =+IF(AO68="Approved","Yes",AS68) -> 46419 | Z68: NA | AD68: 46388 | AE68: 46419 | AF68: Yes | AG68: NA | AH68: NA | AI68: Not Required | AJ68: Not Required | AL68: 46388 | AM68: Yes | AN68: Yes | AO68: To be Initiated | AP68: No | AR68: LSR Awaited | AS68: 46419 | AT68: Yes | AU68: Yes but in next FY | AV68: PMRDA permission pending and LOI holder is often not responsive, The location is in the monopoly market of OMC not recommended for cancellation | AW68: No | AX68: Yes | AY68: Yes | AZ68: Applied | BA68: Applied | BB68: Applied | BC68: Received | BD68: Received | BE68: NA | BF68: NA | BG68: In Process | BH68: No | BI68: 46753 | BJ68: 46784 | BK68: Yes | BL68: Received | BM68: NA | BN68: NA | BO68: Not Required | BW68: Pending | BZ68: AN on 08.04.2026 | CB68: SRMP 2023-24 | CC68: Yes | CD68: Yes | CI68: =TEXT(M68,"MMM'YY") -> Dec'23 | CJ68: Open | CK68: Yes | CL68: Yes
A69: 114 | B69: From Kanheri-Katewadi to Junction on LHS on Baramti-Indapur NH | C69: ABABSAHEB BAPURAO NIMBALKAR | D69: Pune Saswad RSA | E69: 1817 | F69: 9975023030 | G69: D1 | H69: B | I69: RO | J69: RO B Site | K69: R/2023/IN003273/MAH/000358/3203/00106 | L69: 2023-24 | M69: 45314 | N69: =+TODAY()-M69 -> 863 | O69: =+IF(N69<180,"0-6M",IF(N69<365,"6-12M",IF(N69<730,"1-2Y",IF(N69<1095,"2-3Y",IF(N69<1460,"3-4Y",IF(N69<1825,"4-5Y",IF(N69>1825,">5Y"))))))) -> 2-3Y | P69: PUNE | Q69: OPEN | R69: Group 1: Owned land | S69: 30 | T69: 122 | U69: =+S69+T69 -> 152 | W69: Yes | X69: Yes | Y69: =+IF(AO69="Approved","Yes",AS69) -> 46419 | Z69: NA | AD69: 46388 | AE69: 46419 | AF69: Yes | AG69: NA | AH69: NA | AI69: Not Required | AJ69: Not Required | AL69: 46388 | AM69: Yes | AN69: Yes | AO69: To be Initiated | AP69: No | AR69: LSR Awaited | AS69: 46419 | AT69: Yes | AU69: Yes | AW69: NA | AX69: Yes | AY69: Yes | AZ69: Received | BA69: Applied | BB69: Applied | BC69: Received | BD69: Received | BE69: NA | BF69: NA | BG69: In Process | BH69: WIP | BI69: 46382 | BJ69: 46388 | BK69: Yes | BL69: Received | BM69: NA | BN69: NA | BO69: Not Required | BW69: Pending | BZ69: AN on 08.04.2026 | CB69: SRMP 2023-24 | CC69: Yes | CD69: Yes | CI69: =TEXT(M69,"MMM'YY") -> Jan'24 | CJ69: Open | CK69: Yes | CL69: Yes
A70: 126 | B70: From Undri Chowk to Mantarwadi Chowk towards Pune Saswad Road,Urlidevachi on NH | C70: ANNASAHEB VINAYAK BAJARE | D70: Pune Hadapsar RSA | E70: 2023 | F70: 9373762424 | G70: D1 | H70: A | I70: RO | J70: RO A Site | K70: R/2023/IN004128/MAH/000442/3203/00129 | L70: 2023-24 | M70: 45334 | N70: =+TODAY()-M70 -> 843 | O70: =+IF(N70<180,"0-6M",IF(N70<365,"6-12M",IF(N70<730,"1-2Y",IF(N70<1095,"2-3Y",IF(N70<1460,"3-4Y",IF(N70<1825,"4-5Y",IF(N70>1825,">5Y"))))))) -> 2-3Y | P70: PUNE | Q70: OPEN | R70: Group 1: Owned land | S70: 80 | T70: 85 | U70: =+S70+T70 -> 165 | W70: Yes | X70: Yes | Y70: =+AP70 -> Yes | Z70: Approved | AD70: 46388 | AE70: 46419 | AF70: Yes | AG70: NA | AH70: NA | AI70: Yes | AJ70: Yes | AL70: 46388 | AM70: Yes | AN70: Yes | AO70: Approved | AP70: Yes | AQ70: 4338562 | AR70: IO received, Advance tender done, Site is ready, NOC awaited. Planned Comm in Mar'26 | AS70: 46419 | AT70: Yes | AU70: Yes | AV70: NA | AW70: NA | AX70: Yes | AY70: Yes | AZ70: Applied | BA70: Received | BB70: Received | BC70: Received | BD70: NA | BE70: NA | BF70: NA | BG70: Received | BH70: yes | BI70: 46266 | BJ70: 46295 | BK70: Yes | BL70: Received | BN70: Yes | BW70: Pending | CB70: SRMP 2023-24 | CC70: Yes | CD70: Yes | CI70: =TEXT(M70,"MMM'YY") -> Feb'24 | CJ70: Open | CK70: Yes | CL70: Yes
A71: 154 | B71: Village Barhanpur, on RHS towards Patas on NH (Baramati Patas Road) | C71: SWAPNIL SHIVAJI THORAT | D71: Pune Tathawade RSA | E71: 1917 | F71: 8380077342 | G71: D1 | H71: B | I71: RO | J71: RO B Site | K71: R/2024/IN002033/MAH/000087/3203/00003 | L71: 2023-24 | M71: 45456 | N71: =+TODAY()-M71 -> 721 | O71: =+IF(N71<180,"0-6M",IF(N71<365,"6-12M",IF(N71<730,"1-2Y",IF(N71<1095,"2-3Y",IF(N71<1460,"3-4Y",IF(N71<1825,"4-5Y",IF(N71>1825,">5Y"))))))) -> 1-2Y | P71: PUNE | Q71: OPEN | R71: Group 2: Firm Offer | S71: 30 | T71: 120 | U71: =+S71+T71 -> 150 | W71: Yes | X71: Yes | Y71: =+AP71 -> No | Z71: NA | AD71: 46388 | AE71: 46419 | AF71: Yes | AG71: NA | AH71: NA | AI71: Not Required | AJ71: Not Required | AL71: 46388 | AM71: Yes | AN71: Yes | AO71: To be Initiated | AP71: No | AR71: LSR Awaited | AS71: 46419 | AT71: Yes | AU71: Yes | AV71: Tentative NA pending , Provisional MH NOC pending | AW71: No | AX71: Yes | AY71: Yes | AZ71: Applied | BA71: Applied | BB71: Applied | BC71: Received | BD71: Received | BE71: NA | BF71: NA | BG71: In Process | BH71: WIP | BI71: 46357 | BJ71: 46388 | BK71: Yes | BL71: Received | BM71: NA | BN71: NA | BO71: Not Required | BW71: Pending | BZ71: AN on 08.04.2026 | CB71: SRMP 2023-24 | CC71: Yes | CD71: Yes | CI71: =TEXT(M71,"MMM'YY") -> Jun'24 | CJ71: Open | CK71: Yes | CL71: Yes
A72: 246 | B72: Within 5 km from Sub-registrar Office, Paud on Mulshi- Chandni Chowk Highway towards Pirangut | C72: SOMNATH BABURAO BEDARE | D72: Pune City RSA | E72: 1612 | F72: 8788797700 | G72: D1 | H72: A | I72: RO | J72: RO A Site-Corpu | K72: R/2025/IN000329/MAH/000048/3203/00011 | L72: 2023-24 | M72: 45868 | N72: =+TODAY()-M72 -> 309 | O72: =+IF(N72<180,"0-6M",IF(N72<365,"6-12M",IF(N72<730,"1-2Y",IF(N72<1095,"2-3Y",IF(N72<1460,"3-4Y",IF(N72<1825,"4-5Y",IF(N72>1825,">5Y"))))))) -> 6-12M | P72: PUNE | Q72: ST | R72: Group 2: Firm Offer | S72: 50 | T72: 100 | U72: =+S72+T72 -> 150 | W72: Yes | X72: Yes | Z72: Yet to Initiate | AD72: 46388 | AE72: =+AS72 -> 46419 | AF72: Yes | AG72: NA | AH72: NA | AI72: Yes | AJ72: Pending | AK72: Pending | AL72: 46266 | AM72: Yes | AN72: Pending | AO72: To be Initiated | AP72: No | AS72: 46419 | AT72: YES | AU72: YES | AV72: NA | AW72: NA | AX72: YES | AY72: Received | AZ72: Applied | BA72: Applied | BB72: Applied | BC72: Received | BD72: NA | BE72: NA | BF72: NA | BG72: In Process | BH72: NO | BI72: 46357 | BJ72: 46388 | BK72: No | BL72: Yet to Apply | BN72: Pending | BW72: Pending | BZ72: AN on 08.04.2026 | CA72: Received | CB72: SRMP 2023-24 | CC72: Yes | CD72: Yes | CI72: =TEXT(M72,"MMM'YY") -> Jul'25 | CJ72: st | CK72: Yes | CL72: Yes
A73: 53 | B73: TALEGAON TOLL PLAZA TO KUSHGAON ON PUNE MUMBAI EXPRESSWAY ON LHS , | C73: SATYAN BHIMSEN GAIKWAD | D73: Pune Tathawade RSA | F73: 7039131602 | G73: D1 | H73: A | I73: RO | J73: RO A Site | K73: M/2022/IN001225/MAH/000074/3203/00023 | L73: 2018-19 | M73: 44875 | N73: =+TODAY()-M73 -> 1302 | O73: =+IF(N73<180,"0-6M",IF(N73<365,"6-12M",IF(N73<730,"1-2Y",IF(N73<1095,"2-3Y",IF(N73<1460,"3-4Y",IF(N73<1825,"4-5Y",IF(N73>1825,">5Y"))))))) -> 3-4Y | P73: PUNE | Q73: OPEN | R73: Group 2: Firm Offer | S73: 100 | T73: 120 | U73: =+S73+T73 -> 220 | W73: Yes | X73: Yes | Y73: =+IF(AO73="Approved","Yes",AS73) -> 46447 | Z73: Yet to Initiate | AD73: =+AL73 -> 46419 | AE73: =+AS73 -> 46447 | AF73: Yes | AG73: NA | AH73: NA | AI73: Yes | AJ73: Pending | AL73: 46419 | AM73: Pending | AN73: Pending | AO73: To be Initiated | AP73: No | AR73: MSRDC NOC awaited, Site can be commissioned after MSIDC NOC. LSR assigned to AN | AS73: 46447 | AT73: Yes | AU73: Yes | AV73: Expressway location , Applied for MSRDC , Revised PESO construction approval pending | AW73: No | AX73: Yes | AY73: Yes | AZ73: Applied | BA73: Applied | BB73: Applied | BC73: Received | BD73: Received | BE73: NA | BF73: NA | BG73: In Process | BH73: WIP | BI73: 46753 | BJ73: 46784 | BK73: Yes | BL73: To be applied | BN73: Pending | BW73: Pending | BZ73: AN on 08.04.2026 | CA73: Received | CB73: SRMP 2018-19 | CC73: Yes | CD73: Yes | CI73: =TEXT(M73,"MMM'YY") -> Nov'22 | CJ73: Open | CL73: Yes
A74: 188 | B74: Village Murti (Taluka Baramati) on National Highway 965D | C74: VIKRAMSINHA BABANRAO JAGADALE | D74: Pune Tathawade RSA | E74: 1893 | F74: 9637118817 | G74: D1 | H74: A | I74: RO | J74: RO A Site | K74: R/2024/IN002458/MAH/000227/3203/00056 | L74: 2023-24 | M74: 45461 | N74: =+TODAY()-M74 -> 716 | O74: =+IF(N74<180,"0-6M",IF(N74<365,"6-12M",IF(N74<730,"1-2Y",IF(N74<1095,"2-3Y",IF(N74<1460,"3-4Y",IF(N74<1825,"4-5Y",IF(N74>1825,">5Y"))))))) -> 1-2Y | P74: PUNE | Q74: OPEN | R74: Group 1: Owned land | S74: 40 | T74: 110 | U74: =+S74+T74 -> 150 | W74: Yes | X74: Yes | Z74: Yet to Initiate | AD74: =+AL74 -> 46419 | AE74: =+AS74 -> 46447 | AF74: Yes | AG74: NA | AH74: NA | AI74: Yes | AJ74: Pending | AL74: 46419 | AM74: Yes | AN74: Pending | AO74: To be Initiated | AP74: No | AR74: Negotiation Pending | AS74: 46447 | AT74: Yes | AU74: Yes | AV74: TP applied, Tentative NA pending , NH NOC pending, LSR submitted, Valuation Done, Negotiation pending | AW74: No | AX74: Yes | AY74: Yes | AZ74: Applied | BA74: Applied | BB74: Applied | BC74: Received | BD74: Received | BE74: NA | BF74: NA | BG74: Received | BH74: WIP | BI74: 46357 | BJ74: 46388 | BK74: Yes | BL74: Received | BN74: Pending | BW74: Pending | CA74: Received | CB74: SRMP 2023-24 | CC74: Yes | CD74: Yes | CI74: =TEXT(M74,"MMM'YY") -> Jun'24 | CJ74: Open | CK74: Yes | CL74: Yes
A75: 236 | B75: From Garade to Khed Shivapur on Khed-Shivapur-Saswad Link Road | C75: VAIBHAV NARENDRA LODHA | D75: Pune Saswad RSA | E75: 2102 | F75: 9764499799 | G75: E | H75: B | I75: KSK | J75: KSK-B w/o Reco | K75: R/2025/IN000076/MAH/000008/3203/00001 | L75: 2023-24 | M75: 45776 | N75: =+TODAY()-M75 -> 401 | O75: =+IF(N75<180,"0-6M",IF(N75<365,"6-12M",IF(N75<730,"1-2Y",IF(N75<1095,"2-3Y",IF(N75<1460,"3-4Y",IF(N75<1825,"4-5Y",IF(N75>1825,">5Y"))))))) -> 1-2Y | P75: Pune | Q75: OPEN | R75: Group 1: Owned land | S75: 25 | T75: 50 | U75: =+S75+T75 -> 75 | W75: Yes | X75: Yes | Z75: NA | AD75: =+AL75 -> 46419 | AE75: =+AS75 -> 46447 | AF75: Yes | AG75: NA | AH75: NA | AI75: Not Required | AJ75: Not Required | AL75: 46419 | AM75: Yes | AN75: Yes | AO75: To be Initiated | AP75: No | AR75: LSR Awaited | AS75: 46447 | AT75: Yes | AU75: Yes | AW75: NA | AX75: Yes | AY75: Yes | AZ75: Applied | BA75: Applied | BB75: Applied | BC75: Applied | BD75: Applied | BE75: NA | BF75: NA | BG75: In Process | BH75: WIP | BI75: 46419 | BJ75: 46447 | BK75: Yes | BL75: Received | BW75: Pending | BZ75: AN on 08.04.2026 | CB75: SRMP 2023-24 | CC75: Yes | CD75: Yes | CI75: =TEXT(M75,"MMM'YY") -> Apr'25 | CJ75: Open | CK75: Yes | CL75: Yes
A76: 251 | B76: Nashik Phata to Moshi Toll on Pune Nashik Road LHS | C76: SACHIN BITAKUL BHOSALE | D76: Pimpri Chinchwad RSA | E76: 1861 | F76: 8208678882 | G76: A | H76: A | I76: RO | J76: RO A Site-Corpu | K76: R/2025/IN000445/MAH/000061/3203/00016 | L76: 2023-24 | M76: 45911 | N76: =+TODAY()-M76 -> 266 | O76: =+IF(N76<180,"0-6M",IF(N76<365,"6-12M",IF(N76<730,"1-2Y",IF(N76<1095,"2-3Y",IF(N76<1460,"3-4Y",IF(N76<1825,"4-5Y",IF(N76>1825,">5Y"))))))) -> 6-12M | P76: PUNE | Q76: ST | R76: Group 2: Firm Offer | S76: 100 | T76: 100 | U76: =+S76+T76 -> 200 | W76: Yes | X76: Yes | Z76: Yet to Initiate | AD76: =+AL76 -> 46388 | AE76: =+AS76 -> 46447 | AF76: Yes | AG76: NA | AH76: NA | AI76: In Process | AJ76: Pending | AL76: 46388 | AM76: Pending | AN76: Pending | AO76: To be Initiated | AP76: No | AR76: LSR asigned to AN | AS76: 46447 | AT76: Yes | AU76: Yes | BG76: In Process | BI76: 46357 | BJ76: 46388 | BK76: No | BL76: To be applied | BN76: Pending | BW76: Pending | BZ76: AN on 08.04.2026 | CA76: Firodia and Phadtade on 080426 | CB76: SRMP 2023-24 | CC76: Yes | CD76: Yes | CI76: =TEXT(M76,"MMM'YY") -> Sep'25 | CJ76: st | CL76: Yes
A77: 254 | B77: From Talegaon Dabhade Phata to Vadgaon on NH(Pune-Bangalore Highway) | C77: SUPRIYA PRAVIN CHAVAN | D77: Pune Tathawade RSA | E77: 1642 | F77: 8655755595 | G77: D1 | H77: A | I77: RO | J77: RO A Site | K77: R/2025/IN000656/MAH/000084/3203/00019 | L77: 2023-24 | M77: 45997 | N77: =+TODAY()-M77 -> 180 | O77: =+IF(N77<180,"0-6M",IF(N77<365,"6-12M",IF(N77<730,"1-2Y",IF(N77<1095,"2-3Y",IF(N77<1460,"3-4Y",IF(N77<1825,"4-5Y",IF(N77>1825,">5Y"))))))) -> 6-12M | P77: PUNE | Q77: OPEN | R77: Group 1: Owned land | S77: 50 | T77: 200 | U77: =+S77+T77 -> 250 | W77: Yes | X77: Yes | Z77: Yet to Initiate | AD77: =+AL77 -> 46419 | AE77: =+AS77 -> 46447 | AF77: Yes | AG77: NA | AH77: NA | AI77: Yes | AJ77: Pending | AL77: 46419 | AM77: Pending | AN77: Pending | AO77: To be Initiated | AP77: No | AS77: 46447 | AT77: Yes | AU77: Yes | AV77: TP applied, Tentative NA pending , NH NOC pending | AW77: No | AX77: Yes | AY77: Yes | AZ77: Applied | BA77: Applied | BB77: Applied | BC77: Received | BD77: Received | BE77: NA | BF77: NA | BG77: In Process | BH77: WIP | BI77: 46357 | BJ77: 46388 | BK77: Yes | BL77: Received | BN77: Pending | BW77: Pending | BZ77: AN on 08.04.2026 | CA77: Received | CB77: SRMP 2023-24 | CC77: Yes | CD77: Yes | CI77: =TEXT(M77,"MMM'YY") -> Dec'25 | CJ77: Open | CK77: Yes | CL77: Yes
A78: 263 | B78: From Pabal to Kanhur Mesai on SH (Shirur-Pabal Road) | C78: KISHOREKUMAR SHRIRAM MANDALE | D78: Pune Wagholi RSA | E78: 1744 | F78: 9975845625 | G78: D2 | H78: B | I78: RO | J78: RO B Site | K78: R/2025/IN000820/MAH/000093/3203/00025 | L78: 2023-24 | M78: 46071 | N78: =+TODAY()-M78 -> 106 | O78: =+IF(N78<180,"0-6M",IF(N78<365,"6-12M",IF(N78<730,"1-2Y",IF(N78<1095,"2-3Y",IF(N78<1460,"3-4Y",IF(N78<1825,"4-5Y",IF(N78>1825,">5Y"))))))) -> 0-6M | P78: PUNE | Q78: OBC | R78: Group 1: Owned land | S78: 30 | T78: 70 | U78: =+S78+T78 -> 100 | W78: Yes | X78: Yes | Z78: NA | AD78: 46388 | AE78: 46447 | AF78: Yes | AG78: NA | AH78: NA | AI78: Not Required | AJ78: Not Required | AL78: 46419 | AM78: Pending | AO78: To be Initiated | AP78: No | AS78: Yes | AT78: Yes | AU78: Yes | AV78: New LOI | AX78: NO | AY78: Applied | AZ78: Yet to applied | BA78: Yet to applied | BB78: Yet to applied | BC78: Yet to applied | BD78: Yet to applied | BE78: NA | BF78: NA | BG78: Yet to Assign | BH78: No | BI78: 46445 | BJ78: 46447 | BK78: Yes | BL78: To be applied | BW78: Pending | CB78: SRMP 2023-24 | CC78: Yes | CD78: Yes | CI78: =TEXT(M78,"MMM'YY") -> Feb'26 | CJ78: OBC | CK78: Yes | CL78: Yes
A79: 198 | B79: Between KM Stone 8 to 10 on RHS while going from Patas to Baramati on NH965G | C79: SANTOSH MADHUKAR DORGE | D79: Pune Hadapsar RSA | E79: 1899 | F79: 9881031111 | G79: D1 | H79: A | I79: RO | J79: RO A Site | K79: R/2024/IN002484/MAH/000234/3203/00063 | L79: 2023-24 | M79: 45462 | N79: =+TODAY()-M79 -> 715 | O79: =+IF(N79<180,"0-6M",IF(N79<365,"6-12M",IF(N79<730,"1-2Y",IF(N79<1095,"2-3Y",IF(N79<1460,"3-4Y",IF(N79<1825,"4-5Y",IF(N79>1825,">5Y"))))))) -> 1-2Y | P79: PUNE | Q79: OPEN | R79: Group 1: Owned land | S79: 30 | T79: 120 | U79: =+S79+T79 -> 150 | W79: Yes | X79: Yes But not in 26-27 | Y79: =+IF(AO79="Approved","Yes",AS79) -> 46539 | Z79: Yet to Initiate | AD79: =+AL79 -> 46539 | AE79: =+AS79 -> 46539 | AF79: Yes | AI79: Assigned to IAS and MA | AJ79: Pending | AL79: 46539 | AR79: very Slow Candidate | AS79: 46539 | AT79: Yes | AU79: Yes but in next FY | AV79: PESO Prior Change required | AW79: NA | AX79: No | AY79: Applied | AZ79: Applied | BA79: Yet to Apply | BB79: Yet to Apply | BC79: Yet to Apply | BD79: NA | BE79: NA | BF79: NA | BG79: Yet to Assign | BH79: WIP | BI79: 46295 | BJ79: 46415 | BK79: Yes | BL79: Received | BW79: Pending | CB79: SRMP 2023-24 | CC79: Yes | CI79: =TEXT(M79,"MMM'YY") -> Jun'24 | CJ79: Open
A80: 197 | B80: From Pimpale to Nannaj Dumala on Talegaon Dighe Nandur Shingote NH | C80: VIJAY MARUTI MOKAL | D80: Shirdi RSA | E80: 2087 | F80: 9850883072 | G80: D1 | H80: A | I80: RO | J80: RO A Site-Corpu | K80: R/2024/IN002490/MAH/000238/3203/00067 | L80: 2023-24 | M80: 45462 | N80: =+TODAY()-M80 -> 715 | O80: =+IF(N80<180,"0-6M",IF(N80<365,"6-12M",IF(N80<730,"1-2Y",IF(N80<1095,"2-3Y",IF(N80<1460,"3-4Y",IF(N80<1825,"4-5Y",IF(N80>1825,">5Y"))))))) -> 1-2Y | P80: AHMADNAGAR | Q80: SC | R80: Group 1: Owned land | S80: 30 | T80: 120 | U80: =+S80+T80 -> 150 | W80: Yes | X80: Yes But not in 26-27 | Y80: =+IF(AO80="Approved","Yes",AS80) -> 46539 | Z80: Yet to Initiate | AD80: =+AL80 -> 46539 | AE80: =+AS80 -> 46539 | AF80: Yes | AI80: Yes | AJ80: Pending | AL80: 46539 | AM80: To be Provided | AN80: Estimate shall be provided after receiving approved concept note | AR80: Very Slow Candidate | AS80: 46539 | AT80: Yes | AU80: Yes but in next FY | AV80: Slow Candidate | AW80: NA | AX80: Yes | AY80: Recieved | AZ80: Applied | BA80: Recieved | BB80: Applied | BC80: Recived | BD80: NA | BE80: Recived | BF80: Recived | BG80: Yet to Assign | BH80: No | BI80: 46418 | BJ80: 46538 | BK80: Yes | BW80: Pending | CB80: SRMP 2023-24 | CC80: Yes | CI80: =TEXT(M80,"MMM'YY") -> Jun'24 | CJ80: SC
A81: 257 | B81: On RHS From Kamshet to Karla on NH (Pune-Bangalore Highway) | C81: PRAVIN GAJANAN CHAUGULE | D81: Pune Tathawade RSA | E81: 1807 | F81: 9422740000 | G81: D1 | H81: A | I81: RO | J81: RO A Site-Corpu | K81: R/2025/IN000816/MAH/000090/3203/00022 | L81: 2023-24 | M81: 46070 | N81: =+TODAY()-M81 -> 107 | O81: =+IF(N81<180,"0-6M",IF(N81<365,"6-12M",IF(N81<730,"1-2Y",IF(N81<1095,"2-3Y",IF(N81<1460,"3-4Y",IF(N81<1825,"4-5Y",IF(N81>1825,">5Y"))))))) -> 0-6M | P81: PUNE | Q81: SC | R81: Group 1: Owned land | S81: 45 | T81: 220 | U81: =+S81+T81 -> 265 | W81: Yes | X81: Yes But not in 26-27 | Z81: Yet to Initiate | AD81: =+AL81 -> 46539 | AE81: =+AS81 -> 46539 | AF81: Yes | AL81: 46539 | AS81: 46539 | AT81: Yes | AU81: Yes but in next FY | AV81: Greenbelt issue in the old Pune Mumbai Highway , Revised Mojini Applied | AW81: No | AX81: Yes | AY81: Yes | AZ81: Applied | BA81: Applied | BB81: Applied | BC81: Applied | BD81: Received | BE81: NA | BF81: NA | BG81: Received | BH81: WIP | BI81: 46357 | BJ81: 46388 | BK81: Yes | BL81: Recived | BW81: Pending | BZ81: AN on 26.05.2026 | CB81: SRMP 2023-24 | CC81: Yes | CI81: =TEXT(M81,"MMM'YY") -> Feb'26 | CJ81: SC
A82: 259 | B82: From Sahajpur Phata to Khamgaon Phata on RHS of PUNE SOLAPUR NH | C82: SHRI SANTUJI NIVRUTTI KAMBLE | D82: Pune Hadapsar RSA | E82: 1750 | F82: 9082061998 | G82: D1 | H82: A | I82: RO | J82: RO A Site-Corpu | K82: R/2025/IN000822/MAH/000095/3203/00027 | L82: 2023-24 | M82: 46071 | N82: =+TODAY()-M82 -> 106 | O82: =+IF(N82<180,"0-6M",IF(N82<365,"6-12M",IF(N82<730,"1-2Y",IF(N82<1095,"2-3Y",IF(N82<1460,"3-4Y",IF(N82<1825,"4-5Y",IF(N82>1825,">5Y"))))))) -> 0-6M | P82: PUNE | Q82: CC-1 PMP/GOVT.EMPL | R82: Group 2: Firm Offer | S82: 40 | T82: 158 | U82: =+S82+T82 -> 198 | W82: Yes | X82: Yes But not in 26-27 | Z82: Yet to Initiate | AD82: =+AL82 -> 46539 | AE82: =+AS82 -> 46539 | AF82: Yes | AL82: 46539 | AR82: Very Slow Candidate | AS82: 46539 | AT82: Yes | AU82: Yes but in next FY | AV82: NA | AW82: NO | AX82: NO | AY82: NA | AZ82: NA | BA82: NA | BB82: NA | BC82: NA | BD82: NA | BE82: NA | BF82: NA | BG82: Yet to Assign | BH82: WIP | BI82: 46415 | BJ82: 46477 | BK82: Moujani Awaited | BL82: Yet to Apply | BW82: Pending | CB82: SRMP 2023-24 | CC82: Yes | CI82: =TEXT(M82,"MMM'YY") -> Feb'26 | CJ82: SC
A83: 30 | B83: ON SH 45 BETWEEN KM STONE NO. 3 & 8 | C83: MAHESH ADHAV | D83: Shirdi RSA | F83: 9422250439 | G83: D2 | H83: A | I83: RO | J83: RO A Site-Corpu | K83: M/2020/IN000066/MAH/000007/3203/00006 | L83: 2018-19 | M83: 43949 | N83: =+TODAY()-M83 -> 2228 | O83: =+IF(N83<180,"0-6M",IF(N83<365,"6-12M",IF(N83<730,"1-2Y",IF(N83<1095,"2-3Y",IF(N83<1460,"3-4Y",IF(N83<1825,"4-5Y",IF(N83>1825,">5Y"))))))) -> >5Y | P83: AHMADNAGAR | Q83: SC | R83: Group 2: Firm Offer | S83: 30 | T83: 120 | U83: =+S83+T83 -> 150 | W83: Yes | X83: Yes But not in 26-27 | Z83: Yet to Initiate | AD83: =+AL83 -> 46539 | AE83: =+AS83 -> 46569 | AF83: Yes | AG83: Land Not Available due to RLY DPR issue | AL83: 46539 | AM83: To be Provided | AN83: Estimate shall be provided after receiving approved concept note | AR83: Land Issue due to Railway acquisition | AS83: 46569 | AT83: Yes | AU83: Yes but in next FY | AV83: DPR of railway awaited as the land may go in railway construction area. | AW83: No | AX83: Yes | AY83: Yet to apply. | AZ83: Yet to apply | BA83: Yet to apply | BB83: Yet to apply | BC83: Yet to apply | BD83: Yet to apply | BE83: Yet to apply | BF83: Yet to apply | BG83: Yet to apply | BH83: No | BI83: 46721 | BJ83: 46812 | BK83: Moujani Awaited | BL83: Yet to Apply | BW83: Pending | CB83: SRMP 2018-19 | CC83: Yes | CI83: =TEXT(M83,"MMM'YY") -> Apr'20 | CJ83: SC
A84: 51 | B84: VILLAGE SHENOLI ON KARAD TASGAON ROAD ON NH266 , | C84: ASHOK BHAGWAN LOKHANDE | D84: Satara West RSA | F84: 9096420232 | G84: D1 | H84: A | I84: RO | J84: RO A Site-Corpu | K84: M/2022/IN001167/MAH/000067/3203/00019 | L84: 2018-19 | M84: 44865 | N84: =+TODAY()-M84 -> 1312 | O84: =+IF(N84<180,"0-6M",IF(N84<365,"6-12M",IF(N84<730,"1-2Y",IF(N84<1095,"2-3Y",IF(N84<1460,"3-4Y",IF(N84<1825,"4-5Y",IF(N84>1825,">5Y"))))))) -> 3-4Y | P84: SATARA | Q84: CC-1 DEFENCE | R84: Group 1: Owned land | S84: 30 | T84: 125 | U84: =+S84+T84 -> 155 | W84: Yes | X84: Yes But not in 26-27 | Z84: Yet to Initiate | AD84: =+AL84 -> 46539 | AE84: =+AS84 -> 46569 | AF84: Yes | AL84: 46539 | AR84: Very Slow Candidate | AS84: 46569 | AT84: YES | AU84: Yes but in next FY | AV84: Slow candidate, No such sufficient progress in any other NOC except Health and MSEB | AW84: NA | AX84: YES | AY84: Received | AZ84: Applied | BA84: Applied | BB84: Yet to Apply | BC84: Received | BD84: NA | BE84: NA | BF84: NA | BG84: In process. Lawyer has given list of document | BH84: No | BI84: 46568 | BJ84: 46599 | BK84: Yes | BL84: Recived | BW84: Pending | CB84: SRMP 2018-19 | CC84: Yes | CI84: =TEXT(M84,"MMM'YY") -> Oct'22 | CJ84: SC
A85: 149 | B85: From Pokhari to Rajpur on SH on RHS on Manchar Bhimshankar road | C85: GANESH RAMCHANDRA TITKARE. | D85: Pune Wagholi RSA | E85: 1923 | F85: 8010347872 | G85: D2 | H85: A | I85: RO | J85: RO A Site-Corpu | K85: R/2023/IN006223/MAH/000582/3203/00171 | L85: 2023-24 | M85: 45366 | N85: =+TODAY()-M85 -> 811 | O85: =+IF(N85<180,"0-6M",IF(N85<365,"6-12M",IF(N85<730,"1-2Y",IF(N85<1095,"2-3Y",IF(N85<1460,"3-4Y",IF(N85<1825,"4-5Y",IF(N85>1825,">5Y"))))))) -> 2-3Y | P85: PUNE | Q85: ST | R85: Group 1: Owned land | S85: 40 | T85: 76 | U85: =+S85+T85 -> 116 | W85: Yes | X85: Yes But not in 26-27 | Z85: Yet to Initiate | AD85: =+AL85 -> 46539 | AE85: =+AS85 -> 46569 | AF85: Yes | AI85: Yes | AJ85: Pending | AL85: 46539 | AM85: Pending | AN85: Pending | AO85: Pending | AR85: Very slow Candidate | AS85: 46569 | AT85: Yes | AU85: No | AV85: Issue in mauzni ,New Mauzni awited | AW85: No | AX85: No | AY85: Applied | AZ85: Yet to applied | BA85: Yet to applied | BB85: Not Required | BK85: Moujani Awaited | BL85: Yet to Apply | BW85: Pending | CB85: SRMP 2023-24 | CC85: Yes | CI85: =TEXT(M85,"MMM'YY") -> Mar'24 | CJ85: st
A86: 202 | B86: From Ravet to Malavli on Pune Mumbai Expressway | C86: SARITA RAHUL BADOLE | D86: Pune Tathawade RSA | E86: 2028 | F86: 9834486238 | G86: D1 | H86: A | I86: RO | J86: RO A Site | K86: R/2024/IN002488/MAH/000236/3203/00065 | L86: 2023-24 | M86: 45462 | N86: =+TODAY()-M86 -> 715 | O86: =+IF(N86<180,"0-6M",IF(N86<365,"6-12M",IF(N86<730,"1-2Y",IF(N86<1095,"2-3Y",IF(N86<1460,"3-4Y",IF(N86<1825,"4-5Y",IF(N86>1825,">5Y"))))))) -> 1-2Y | P86: PUNE | Q86: OPEN | R86: Group 1: Owned land | S86: 90 | T86: 110 | U86: =+S86+T86 -> 200 | W86: Yes | X86: Yes But not in 26-27 | Z86: Yet to Initiate | AD86: =+AL86 -> 46539 | AE86: =+AS86 -> 46569 | AF86: Yes | AL86: 46539 | AS86: 46569 | AT86: Yes | AU86: Yes but in next FY | AV86: Expressway location , Applied for MSRDC | AW86: No | AX86: Yes | AY86: Yes | AZ86: Applied | BA86: Applied | BB86: Applied | BC86: Applied | BD86: Received | BE86: NA | BF86: NA | BG86: Yet to Assign | BH86: WIP | BI86: 46753 | BJ86: 46784 | BK86: Yes | BL86: #N/A | BW86: Pending | CB86: SRMP 2023-24 | CC86: Yes | CI86: =TEXT(M86,"MMM'YY") -> Jun'24 | CJ86: Open
A87: 210 | B87: From Bhanashiware to Soundala on Nevasa-Shevgaon SH | C87: SANJAY TUKARAM PAWARA | D87: Ahmednagar East RSA | E87: 1794 | F87: 7722014513 | G87: D2 | H87: A | I87: RO | J87: RO A Site-Corpu | K87: R/2024/IN002783/MAH/000311/3203/00094 | L87: 2023-24 | M87: 45479 | N87: =+TODAY()-M87 -> 698 | O87: =+IF(N87<180,"0-6M",IF(N87<365,"6-12M",IF(N87<730,"1-2Y",IF(N87<1095,"2-3Y",IF(N87<1460,"3-4Y",IF(N87<1825,"4-5Y",IF(N87>1825,">5Y"))))))) -> 1-2Y | P87: AHMADNAGAR | Q87: ST | R87: Group 2: Firm Offer | S87: 35 | T87: 90 | U87: =+S87+T87 -> 125 | W87: Yes | X87: Yes But not in 26-27 | Z87: Yet to Initiate | AD87: =+AL87 -> 46539 | AE87: =+AS87 -> 46569 | AF87: Yes | AG87: NA | AH87: NA | AL87: 46539 | AM87: To be Provided | AN87: Estimate shall be provided after receiving approved concept note | AR87: Slow Candidate | AS87: 46569 | AT87: Yes | AU87: Yes but in next FY | AX87: Yes | AY87: Received | AZ87: Yet to apply | BA87: Applied | BB87: Applied | BC87: Applied | BD87: na | BE87: Applied | BF87: Applied | BG87: Yet To assign | BK87: Yes | BW87: Pending | CB87: SRMP 2023-24 | CC87: Yes | CI87: =TEXT(M87,"MMM'YY") -> Jul'24 | CJ87: st
A88: 228 | B88: ON NH-4 RHS FROM PUNE TO SATARA BETWEEN KM STONE 760 TO 755 | C88: SHUBHANGI PRAKASH GAIKWAD | D88: Satara West RSA | F88: 9922935234 | G88: D1 | H88: A | I88: RO | J88: RO A Site-Corpu | K88: M/2024/IN004281/MAH/000436/3203/00120 | L88: 2018-19 | M88: 45632 | N88: =+TODAY()-M88 -> 545 | O88: =+IF(N88<180,"0-6M",IF(N88<365,"6-12M",IF(N88<730,"1-2Y",IF(N88<1095,"2-3Y",IF(N88<1460,"3-4Y",IF(N88<1825,"4-5Y",IF(N88>1825,">5Y"))))))) -> 1-2Y | P88: SATARA | Q88: SC | R88: Group 2: Firm Offer | S88: 40 | T88: 110 | U88: =+S88+T88 -> 150 | W88: Yes | X88: Yes But not in 26-27 | Z88: Yet to Initiate | AD88: =+AL88 -> 46539 | AE88: =+AS88 -> 46569 | AF88: Yes | AL88: 46539 | AS88: 46569 | AT88: YES | AU88: Yes but in next FY | AV88: Layout prepared recently, NA process yet to be initiated | AW88: NA | AX88: YES | AY88: Received | AZ88: Yet to Apply | BA88: Applied | BB88: Yet to Apply | BC88: Applied | BD88: NA | BE88: NA | BF88: NA | BG88: Yet to Assign | BH88: No | BI88: 46568 | BJ88: 46599 | BK88: Yes | BL88: Recived | BW88: Pending | CB88: SRMP 2018-19 | CC88: Yes | CI88: =TEXT(M88,"MMM'YY") -> Dec'24 | CJ88: SC
A89: 231 | B89: From Mayani To Katarkhatav on Mayani Dahiwadi Road | C89: YOGITA ARUN AHIRE | D89: Satara East RSA | E89: 110 | F89: 7020657052 | G89: D1 | H89: A | I89: RO | J89: RO A Site-Corpu | K89: R/2024/IN004519/MAH/000464/3203/00125 | L89: 2023-24 | M89: 45660 | N89: =+TODAY()-M89 -> 517 | O89: =+IF(N89<180,"0-6M",IF(N89<365,"6-12M",IF(N89<730,"1-2Y",IF(N89<1095,"2-3Y",IF(N89<1460,"3-4Y",IF(N89<1825,"4-5Y",IF(N89>1825,">5Y"))))))) -> 1-2Y | P89: SATARA | Q89: ST | R89: Group 1: Owned land | S89: 30 | T89: 120 | U89: =+S89+T89 -> 150 | W89: Yes | X89: Yes But not in 26-27 | Z89: Yet to Initiate | AD89: =+AL89 -> 46539 | AE89: =+AS89 -> 46569 | AF89: Yes | AL89: 46539 | AR89: No Progress in NOC | AS89: 46569 | AT89: Yes | AU89: Yes but in next FY | AV89: Slow condidate,NA applied but yet to be done,Condidate not responding on phone calls | AW89: NA | AX89: No | AY89: Received | AZ89: Applied | BA89: Yet to apply | BB89: Yet to apply | BC89: Yet to apply | BD89: NA | BE89: NA | BF89: NA | BG89: Received | BH89: NA | BI89: 46568 | BJ89: 46595 | BK89: Yes | BW89: Pending | CA89: VAC and Gosavi on 25.05.2026 | CB89: SRMP 2023-24 | CC89: Yes | CI89: =TEXT(M89,"MMM'YY") -> Jan'25 | CJ89: st
A90: 235 | B90: From KM stone 749 to 747 On RHS of Pune To Satara NH | C90: VISHAL SHIVAJI SONVANE | D90: Satara West RSA | E90: 1825 | F90: 8329813327 | G90: D1 | H90: A | I90: RO | J90: RO A Site-Corpu | K90: R/2024/IN004865/MAH/000491/3203/00132 | L90: 2023-24 | M90: 45742 | N90: =+TODAY()-M90 -> 435 | O90: =+IF(N90<180,"0-6M",IF(N90<365,"6-12M",IF(N90<730,"1-2Y",IF(N90<1095,"2-3Y",IF(N90<1460,"3-4Y",IF(N90<1825,"4-5Y",IF(N90>1825,">5Y"))))))) -> 1-2Y | P90: SATARA | Q90: SC | R90: Group 1: Owned land | S90: 40 | T90: 160 | U90: =+S90+T90 -> 200 | W90: Yes | X90: Yes But not in 26-27 | Z90: Yet to Initiate | AD90: =+AL90 -> 46539 | AE90: =+AS90 -> 46569 | AF90: Yes | AL90: 46539 | AR90: very slow candidate | AS90: 46569 | AT90: YES | AU90: Yes but in next FY | AV90: No much porgess as of now in NA which is a major requisite, LSR etc | AW90: NA | AX90: YES | AY90: Received | AZ90: Applied | BA90: Applied | BB90: Yet to Apply | BC90: Received | BD90: NA | BE90: NA | BF90: NA | BG90: Yet to Assign | BH90: NO | BI90: 46568 | BJ90: 46599 | BK90: Moujani Awaited | BL90: Yet to Apply | BW90: Pending | CB90: SRMP 2023-24 | CC90: Yes | CI90: =TEXT(M90,"MMM'YY") -> Mar'25 | CJ90: SC
A91: 244 | B91: From KM stone 75 to KM stone 85 on Pune Solapur Highway | C91: SAGAR ASHOK SALVE | D91: Pune Hadapsar RSA | E91: 1856 | F91: 9763715716 | G91: D1 | H91: A | I91: RO | J91: RO A Site-Corpu | K91: R/2025/IN000253/MAH/000032/3203/00008 | L91: 2023-24 | M91: 45839 | N91: =+TODAY()-M91 -> 338 | O91: =+IF(N91<180,"0-6M",IF(N91<365,"6-12M",IF(N91<730,"1-2Y",IF(N91<1095,"2-3Y",IF(N91<1460,"3-4Y",IF(N91<1825,"4-5Y",IF(N91>1825,">5Y"))))))) -> 6-12M | P91: PUNE | Q91: SC | R91: Group 1: Owned land | S91: 30 | T91: 157 | U91: =+S91+T91 -> 187 | W91: Yes | X91: Yes But not in 26-27 | Z91: Yet to Initiate | AD91: =+AL91 -> 46539 | AE91: =+AS91 -> 46569 | AF91: Yes | AL91: 46539 | AR91: Very Slow Candidate | AS91: 46569 | AT91: Yes | AU91: Yes but in next FY | AV91: Financially Stressed Candidate | AW91: NA | AX91: Yes | AY91: Yes | AZ91: Yet to Apply | BA91: Yet to apply | BB91: Yet to apply | BC91: Yet to apply | BD91: Applied | BE91: NA | BF91: NA | BK91: Yes | BL91: Recived | BW91: Pending | CB91: SRMP 2023-24 | CC91: Yes | CI91: =TEXT(M91,"MMM'YY") -> Jul'25 | CJ91: SC
A92: 248 | B92: From Antarwali Khurd she. to Kurudgaon on Bodhegaon Road | C92: SHARAD DEVIDAS GHODAKE | D92: Ahmednagar East RSA | E92: 86 | F92: 9657436679 | G92: E | H92: A | I92: KSK | J92: KSK-A w/o Reco | K92: R/2025/IN000330/MAH/000049/3203/00012 | L92: 2023-24 | M92: 45868 | N92: =+TODAY()-M92 -> 309 | O92: =+IF(N92<180,"0-6M",IF(N92<365,"6-12M",IF(N92<730,"1-2Y",IF(N92<1095,"2-3Y",IF(N92<1460,"3-4Y",IF(N92<1825,"4-5Y",IF(N92>1825,">5Y"))))))) -> 6-12M | P92: AHMADNAGAR | Q92: SC | R92: Group 1: Owned land | S92: 20 | T92: 50 | U92: =+S92+T92 -> 70 | W92: Yes | X92: Yes But not in 26-27 | Z92: Yet to Initiate | AD92: =+AL92 -> 46539 | AE92: =+AS92 -> 46569 | AF92: Yes | AG92: NA | AH92: NA | AL92: 46539 | AM92: Slow Candidate | AR92: Slow Candidate | AS92: 46569 | AT92: Yes | AU92: Yes but in next FY | AX92: Yes | AY92: Yes | AZ92: Yet to Apply | BA92: Yet to Apply | BB92: Yet to Apply | BC92: Applied | BD92: NA | BE92: Applied | BF92: Applied | BG92: Yet To assign | BK92: Moujani Awaited | BL92: Yet to Apply | BW92: Pending | CB92: SRMP 2023-24 | CC92: Yes | CI92: =TEXT(M92,"MMM'YY") -> Jul'25 | CJ92: SC
A93: 252 | B93: From KM stone 52 to KM stone 56 ON LHS OF PUNE SOLAPUR NH | C93: VIJAY WAMAN MASURE | D93: Pune Hadapsar RSA | E93: 1590 | F93: 9021613733 | G93: D1 | H93: A | I93: RO | J93: RO A Site-Corpu | K93: R/2025/IN000573/MAH/000076/3203/00017 | L93: 2023-24 | M93: 45961 | N93: =+TODAY()-M93 -> 216 | O93: =+IF(N93<180,"0-6M",IF(N93<365,"6-12M",IF(N93<730,"1-2Y",IF(N93<1095,"2-3Y",IF(N93<1460,"3-4Y",IF(N93<1825,"4-5Y",IF(N93>1825,">5Y"))))))) -> 6-12M | P93: PUNE | Q93: SC | R93: Group 2: Firm Offer | S93: 37 | T93: 120 | U93: =+S93+T93 -> 157 | W93: Yes | X93: Yes But not in 26-27 | Z93: Yet to Initiate | AD93: =+AL93 -> 46539 | AE93: =+AS93 -> 46569 | AF93: Yes | AL93: 46539 | AR93: Land is not available with Candidate | AS93: 46569 | AT93: Yes | AU93: No | AV93: Land is not available with Candidate | AW93: No | AX93: NA | AY93: NA | AZ93: NA | BA93: NA | BB93: NA | BC93: NA | BD93: NA | BE93: NA | BF93: NA | BG93: NA | BH93: NA | BI93: NA | BJ93: NA | BW93: Pending | CB93: SRMP 2023-24 | CC93: Yes | CI93: =TEXT(M93,"MMM'YY") -> Oct'25 | CJ93: SC
A94: 260 | B94: From Km stone 715 to 720 on LHS on Karad to Satara Road | C94: SURESH PANDURANG RANDIVE | D94: Satara West RSA | E94: 1678 | F94: 9552595582 | G94: D1 | H94: A | I94: RO | J94: RO A Site-Corpu | K94: R/2025/IN000818/MAH/000092/3203/00024 | L94: 2023-24 | M94: 46071 | N94: =+TODAY()-M94 -> 106 | O94: =+IF(N94<180,"0-6M",IF(N94<365,"6-12M",IF(N94<730,"1-2Y",IF(N94<1095,"2-3Y",IF(N94<1460,"3-4Y",IF(N94<1825,"4-5Y",IF(N94>1825,">5Y"))))))) -> 0-6M | P94: SATARA | Q94: SC | R94: Group 2: Firm Offer | S94: 40 | T94: 120 | U94: =+S94+T94 -> 160 | W94: Yes | X94: Yes But not in 26-27 | Z94: Yet to Initiate | AD94: =+AL94 -> 46539 | AE94: =+AS94 -> 46569 | AF94: Yes | AL94: 46539 | AS94: 46569 | AT94: YES | AU94: Yes but in next FY | AV94: Freshly issued LOI, All procedure to be started | AW94: NA | AX94: NO | AY94: Received | AZ94: Yet to Apply | BA94: Yet to Apply | BB94: Yet to Apply | BC94: Yet to Apply | BD94: NA | BE94: NA | BF94: NA | BG94: Yet to Assign | BH94: NO | BI94: 46568 | BJ94: 46599 | BW94: Pending | CB94: SRMP 2023-24 | CC94: Yes | CI94: =TEXT(M94,"MMM'YY") -> Feb'26 | CJ94: SC
A95: 264 | B95: Within 5 Km from Sai Anand Lawns towards Pune on Pune-Aurangabad NH | C95: GURUDAS VIJAY PAWARA | D95: Ahmednagar East RSA | E95: 91 | F95: 7972678127 | G95: D1 | H95: A | I95: RO | J95: RO A Site-Corpu | K95: R/2025/IN000871/MAH/000098/3203/00029 | L95: 2023-24 | M95: 46099 | N95: =+TODAY()-M95 -> 78 | O95: =+IF(N95<180,"0-6M",IF(N95<365,"6-12M",IF(N95<730,"1-2Y",IF(N95<1095,"2-3Y",IF(N95<1460,"3-4Y",IF(N95<1825,"4-5Y",IF(N95>1825,">5Y"))))))) -> 0-6M | P95: AHMADNAGAR | Q95: ST | R95: Group 2: Firm Offer | S95: 25 | T95: 125 | U95: =+S95+T95 -> 150 | W95: Yes | X95: Yes But not in 26-27 | Z95: Yet to Initiate | AD95: =+AL95 -> 46539 | AE95: =+AS95 -> 46569 | AF95: Yes | AG95: NA | AH95: NA | AL95: 46539 | AS95: 46569 | AT95: Yes | AU95: Yes but in next FY | AX95: No | AY95: Applied | AZ95: Yet to Apply | BA95: Yet to Apply | BB95: Yet to Apply | BC95: Yet to Apply | BD95: NA | BE95: Yet to Apply | BF95: Yet to Apply | BG95: In Process | BW95: Pending | BZ95: AG on 14.05.2026 | CB95: SRMP 2023-24 | CC95: Yes | CI95: =TEXT(M95,"MMM'YY") -> Mar'26 | CJ95: st
A96: 31 | B96: SARADWADI TO SHIRUR ON PUNE-AHMEDNAGAR ROAD, | C96: GAURAV KALEWAR | D96: Pune Wagholi RSA | F96: 9764750909 | G96: D1 | H96: B | I96: RO | J96: RO B Site | K96: M/2020/IN000088/MAH/000010/3203/00009 | L96: 2018-19 | M96: 43951 | N96: =+TODAY()-M96 -> 2226 | O96: =+IF(N96<180,"0-6M",IF(N96<365,"6-12M",IF(N96<730,"1-2Y",IF(N96<1095,"2-3Y",IF(N96<1460,"3-4Y",IF(N96<1825,"4-5Y",IF(N96>1825,">5Y"))))))) -> >5Y | P96: PUNE | Q96: OBC | R96: Group 1: Owned land | S96: 25 | T96: 130 | U96: =+S96+T96 -> 155 | W96: Yes | X96: Yes But not in 26-27 | AD96: =+AL96 -> 46539 | AE96: =+AS96 -> 46570 | AF96: Yes | AI96: Not Required | AJ96: Not Required | AL96: 46539 | AM96: Yes | AN96: Yes | AR96: Very Slow Candidate | AS96: =+AL96+31 -> 46570 | AT96: Yes | AU96: No | AV96: OlD loi , Financial issue ,Meeting with loi holder is cheduled on 18.05.2026 | AW96: No | AX96: Yes | BB96: 0 | BK96: Yes | BL96: Recived | BM96: NA | BN96: NA | BO96: Not Required | BW96: Pending | CB96: SRMP 2018-19 | CC96: Yes | CI96: =TEXT(M96,"MMM'YY") -> Apr'20 | CJ96: OBC
A97: 43 | B97: KATI(TALUKA-INDAPUR) | C97: TUSHAR BABAN SHENDE | D97: Pune Saswad RSA | F97: 8600400101 | G97: E | H97: B | I97: KSK | J97: KSK-B w/o Reco | K97: M/2021/IN000872/MAH/000049/3203/00015 | L97: 2018-19 | M97: 44417 | N97: =+TODAY()-M97 -> 1760 | O97: =+IF(N97<180,"0-6M",IF(N97<365,"6-12M",IF(N97<730,"1-2Y",IF(N97<1095,"2-3Y",IF(N97<1460,"3-4Y",IF(N97<1825,"4-5Y",IF(N97>1825,">5Y"))))))) -> 4-5Y | P97: PUNE | Q97: OPEN | R97: Group 2: Firm Offer | S97: 6 | T97: 40 | U97: =+S97+T97 -> 46 | W97: Yes | X97: Yes But not in 26-27 | Y97: =+IF(AO97="Approved","Yes",AS97) -> 46570 | AD97: =+AL97 -> 46539 | AE97: =+AS97 -> 46570 | AF97: Yes | AI97: Not Required | AJ97: Not Required | AL97: 46539 | AM97: Yes | AN97: Yes | AR97: Disinterested LOI holder | AS97: =+AL97+31 -> 46570 | AT97: Yes | AU97: Yes but in next FY | AW97: NA | AX97: Yes | AY97: Yes | AZ97: Applied | BA97: Applied | BB97: Applied | BC97: Applied | BD97: Applied | BE97: NA | BF97: NA | BG97: In Process | BH97: No | BI97: 46539 | BJ97: 46569 | BK97: Yes | BL97: Recived | BM97: NA | BN97: NA | BO97: Not Required | BW97: Pending | CB97: SRMP 2018-19 | CC97: Yes | CI97: =TEXT(M97,"MMM'YY") -> Aug'21 | CJ97: Open
A98: 68 | B98: BORIPARDHI (TALUKA-DAUND) | C98: ABHIJIT NITIN TENGLE | D98: Pune Hadapsar RSA | F98: 9503035055 | G98: E | H98: B | I98: KSK | J98: KSK-B w/o Reco | K98: M/2023/IN000176/MAH/000021/3203/00010 | L98: 2018-19 | M98: 45099 | N98: =+TODAY()-M98 -> 1078 | O98: =+IF(N98<180,"0-6M",IF(N98<365,"6-12M",IF(N98<730,"1-2Y",IF(N98<1095,"2-3Y",IF(N98<1460,"3-4Y",IF(N98<1825,"4-5Y",IF(N98>1825,">5Y"))))))) -> 2-3Y | P98: PUNE | Q98: OBC | R98: Group 1: Owned land | S98: 6 | T98: 40 | U98: =+S98+T98 -> 46 | W98: Yes | X98: Yes But not in 26-27 | AD98: =+AL98 -> 46539 | AE98: =+AS98 -> 46570 | AF98: Yes | AG98: Disinterested LOI holder | AI98: Not Required | AJ98: Not Required | AL98: 46539 | AM98: Yes | AN98: Yes | AR98: Very Slow Candidate | AS98: =+AL98+31 -> 46570 | AU98: Yes but in next FY | BK98: Yes | BL98: Recived | BM98: NA | BN98: NA | BO98: Not Required | BW98: Pending | CB98: SRMP 2018-19 | CC98: Yes | CI98: =TEXT(M98,"MMM'YY") -> Jun'23 | CJ98: OBC
A99: 73 | B99: From Shiroli to Rajgurunagar on LHS on NH (Pune-Nashik Road) | C99: RANJENDRA RAMESH SANDBHOR | D99: Pune Wagholi RSA | E99: Pune IV RSA | F99: 9850581349 | G99: D1 | H99: B | I99: RO | J99: RO B Site | K99: R/2023/IN000993/MAH/000075/3203/00023 | L99: 2023-24 | M99: 45258 | N99: =+TODAY()-M99 -> 919 | O99: =+IF(N99<180,"0-6M",IF(N99<365,"6-12M",IF(N99<730,"1-2Y",IF(N99<1095,"2-3Y",IF(N99<1460,"3-4Y",IF(N99<1825,"4-5Y",IF(N99>1825,">5Y"))))))) -> 2-3Y | P99: PUNE | Q99: OPEN | R99: Group 1: Owned land | S99: 30 | T99: 131 | U99: =+S99+T99 -> 161 | W99: Yes | X99: Yes But not in 26-27 | Y99: =+IF(AO99="Approved","Yes",AS99) -> 46570 | AD99: =+AL99 -> 46539 | AE99: =+AS99 -> 46570 | AG99: NOC rejected by DM/NH/PWD | AI99: Not Required | AJ99: Not Required | AL99: 46539 | AM99: Yes | AN99: Yes | AR99: Very Slow Candidate | AS99: =+AL99+31 -> 46570 | AT99: Yes | AU99: Yes but in next FY | AV99: There is a flyover sanctioned at nasik highway Due to that dealer has lost intrest. We are in talking with dealer as it is high potential location | AW99: No | AX99: Yes | AY99: Yes | AZ99: Yes | BB99: 45992 | BK99: Yes | BL99: #N/A | BM99: NA | BN99: NA | BO99: Not Required | BW99: Pending | CB99: SRMP 2023-24 | CC99: Yes | CI99: =TEXT(M99,"MMM'YY") -> Nov'23 | CJ99: Open
A100: 80 | B100: From Surwad to Bawada Police Station on RHS of Indapur-Akluj Road | C100: SWAPNAJA AMARDEEP JAKHALKAR | D100: Pune Saswad RSA | E100: 1655 | F100: 9004917007 | G100: D1 | H100: B | I100: RO | J100: RO B Site | K100: R/2023/IN001438/MAH/000104/3203/00040 | L100: 2023-24 | M100: 45271 | N100: =+TODAY()-M100 -> 906 | O100: =+IF(N100<180,"0-6M",IF(N100<365,"6-12M",IF(N100<730,"1-2Y",IF(N100<1095,"2-3Y",IF(N100<1460,"3-4Y",IF(N100<1825,"4-5Y",IF(N100>1825,">5Y"))))))) -> 2-3Y | P100: PUNE | Q100: OBC | R100: Group 1: Owned land | S100: 40 | T100: 135 | U100: =+S100+T100 -> 175 | W100: Yes | X100: Yes But not in 26-27 | Y100: =+IF(AO100="Approved","Yes",AS100) -> 46570 | AD100: =+AL100 -> 46539 | AE100: =+AS100 -> 46570 | AF100: Yes | AI100: Not Required | AJ100: Not Required | AL100: 46539 | AM100: Yes | AN100: Yes | AO100: Draft | AR100: Very Slow Candidate | AS100: =+AL100+31 -> 46570 | AT100: Yes | AU100: Yes but in next FY | AW100: NA | AX100: Yes | AY100: Yes | AZ100: Applied | BA100: Applied | BB100: Yet to Apply | BC100: Received | BD100: 8985443 | BE100: NA | BF100: NA | BG100: Yet to assign | BH100: No | BI100: 46539 | BJ100: 46569 | BK100: Yes | BL100: Received | BM100: NA | BN100: NA | BO100: Not Required | BW100: Pending | CB100: SRMP 2023-24 | CC100: Yes | CI100: =TEXT(M100,"MMM'YY") -> Dec'23 | CJ100: OBC
...

Sheet Summary
C1: Total | M1: A | N1: A | O1: A | P1: A | Q1: A | R1: A | S1: A | T1: A | U1: A | V1: D1 | W1: D1 | X1: D1 | Y1: D1 | Z1: D1 | AA1: D1 | AB1: D1 | AC1: D1 | AD1: D1 | AE1: D2 | AF1: D2 | AG1: D2 | AH1: D2 | AI1: D2 | AJ1: D2 | AK1: D2 | AL1: D2 | AM1: D2 | AN1: C | AO1: C | AP1: C | AQ1: C | AR1: C | AS1: C | AT1: C | AU1: C | AV1: C | AW1: E | AX1: E | AY1: E | AZ1: E | BA1: E | BB1: E | BC1: E | BD1: E | BE1: E | BF1: Already Commissioned | BR1: Total
C2: Commissionable in this FY | F2: Drawing | G2: NOC Available | J2: IO Available | M2: Commissionable in this FY | P2: NOC Available | S2: IO Available | V2: Commissionable in this FY | Y2: NOC Available | AB2: IO Available | AE2: Commissionable in this FY | AH2: NOC Available | AK2: IO Available | AN2: Commissionable in this FY | AQ2: NOC Available | AT2: IO Available | AW2: Commissionable in this FY | AZ2: NOC Available | BC2: IO Available | BF2: A | BG2: A | BH2: B | BI2: B | BJ2: C | BK2: C | BL2: D1 | BM2: D1 | BN2: D2 | BO2: D2 | BP2: E | BQ2: E | BR2: All COM
A3: RSA | B3: Total | C3: A | D3: B | E3: Total | F3: A+B | G3: A | H3: B | I3: Total | J3: A | K3: B | L3: Total | M3: A | N3: B | O3: otal | P3: A | Q3: B | R3: Total | S3: A | T3: B | U3: Total | V3: A | W3: B | X3: Total | Y3: A | Z3: B | AA3: Total | AB3: A | AC3: B | AD3: Total | AE3: A | AF3: B | AG3: Total | AH3: A | AI3: B | AJ3: Total | AK3: A | AL3: B | AM3: Total | AN3: A | AO3: B | AP3: Total | AQ3: A | AR3: B | AS3: Total | AT3: A | AU3: B | AV3: Total | AW3: A | AX3: B | AY3: Total | AZ3: A | BA3: B | BB3: Total | BC3: A | BD3: B | BE3: Total | BF3: A | BG3: B | BH3: A | BI3: B | BJ3: A | BK3: B | BL3: A | BM3: B | BN3: A | BO3: B | BP3: A | BQ3: B
A4: Ahmednagar East RSA | B4: =COUNTIFS('LOI and Commissioning Master Sh'!D:D,Summary!A4) -> 22 | C4: =COUNTIFS('LOI and Commissioning Master Sh'!$D:$D,Summary!$A4,'LOI and Commissioning Master Sh'!$X:$X,"Yes",'LOI and Commissioning Master Sh'!$H:$H,"A") -> 4 | D4: =COUNTIFS('LOI and Commissioning Master Sh'!$D:$D,Summary!$A4,'LOI and Commissioning Master Sh'!$X:$X,"Yes",'LOI and Commissioning Master Sh'!$H:$H,"B") -> 4 | E4: =C4+D4 -> 8 | F4: =+COUNTIFS('LOI and Commissioning Master Sh'!$D:$D,Summary!$A4,'LOI and Commissioning Master Sh'!$X:$X, "Yes",'LOI and Commissioning Master Sh'!$BK:$BK, "Yes") -> 7 | G4: =COUNTIFS('LOI and Commissioning Master Sh'!$D:$D,Summary!$A4,'LOI and Commissioning Master Sh'!$X:$X,"Yes",'LOI and Commissioning Master Sh'!$H:$H,"A",'LOI and Commissioning Master Sh'!$AC:$AC,"Yes") -> 1 | H4: =COUNTIFS('LOI and Commissioning Master Sh'!$D:$D,Summary!$A4,'LOI and Commissioning Master Sh'!$X:$X,"Yes",'LOI and Commissioning Master Sh'!$H:$H,"B",'LOI and Commissioning Master Sh'!$AC:$AC,"Yes") -> 0 | I4: =G4+H4 -> 1 | J4: =COUNTIFS('LOI and Commissioning Master Sh'!$D:$D,Summary!$A4,'LOI and Commissioning Master Sh'!$X:$X,"Yes",'LOI and Commissioning Master Sh'!$H:$H,"A",'LOI and Commissioning Master Sh'!$Y:$Y,"Yes") -> 0 | K4: =COUNTIFS('LOI and Commissioning Master Sh'!$D:$D,Summary!$A4,'LOI and Commissioning Master Sh'!$X:$X,"Yes",'LOI and Commissioning Master Sh'!$H:$H,"B",'LOI and Commissioning Master Sh'!$Y:$Y,"Yes") -> 1 | L4: =J4+K4 -> 1 | M4: =COUNTIFS('LOI and Commissioning Master Sh'!$D:$D,Summary!$A4, 'LOI and Commissioning Master Sh'!$G:$G,M$1,'LOI and Commissioning Master Sh'!$X:$X,"Yes",'LOI and Commissioning Master Sh'!$H:$H,M$3) -> 0 | N4: =COUNTIFS('LOI and Commissioning Master Sh'!$D:$D,Summary!$A4, 'LOI and Commissioning Master Sh'!$G:$G,N$1,'LOI and Commissioning Master Sh'!$X:$X,"Yes",'LOI and Commissioning Master Sh'!$H:$H,N$3) -> 0 | O4: =M4+N4 -> 0 | P4: =COUNTIFS('LOI and Commissioning Master Sh'!$D:$D,Summary!$A4, 'LOI and Commissioning Master Sh'!$G:$G,P$1,'LOI and Commissioning Master Sh'!$X:$X,"Yes",'LOI and Commissioning Master Sh'!$H:$H,P$3,'LOI and Commissioning Master Sh'!$AC:$AC,"Yes") -> 0 | Q4: =COUNTIFS('LOI and Commissioning Master Sh'!$D:$D,Summary!$A4, 'LOI and Commissioning Master Sh'!$G:$G,Q$1,'LOI and Commissioning Master Sh'!$X:$X,"Yes",'LOI and Commissioning Master Sh'!$H:$H,Q$3,'LOI and Commissioning Master Sh'!$AC:$AC,"Yes") -> 0 | R4: =P4+Q4 -> 0 | S4: =COUNTIFS('LOI and Commissioning Master Sh'!$D:$D,Summary!$A4, 'LOI and Commissioning Master Sh'!$G:$G,S$1,'LOI and Commissioning Master Sh'!$X:$X,"Yes",'LOI and Commissioning Master Sh'!$H:$H,S$3,'LOI and Commissioning Master Sh'!$Y:$Y,"Yes") -> 0 | T4: =COUNTIFS('LOI and Commissioning Master Sh'!$D:$D,Summary!$A4, 'LOI and Commissioning Master Sh'!$G:$G,T$1,'LOI and Commissioning Master Sh'!$X:$X,"Yes",'LOI and Commissioning Master Sh'!$H:$H,T$3,'LOI and Commissioning Master Sh'!$Y:$Y,"Yes") -> 0 | U4: =S4+T4 -> 0 | V4: =COUNTIFS('LOI and Commissioning Master Sh'!$D:$D,Summary!$A4, 'LOI and Commissioning Master Sh'!$G:$G,V$1,'LOI and Commissioning Master Sh'!$X:$X,"Yes",'LOI and Commissioning Master Sh'!$H:$H,V$3) -> 3 | W4: =COUNTIFS('LOI and Commissioning Master Sh'!$D:$D,Summary!$A4, 'LOI and Commissioning Master Sh'!$G:$G,W$1,'LOI and Commissioning Master Sh'!$X:$X,"Yes",'LOI and Commissioning Master Sh'!$H:$H,W$3) -> 0 | X4: =V4+W4 -> 3 | Y4: =COUNTIFS('LOI and Commissioning Master Sh'!$D:$D,Summary!$A4, 'LOI and Commissioning Master Sh'!$G:$G,Y$1,'LOI and Commissioning Master Sh'!$X:$X,"Yes",'LOI and Commissioning Master Sh'!$H:$H,Y$3,'LOI and Commissioning Master Sh'!$AC:$AC,"Yes") -> 0 | Z4: =COUNTIFS('LOI and Commissioning Master Sh'!$D:$D,Summary!$A4, 'LOI and Commissioning Master Sh'!$G:$G,Z$1,'LOI and Commissioning Master Sh'!$X:$X,"Yes",'LOI and Commissioning Master Sh'!$H:$H,Z$3,'LOI and Commissioning Master Sh'!$AC:$AC,"Yes") -> 0 | AA4: =Y4+Z4 -> 0 | AB4: =COUNTIFS('LOI and Commissioning Master Sh'!$D:$D,Summary!$A4, 'LOI and Commissioning Master Sh'!$G:$G,AB$1,'LOI and Commissioning Master Sh'!$X:$X,"Yes",'LOI and Commissioning Master Sh'!$H:$H,AB$3,'LOI and Commissioning Master Sh'!$Y:$Y,"Yes") -> 0 | AC4: =COUNTIFS('LOI and Commissioning Master Sh'!$D:$D,Summary!$A4, 'LOI and Commissioning Master Sh'!$G:$G,AC$1,'LOI and Commissioning Master Sh'!$X:$X,"Yes",'LOI and Commissioning Master Sh'!$H:$H,AC$3,'LOI and Commissioning Master Sh'!$Y:$Y,"Yes") -> 0 | AD4: =AB4+AC4 -> 0 | AE4: =COUNTIFS('LOI and Commissioning Master Sh'!$D:$D,Summary!$A4, 'LOI and Commissioning Master Sh'!$G:$G,AE$1,'LOI and Commissioning Master Sh'!$X:$X,"Yes",'LOI and Commissioning Master Sh'!$H:$H,AE$3) -> 1 | AF4: =COUNTIFS('LOI and Commissioning Master Sh'!$D:$D,Summary!$A4, 'LOI and Commissioning Master Sh'!$G:$G,AF$1,'LOI and Commissioning Master Sh'!$X:$X,"Yes",'LOI and Commissioning Master Sh'!$H:$H,AF$3) -> 3 | AG4: =AE4+AF4 -> 4 | AH4: =COUNTIFS('LOI and Commissioning Master Sh'!$D:$D,Summary!$A4, 'LOI and Commissioning Master Sh'!$G:$G,AH$1,'LOI and Commissioning Master Sh'!$X:$X,"Yes",'LOI and Commissioning Master Sh'!$H:$H,AH$3,'LOI and Commissioning Master Sh'!$AC:$AC,"Yes") -> 1 | AI4: =COUNTIFS('LOI and Commissioning Master Sh'!$D:$D,Summary!$A4, 'LOI and Commissioning Master Sh'!$G:$G,AI$1,'LOI and Commissioning Master Sh'!$X:$X,"Yes",'LOI and Commissioning Master Sh'!$H:$H,AI$3,'LOI and Commissioning Master Sh'!$AC:$AC,"Yes") -> 0 | AJ4: =AH4+AI4 -> 1 | AK4: =COUNTIFS('LOI and Commissioning Master Sh'!$D:$D,Summary!$A4, 'LOI and Commissioning Master Sh'!$G:$G,AK$1,'LOI and Commissioning Master Sh'!$X:$X,"Yes",'LOI and Commissioning Master Sh'!$H:$H,AK$3,'LOI and Commissioning Master Sh'!$Y:$Y,"Yes") -> 0 | AL4: =COUNTIFS('LOI and Commissioning Master Sh'!$D:$D,Summary!$A4, 'LOI and Commissioning Master Sh'!$G:$G,AL$1,'LOI and Commissioning Master Sh'!$X:$X,"Yes",'LOI and Commissioning Master Sh'!$H:$H,AL$3,'LOI and Commissioning Master Sh'!$Y:$Y,"Yes") -> 1 | AM4: =AK4+AL4 -> 1 | AN4: =COUNTIFS('LOI and Commissioning Master Sh'!$D:$D,Summary!$A4, 'LOI and Commissioning Master Sh'!$G:$G,AN$1,'LOI and Commissioning Master Sh'!$X:$X,"Yes",'LOI and Commissioning Master Sh'!$H:$H,AN$3) -> 0 | AO4: =COUNTIFS('LOI and Commissioning Master Sh'!$D:$D,Summary!$A4, 'LOI and Commissioning Master Sh'!$G:$G,AO$1,'LOI and Commissioning Master Sh'!$X:$X,"Yes",'LOI and Commissioning Master Sh'!$H:$H,AO$3) -> 0 | AP4: =AN4+AO4 -> 0 | AQ4: =COUNTIFS('LOI and Commissioning Master Sh'!$D:$D,Summary!$A4, 'LOI and Commissioning Master Sh'!$G:$G,AQ$1,'LOI and Commissioning Master Sh'!$X:$X,"Yes",'LOI and Commissioning Master Sh'!$H:$H,AQ$3,'LOI and Commissioning Master Sh'!$AC:$AC,"Yes") -> 0 | AR4: =COUNTIFS('LOI and Commissioning Master Sh'!$D:$D,Summary!$A4, 'LOI and Commissioning Master Sh'!$G:$G,AR$1,'LOI and Commissioning Master Sh'!$X:$X,"Yes",'LOI and Commissioning Master Sh'!$H:$H,AR$3,'LOI and Commissioning Master Sh'!$AC:$AC,"Yes") -> 0 | AS4: =AQ4+AR4 -> 0 | AT4: =COUNTIFS('LOI and Commissioning Master Sh'!$D:$D,Summary!$A4, 'LOI and Commissioning Master Sh'!$G:$G,AT$1,'LOI and Commissioning Master Sh'!$X:$X,"Yes",'LOI and Commissioning Master Sh'!$H:$H,AT$3,'LOI and Commissioning Master Sh'!$Y:$Y,"Yes") -> 0 | AU4: =COUNTIFS('LOI and Commissioning Master Sh'!$D:$D,Summary!$A4, 'LOI and Commissioning Master Sh'!$G:$G,AU$1,'LOI and Commissioning Master Sh'!$X:$X,"Yes",'LOI and Commissioning Master Sh'!$H:$H,AU$3,'LOI and Commissioning Master Sh'!$Y:$Y,"Yes") -> 0 | AV4: =AT4+AU4 -> 0 | AW4: =COUNTIFS('LOI and Commissioning Master Sh'!$D:$D,Summary!$A4, 'LOI and Commissioning Master Sh'!$G:$G,AW$1,'LOI and Commissioning Master Sh'!$X:$X,"Yes",'LOI and Commissioning Master Sh'!$H:$H,AW$3) -> 0 | AX4: =COUNTIFS('LOI and Commissioning Master Sh'!$D:$D,Summary!$A4, 'LOI and Commissioning Master Sh'!$G:$G,AX$1,'LOI and Commissioning Master Sh'!$X:$X,"Yes",'LOI and Commissioning Master Sh'!$H:$H,AX$3) -> 1 | AY4: =+AW4+AX4 -> 1 | AZ4: =COUNTIFS('LOI and Commissioning Master Sh'!$D:$D,Summary!$A4, 'LOI and Commissioning Master Sh'!$G:$G,AZ$1,'LOI and Commissioning Master Sh'!$X:$X,"Yes",'LOI and Commissioning Master Sh'!$H:$H,AZ$3,'LOI and Commissioning Master Sh'!$AC:$AC,"Yes") -> 0 | BA4: =COUNTIFS('LOI and Commissioning Master Sh'!$D:$D,Summary!$A4, 'LOI and Commissioning Master Sh'!$G:$G,BA$1,'LOI and Commissioning Master Sh'!$X:$X,"Yes",'LOI and Commissioning Master Sh'!$H:$H,BA$3,'LOI and Commissioning Master Sh'!$AC:$AC,"Yes") -> 0 | BB4: =+AZ4+BA4 -> 0 | BC4: =COUNTIFS('LOI and Commissioning Master Sh'!$D:$D,Summary!$A4, 'LOI and Commissioning Master Sh'!$G:$G,BC$1,'LOI and Commissioning Master Sh'!$X:$X,"Yes",'LOI and Commissioning Master Sh'!$H:$H,BC$3,'LOI and Commissioning Master Sh'!$Y:$Y,"Yes") -> 0 | BD4: =COUNTIFS('LOI and Commissioning Master Sh'!$D:$D,Summary!$A4, 'LOI and Commissioning Master Sh'!$G:$G,BD$1,'LOI and Commissioning Master Sh'!$X:$X,"Yes",'LOI and Commissioning Master Sh'!$H:$H,BD$3,'LOI and Commissioning Master Sh'!$Y:$Y,"Yes") -> 0 | BE4: =+BC4+BD4 -> 0 | BF4: =COUNTIFS('LOI and Commissioning Master Sh'!$D:$D,Summary!$A4,'LOI and Commissioning Master Sh'!$G:$G,Summary!BF$2,'LOI and Commissioning Master Sh'!$H:$H,Summary!BF$3,'LOI and Commissioning Master Sh'!$BW:$BW, "Commissioned") -> 0 | BG4: =COUNTIFS('LOI and Commissioning Master Sh'!$D:$D,Summary!$A4,'LOI and Commissioning Master Sh'!$G:$G,Summary!BG$2,'LOI and Commissioning Master Sh'!$H:$H,Summary!BG$3,'LOI and Commissioning Master Sh'!$BW:$BW, "Commissioned") -> 0 | BH4: =COUNTIFS('LOI and Commissioning Master Sh'!$D:$D,Summary!$A4,'LOI and Commissioning Master Sh'!$G:$G,Summary!BH$2,'LOI and Commissioning Master Sh'!$H:$H,Summary!BH$3,'LOI and Commissioning Master Sh'!$BW:$BW, "Commissioned") -> 0 | BI4: =COUNTIFS('LOI and Commissioning Master Sh'!$D:$D,Summary!$A4,'LOI and Commissioning Master Sh'!$G:$G,Summary!BI$2,'LOI and Commissioning Master Sh'!$H:$H,Summary!BI$3,'LOI and Commissioning Master Sh'!$BW:$BW, "Commissioned") -> 0 | BJ4: =COUNTIFS('LOI and Commissioning Master Sh'!$D:$D,Summary!$A4,'LOI and Commissioning Master Sh'!$G:$G,Summary!BJ$2,'LOI and Commissioning Master Sh'!$H:$H,Summary!BJ$3,'LOI and Commissioning Master Sh'!$BW:$BW, "Commissioned") -> 0 | BK4: =COUNTIFS('LOI and Commissioning Master Sh'!$D:$D,Summary!$A4,'LOI and Commissioning Master Sh'!$G:$G,Summary!BK$2,'LOI and Commissioning Master Sh'!$H:$H,Summary!BK$3,'LOI and Commissioning Master Sh'!$BW:$BW, "Commissioned") -> 0 | BL4: =COUNTIFS('LOI and Commissioning Master Sh'!$D:$D,Summary!$A4,'LOI and Commissioning Master Sh'!$G:$G,Summary!BL$2,'LOI and Commissioning Master Sh'!$H:$H,Summary!BL$3,'LOI and Commissioning Master Sh'!$BW:$BW, "Commissioned") -> 0 | BM4: =COUNTIFS('LOI and Commissioning Master Sh'!$D:$D,Summary!$A4,'LOI and Commissioning Master Sh'!$G:$G,Summary!BM$2,'LOI and Commissioning Master Sh'!$H:$H,Summary!BM$3,'LOI and Commissioning Master Sh'!$BW:$BW, "Commissioned") -> 0 | ... BQ4: =COUNTIFS('LOI and Commissioning Master Sh'!$D:$D,Summary!$A4,'LOI and Commissioning Master Sh'!$G:$G,Summary!BQ$2,'LOI and Commissioning Master Sh'!$H:$H,Summary!BQ$3,'LOI and Commissioning Master Sh'!$BW:$BW, "Commissioned") -> 0 | BR4: =+SUM(BF4:BQ4) -> 0
A5: Ahmednagar West RSA | B5: =COUNTIFS('LOI and Commissioning Master Sh'!D:D,Summary!A5) -> 33 | C5: =COUNTIFS('LOI and Commissioning Master Sh'!$D:$D,Summary!$A5,'LOI and Commissioning Master Sh'!$X:$X,"Yes",'LOI and Commissioning Master Sh'!$H:$H,"A") -> 1 | D5: =COUNTIFS('LOI and Commissioning Master Sh'!$D:$D,Summary!$A5,'LOI and Commissioning Master Sh'!$X:$X,"Yes",'LOI and Commissioning Master Sh'!$H:$H,"B") -> 10 | E5: =C5+D5 -> 11 | F5: =+COUNTIFS('LOI and Commissioning Master Sh'!$D:$D,Summary!$A5,'LOI and Commissioning Master Sh'!$X:$X, "Yes",'LOI and Commissioning Master Sh'!$BK:$BK, "Yes") -> 10 | G5: =COUNTIFS('LOI and Commissioning Master Sh'!$D:$D,Summary!$A5,'LOI and Commissioning Master Sh'!$X:$X,"Yes",'LOI and Commissioning Master Sh'!$H:$H,"A",'LOI and Commissioning Master Sh'!$AC:$AC,"Yes") -> 1 | H5: =COUNTIFS('LOI and Commissioning Master Sh'!$D:$D,Summary!$A5,'LOI and Commissioning Master Sh'!$X:$X,"Yes",'LOI and Commissioning Master Sh'!$H:$H,"B",'LOI and Commissioning Master Sh'!$AC:$AC,"Yes") -> 0 | I5: =G5+H5 -> 1 | J5: =COUNTIFS('LOI and Commissioning Master Sh'!$D:$D,Summary!$A5,'LOI and Commissioning Master Sh'!$X:$X,"Yes",'LOI and Commissioning Master Sh'!$H:$H,"A",'LOI and Commissioning Master Sh'!$Y:$Y,"Yes") -> 0 | K5: =COUNTIFS('LOI and Commissioning Master Sh'!$D:$D,Summary!$A5,'LOI and Commissioning Master Sh'!$X:$X,"Yes",'LOI and Commissioning Master Sh'!$H:$H,"B",'LOI and Commissioning Master Sh'!$Y:$Y,"Yes") -> 4 | L5: =J5+K5 -> 4 | M5: =COUNTIFS('LOI and Commissioning Master Sh'!$D:$D,Summary!$A5, 'LOI and Commissioning Master Sh'!$G:$G,M$1,'LOI and Commissioning Master Sh'!$X:$X,"Yes",'LOI and Commissioning Master Sh'!$H:$H,M$3) -> 0 | N5: =COUNTIFS('LOI and Commissioning Master Sh'!$D:$D,Summary!$A5, 'LOI and Commissioning Master Sh'!$G:$G,N$1,'LOI and Commissioning Master Sh'!$X:$X,"Yes",'LOI and Commissioning Master Sh'!$H:$H,N$3) -> 0 | O5: =M5+N5 -> 0 | P5: =COUNTIFS('LOI and Commissioning Master Sh'!$D:$D,Summary!$A5, 'LOI and Commissioning Master Sh'!$G:$G,P$1,'LOI and Commissioning Master Sh'!$X:$X,"Yes",'LOI and Commissioning Master Sh'!$H:$H,P$3,'LOI and Commissioning Master Sh'!$AC:$AC,"Yes") -> 0 | Q5: =COUNTIFS('LOI and Commissioning Master Sh'!$D:$D,Summary!$A5, 'LOI and Commissioning Master Sh'!$G:$G,Q$1,'LOI and Commissioning Master Sh'!$X:$X,"Yes",'LOI and Commissioning Master Sh'!$H:$H,Q$3,'LOI and Commissioning Master Sh'!$AC:$AC,"Yes") -> 0 | R5: =P5+Q5 -> 0 | S5: =COUNTIFS('LOI and Commissioning Master Sh'!$D:$D,Summary!$A5, 'LOI and Commissioning Master Sh'!$G:$G,S$1,'LOI and Commissioning Master Sh'!$X:$X,"Yes",'LOI and Commissioning Master Sh'!$H:$H,S$3,'LOI and Commissioning Master Sh'!$Y:$Y,"Yes") -> 0 | T5: =COUNTIFS('LOI and Commissioning Master Sh'!$D:$D,Summary!$A5, 'LOI and Commissioning Master Sh'!$G:$G,T$1,'LOI and Commissioning Master Sh'!$X:$X,"Yes",'LOI and Commissioning Master Sh'!$H:$H,T$3,'LOI and Commissioning Master Sh'!$Y:$Y,"Yes") -> 0 | U5: =S5+T5 -> 0 | V5: =COUNTIFS('LOI and Commissioning Master Sh'!$D:$D,Summary!$A5, 'LOI and Commissioning Master Sh'!$G:$G,V$1,'LOI and Commissioning Master Sh'!$X:$X,"Yes",'LOI and Commissioning Master Sh'!$H:$H,V$3) -> 0 | W5: =COUNTIFS('LOI and Commissioning Master Sh'!$D:$D,Summary!$A5, 'LOI and Commissioning Master Sh'!$G:$G,W$1,'LOI and Commissioning Master Sh'!$X:$X,"Yes",'LOI and Commissioning Master Sh'!$H:$H,W$3) -> 5 | X5: =V5+W5 -> 5 | Y5: =COUNTIFS('LOI and Commissioning Master Sh'!$D:$D,Summary!$A5, 'LOI and Commissioning Master Sh'!$G:$G,Y$1,'LOI and Commissioning Master Sh'!$X:$X,"Yes",'LOI and Commissioning Master Sh'!$H:$H,Y$3,'LOI and Commissioning Master Sh'!$AC:$AC,"Yes") -> 0 | Z5: =COUNTIFS('LOI and Commissioning Master Sh'!$D:$D,Summary!$A5, 'LOI and Commissioning Master Sh'!$G:$G,Z$1,'LOI and Commissioning Master Sh'!$X:$X,"Yes",'LOI and Commissioning Master Sh'!$H:$H,Z$3,'LOI and Commissioning Master Sh'!$AC:$AC,"Yes") -> 0 | AA5: =Y5+Z5 -> 0 | AB5: =COUNTIFS('LOI and Commissioning Master Sh'!$D:$D,Summary!$A5, 'LOI and Commissioning Master Sh'!$G:$G,AB$1,'LOI and Commissioning Master Sh'!$X:$X,"Yes",'LOI and Commissioning Master Sh'!$H:$H,AB$3,'LOI and Commissioning Master Sh'!$Y:$Y,"Yes") -> 0 | AC5: =COUNTIFS('LOI and Commissioning Master Sh'!$D:$D,Summary!$A5, 'LOI and Commissioning Master Sh'!$G:$G,AC$1,'LOI and Commissioning Master Sh'!$X:$X,"Yes",'LOI and Commissioning Master Sh'!$H:$H,AC$3,'LOI and Commissioning Master Sh'!$Y:$Y,"Yes") -> 3 | AD5: =AB5+AC5 -> 3 | AE5: =COUNTIFS('LOI and Commissioning Master Sh'!$D:$D,Summary!$A5, 'LOI and Commissioning Master Sh'!$G:$G,AE$1,'LOI and Commissioning Master Sh'!$X:$X,"Yes",'LOI and Commissioning Master Sh'!$H:$H,AE$3) -> 1 | AF5: =COUNTIFS('LOI and Commissioning Master Sh'!$D:$D,Summary!$A5, 'LOI and Commissioning Master Sh'!$G:$G,AF$1,'LOI and Commissioning Master Sh'!$X:$X,"Yes",'LOI and Commissioning Master Sh'!$H:$H,AF$3) -> 2 | AG5: =AE5+AF5 -> 3 | AH5: =COUNTIFS('LOI and Commissioning Master Sh'!$D:$D,Summary!$A5, 'LOI and Commissioning Master Sh'!$G:$G,AH$1,'LOI and Commissioning Master Sh'!$X:$X,"Yes",'LOI and Commissioning Master Sh'!$H:$H,AH$3,'LOI and Commissioning Master Sh'!$AC:$AC,"Yes") -> 1 | AI5: =COUNTIFS('LOI and Commissioning Master Sh'!$D:$D,Summary!$A5, 'LOI and Commissioning Master Sh'!$G:$G,AI$1,'LOI and Commissioning Master Sh'!$X:$X,"Yes",'LOI and Commissioning Master Sh'!$H:$H,AI$3,'LOI and Commissioning Master Sh'!$AC:$AC,"Yes") -> 0 | AJ5: =AH5+AI5 -> 1 | AK5: =COUNTIFS('LOI and Commissioning Master Sh'!$D:$D,Summary!$A5, 'LOI and Commissioning Master Sh'!$G:$G,AK$1,'LOI and Commissioning Master Sh'!$X:$X,"Yes",'LOI and Commissioning Master Sh'!$H:$H,AK$3,'LOI and Commissioning Master Sh'!$Y:$Y,"Yes") -> 0 | AL5: =COUNTIFS('LOI and Commissioning Master Sh'!$D:$D,Summary!$A5, 'LOI and Commissioning Master Sh'!$G:$G,AL$1,'LOI and Commissioning Master Sh'!$X:$X,"Yes",'LOI and Commissioning Master Sh'!$H:$H,AL$3,'LOI and Commissioning Master Sh'!$Y:$Y,"Yes") -> 1 | AM5: =AK5+AL5 -> 1 | AN5: =COUNTIFS('LOI and Commissioning Master Sh'!$D:$D,Summary!$A5, 'LOI and Commissioning Master Sh'!$G:$G,AN$1,'LOI and Commissioning Master Sh'!$X:$X,"Yes",'LOI and Commissioning Master Sh'!$H:$H,AN$3) -> 0 | AO5: =COUNTIFS('LOI and Commissioning Master Sh'!$D:$D,Summary!$A5, 'LOI and Commissioning Master Sh'!$G:$G,AO$1,'LOI and Commissioning Master Sh'!$X:$X,"Yes",'LOI and Commissioning Master Sh'!$H:$H,AO$3) -> 0 | AP5: =AN5+AO5 -> 0 | AQ5: =COUNTIFS('LOI and Commissioning Master Sh'!$D:$D,Summary!$A5, 'LOI and Commissioning Master Sh'!$G:$G,AQ$1,'LOI and Commissioning Master Sh'!$X:$X,"Yes",'LOI and Commissioning Master Sh'!$H:$H,AQ$3,'LOI and Commissioning Master Sh'!$AC:$AC,"Yes") -> 0 | AR5: =COUNTIFS('LOI and Commissioning Master Sh'!$D:$D,Summary!$A5, 'LOI and Commissioning Master Sh'!$G:$G,AR$1,'LOI and Commissioning Master Sh'!$X:$X,"Yes",'LOI and Commissioning Master Sh'!$H:$H,AR$3,'LOI and Commissioning Master Sh'!$AC:$AC,"Yes") -> 0 | AS5: =AQ5+AR5 -> 0 | AT5: =COUNTIFS('LOI and Commissioning Master Sh'!$D:$D,Summary!$A5, 'LOI and Commissioning Master Sh'!$G:$G,AT$1,'LOI and Commissioning Master Sh'!$X:$X,"Yes",'LOI and Commissioning Master Sh'!$H:$H,AT$3,'LOI and Commissioning Master Sh'!$Y:$Y,"Yes") -> 0 | AU5: =COUNTIFS('LOI and Commissioning Master Sh'!$D:$D,Summary!$A5, 'LOI and Commissioning Master Sh'!$G:$G,AU$1,'LOI and Commissioning Master Sh'!$X:$X,"Yes",'LOI and Commissioning Master Sh'!$H:$H,AU$3,'LOI and Commissioning Master Sh'!$Y:$Y,"Yes") -> 0 | AV5: =AT5+AU5 -> 0 | AW5: =COUNTIFS('LOI and Commissioning Master Sh'!$D:$D,Summary!$A5, 'LOI and Commissioning Master Sh'!$G:$G,AW$1,'LOI and Commissioning Master Sh'!$X:$X,"Yes",'LOI and Commissioning Master Sh'!$H:$H,AW$3) -> 0 | AX5: =COUNTIFS('LOI and Commissioning Master Sh'!$D:$D,Summary!$A5, 'LOI and Commissioning Master Sh'!$G:$G,AX$1,'LOI and Commissioning Master Sh'!$X:$X,"Yes",'LOI and Commissioning Master Sh'!$H:$H,AX$3) -> 3 | AY5: =+AW5+AX5 -> 3 | AZ5: =COUNTIFS('LOI and Commissioning Master Sh'!$D:$D,Summary!$A5, 'LOI and Commissioning Master Sh'!$G:$G,AZ$1,'LOI and Commissioning Master Sh'!$X:$X,"Yes",'LOI and Commissioning Master Sh'!$H:$H,AZ$3,'LOI and Commissioning Master Sh'!$AC:$AC,"Yes") -> 0 | BA5: =COUNTIFS('LOI and Commissioning Master Sh'!$D:$D,Summary!$A5, 'LOI and Commissioning Master Sh'!$G:$G,BA$1,'LOI and Commissioning Master Sh'!$X:$X,"Yes",'LOI and Commissioning Master Sh'!$H:$H,BA$3,'LOI and Commissioning Master Sh'!$AC:$AC,"Yes") -> 0 | BB5: =+AZ5+BA5 -> 0 | BC5: =COUNTIFS('LOI and Commissioning Master Sh'!$D:$D,Summary!$A5, 'LOI and Commissioning Master Sh'!$G:$G,BC$1,'LOI and Commissioning Master Sh'!$X:$X,"Yes",'LOI and Commissioning Master Sh'!$H:$H,BC$3,'LOI and Commissioning Master Sh'!$Y:$Y,"Yes") -> 0 | BD5: =COUNTIFS('LOI and Commissioning Master Sh'!$D:$D,Summary!$A5, 'LOI and Commissioning Master Sh'!$G:$G,BD$1,'LOI and Commissioning Master Sh'!$X:$X,"Yes",'LOI and Commissioning Master Sh'!$H:$H,BD$3,'LOI and Commissioning Master Sh'!$Y:$Y,"Yes") -> 0 | BE5: =+BC5+BD5 -> 0 | BF5: =COUNTIFS('LOI and Commissioning Master Sh'!$D:$D,Summary!$A5,'LOI and Commissioning Master Sh'!$G:$G,Summary!BF$2,'LOI and Commissioning Master Sh'!$H:$H,Summary!BF$3,'LOI and Commissioning Master Sh'!$BW:$BW, "Commissioned") -> 0 | BG5: =COUNTIFS('LOI and Commissioning Master Sh'!$D:$D,Summary!$A5,'LOI and Commissioning Master Sh'!$G:$G,Summary!BG$2,'LOI and Commissioning Master Sh'!$H:$H,Summary!BG$3,'LOI and Commissioning Master Sh'!$BW:$BW, "Commissioned") -> 0 | BH5: =COUNTIFS('LOI and Commissioning Master Sh'!$D:$D,Summary!$A5,'LOI and Commissioning Master Sh'!$G:$G,Summary!BH$2,'LOI and Commissioning Master Sh'!$H:$H,Summary!BH$3,'LOI and Commissioning Master Sh'!$BW:$BW, "Commissioned") -> 0 | BI5: =COUNTIFS('LOI and Commissioning Master Sh'!$D:$D,Summary!$A5,'LOI and Commissioning Master Sh'!$G:$G,Summary!BI$2,'LOI and Commissioning Master Sh'!$H:$H,Summary!BI$3,'LOI and Commissioning Master Sh'!$BW:$BW, "Commissioned") -> 0 | BJ5: =COUNTIFS('LOI and Commissioning Master Sh'!$D:$D,Summary!$A5,'LOI and Commissioning Master Sh'!$G:$G,Summary!BJ$2,'LOI and Commissioning Master Sh'!$H:$H,Summary!BJ$3,'LOI and Commissioning Master Sh'!$BW:$BW, "Commissioned") -> 0 | BK5: =COUNTIFS('LOI and Commissioning Master Sh'!$D:$D,Summary!$A5,'LOI and Commissioning Master Sh'!$G:$G,Summary!BK$2,'LOI and Commissioning Master Sh'!$H:$H,Summary!BK$3,'LOI and Commissioning Master Sh'!$BW:$BW, "Commissioned") -> 0 | BL5: =COUNTIFS('LOI and Commissioning Master Sh'!$D:$D,Summary!$A5,'LOI and Commissioning Master Sh'!$G:$G,Summary!BL$2,'LOI and Commissioning Master Sh'!$H:$H,Summary!BL$3,'LOI and Commissioning Master Sh'!$BW:$BW, "Commissioned") -> 0 | BM5: =COUNTIFS('LOI and Commissioning Master Sh'!$D:$D,Summary!$A5,'LOI and Commissioning Master Sh'!$G:$G,Summary!BM$2,'LOI and Commissioning Master Sh'!$H:$H,Summary!BM$3,'LOI and Commissioning Master Sh'!$BW:$BW, "Commissioned") -> 1 | ... BQ5: =COUNTIFS('LOI and Commissioning Master Sh'!$D:$D,Summary!$A5,'LOI and Commissioning Master Sh'!$G:$G,Summary!BQ$2,'LOI and Commissioning Master Sh'!$H:$H,Summary!BQ$3,'LOI and Commissioning Master Sh'!$BW:$BW, "Commissioned") -> 0 | BR5: =+SUM(BF5:BQ5) -> 1
A6: Pune City RSA | B6: =COUNTIFS('LOI and Commissioning Master Sh'!D:D,Summary!A6) -> 16 | C6: =COUNTIFS('LOI and Commissioning Master Sh'!$D:$D,Summary!$A6,'LOI and Commissioning Master Sh'!$X:$X,"Yes",'LOI and Commissioning Master Sh'!$H:$H,"A") -> 2 | D6: =COUNTIFS('LOI and Commissioning Master Sh'!$D:$D,Summary!$A6,'LOI and Commissioning Master Sh'!$X:$X,"Yes",'LOI and Commissioning Master Sh'!$H:$H,"B") -> 1 | E6: =C6+D6 -> 3 | F6: =+COUNTIFS('LOI and Commissioning Master Sh'!$D:$D,Summary!$A6,'LOI and Commissioning Master Sh'!$X:$X, "Yes",'LOI and Commissioning Master Sh'!$BK:$BK, "Yes") -> 2 | G6: =COUNTIFS('LOI and Commissioning Master Sh'!$D:$D,Summary!$A6,'LOI and Commissioning Master Sh'!$X:$X,"Yes",'LOI and Commissioning Master Sh'!$H:$H,"A",'LOI and Commissioning Master Sh'!$AC:$AC,"Yes") -> 0 | H6: =COUNTIFS('LOI and Commissioning Master Sh'!$D:$D,Summary!$A6,'LOI and Commissioning Master Sh'!$X:$X,"Yes",'LOI and Commissioning Master Sh'!$H:$H,"B",'LOI and Commissioning Master Sh'!$AC:$AC,"Yes") -> 0 | I6: =G6+H6 -> 0 | J6: =COUNTIFS('LOI and Commissioning Master Sh'!$D:$D,Summary!$A6,'LOI and Commissioning Master Sh'!$X:$X,"Yes",'LOI and Commissioning Master Sh'!$H:$H,"A",'LOI and Commissioning Master Sh'!$Y:$Y,"Yes") -> 1 | K6: =COUNTIFS('LOI and Commissioning Master Sh'!$D:$D,Summary!$A6,'LOI and Commissioning Master Sh'!$X:$X,"Yes",'LOI and Commissioning Master Sh'!$H:$H,"B",'LOI and Commissioning Master Sh'!$Y:$Y,"Yes") -> 0 | L6: =J6+K6 -> 1 | M6: =COUNTIFS('LOI and Commissioning Master Sh'!$D:$D,Summary!$A6, 'LOI and Commissioning Master Sh'!$G:$G,M$1,'LOI and Commissioning Master Sh'!$X:$X,"Yes",'LOI and Commissioning Master Sh'!$H:$H,M$3) -> 1 | N6: =COUNTIFS('LOI and Commissioning Master Sh'!$D:$D,Summary!$A6, 'LOI and Commissioning Master Sh'!$G:$G,N$1,'LOI and Commissioning Master Sh'!$X:$X,"Yes",'LOI and Commissioning Master Sh'!$H:$H,N$3) -> 1 | O6: =M6+N6 -> 2 | P6: =COUNTIFS('LOI and Commissioning Master Sh'!$D:$D,Summary!$A6, 'LOI and Commissioning Master Sh'!$G:$G,P$1,'LOI and Commissioning Master Sh'!$X:$X,"Yes",'LOI and Commissioning Master Sh'!$H:$H,P$3,'LOI and Commissioning Master Sh'!$AC:$AC,"Yes") -> 0 | Q6: =COUNTIFS('LOI and Commissioning Master Sh'!$D:$D,Summary!$A6, 'LOI and Commissioning Master Sh'!$G:$G,Q$1,'LOI and Commissioning Master Sh'!$X:$X,"Yes",'LOI and Commissioning Master Sh'!$H:$H,Q$3,'LOI and Commissioning Master Sh'!$AC:$AC,"Yes") -> 0 | R6: =P6+Q6 -> 0 | S6: =COUNTIFS('LOI and Commissioning Master Sh'!$D:$D,Summary!$A6, 'LOI and Commissioning Master Sh'!$G:$G,S$1,'LOI and Commissioning Master Sh'!$X:$X,"Yes",'LOI and Commissioning Master Sh'!$H:$H,S$3,'LOI and Commissioning Master Sh'!$Y:$Y,"Yes") -> 1 | T6: =COUNTIFS('LOI and Commissioning Master Sh'!$D:$D,Summary!$A6, 'LOI and Commissioning Master Sh'!$G:$G,T$1,'LOI and Commissioning Master Sh'!$X:$X,"Yes",'LOI and Commissioning Master Sh'!$H:$H,T$3,'LOI and Commissioning Master Sh'!$Y:$Y,"Yes") -> 0 | U6: =S6+T6 -> 1 | V6: =COUNTIFS('LOI and Commissioning Master Sh'!$D:$D,Summary!$A6, 'LOI and Commissioning Master Sh'!$G:$G,V$1,'LOI and Commissioning Master Sh'!$X:$X,"Yes",'LOI and Commissioning Master Sh'!$H:$H,V$3) -> 1 | W6: =COUNTIFS('LOI and Commissioning Master Sh'!$D:$D,Summary!$A6, 'LOI and Commissioning Master Sh'!$G:$G,W$1,'LOI and Commissioning Master Sh'!$X:$X,"Yes",'LOI and Commissioning Master Sh'!$H:$H,W$3) -> 0 | X6: =V6+W6 -> 1 | Y6: =COUNTIFS('LOI and Commissioning Master Sh'!$D:$D,Summary!$A6, 'LOI and Commissioning Master Sh'!$G:$G,Y$1,'LOI and Commissioning Master Sh'!$X:$X,"Yes",'LOI and Commissioning Master Sh'!$H:$H,Y$3,'LOI and Commissioning Master Sh'!$AC:$AC,"Yes") -> 0 | Z6: =COUNTIFS('LOI and Commissioning Master Sh'!$D:$D,Summary!$A6, 'LOI and Commissioning Master Sh'!$G:$G,Z$1,'LOI and Commissioning Master Sh'!$X:$X,"Yes",'LOI and Commissioning Master Sh'!$H:$H,Z$3,'LOI and Commissioning Master Sh'!$AC:$AC,"Yes") -> 0 | AA6: =Y6+Z6 -> 0 | AB6: =COUNTIFS('LOI and Commissioning Master Sh'!$D:$D,Summary!$A6, 'LOI and Commissioning Master Sh'!$G:$G,AB$1,'LOI and Commissioning Master Sh'!$X:$X,"Yes",'LOI and Commissioning Master Sh'!$H:$H,AB$3,'LOI and Commissioning Master Sh'!$Y:$Y,"Yes") -> 0 | AC6: =COUNTIFS('LOI and Commissioning Master Sh'!$D:$D,Summary!$A6, 'LOI and Commissioning Master Sh'!$G:$G,AC$1,'LOI and Commissioning Master Sh'!$X:$X,"Yes",'LOI and Commissioning Master Sh'!$H:$H,AC$3,'LOI and Commissioning Master Sh'!$Y:$Y,"Yes") -> 0 | AD6: =AB6+AC6 -> 0 | AE6: =COUNTIFS('LOI and Commissioning Master Sh'!$D:$D,Summary!$A6, 'LOI and Commissioning Master Sh'!$G:$G,AE$1,'LOI and Commissioning Master Sh'!$X:$X,"Yes",'LOI and Commissioning Master Sh'!$H:$H,AE$3) -> 0 | AF6: =COUNTIFS('LOI and Commissioning Master Sh'!$D:$D,Summary!$A6, 'LOI and Commissioning Master Sh'!$G:$G,AF$1,'LOI and Commissioning Master Sh'!$X:$X,"Yes",'LOI and Commissioning Master Sh'!$H:$H,AF$3) -> 0 | AG6: =AE6+AF6 -> 0 | AH6: =COUNTIFS('LOI and Commissioning Master Sh'!$D:$D,Summary!$A6, 'LOI and Commissioning Master Sh'!$G:$G,AH$1,'LOI and Commissioning Master Sh'!$X:$X,"Yes",'LOI and Commissioning Master Sh'!$H:$H,AH$3,'LOI and Commissioning Master Sh'!$AC:$AC,"Yes") -> 0 | AI6: =COUNTIFS('LOI and Commissioning Master Sh'!$D:$D,Summary!$A6, 'LOI and Commissioning Master Sh'!$G:$G,AI$1,'LOI and Commissioning Master Sh'!$X:$X,"Yes",'LOI and Commissioning Master Sh'!$H:$H,AI$3,'LOI and Commissioning Master Sh'!$AC:$AC,"Yes") -> 0 | AJ6: =AH6+AI6 -> 0 | AK6: =COUNTIFS('LOI and Commissioning Master Sh'!$D:$D,Summary!$A6, 'LOI and Commissioning Master Sh'!$G:$G,AK$1,'LOI and Commissioning Master Sh'!$X:$X,"Yes",'LOI and Commissioning Master Sh'!$H:$H,AK$3,'LOI and Commissioning Master Sh'!$Y:$Y,"Yes") -> 0 | AL6: =COUNTIFS('LOI and Commissioning Master Sh'!$D:$D,Summary!$A6, 'LOI and Commissioning Master Sh'!$G:$G,AL$1,'LOI and Commissioning Master Sh'!$X:$X,"Yes",'LOI and Commissioning Master Sh'!$H:$H,AL$3,'LOI and Commissioning Master Sh'!$Y:$Y,"Yes") -> 0 | AM6: =AK6+AL6 -> 0 | AN6: =COUNTIFS('LOI and Commissioning Master Sh'!$D:$D,Summary!$A6, 'LOI and Commissioning Master Sh'!$G:$G,AN$1,'LOI and Commissioning Master Sh'!$X:$X,"Yes",'LOI and Commissioning Master Sh'!$H:$H,AN$3) -> 0 | AO6: =COUNTIFS('LOI and Commissioning Master Sh'!$D:$D,Summary!$A6, 'LOI and Commissioning Master Sh'!$G:$G,AO$1,'LOI and Commissioning Master Sh'!$X:$X,"Yes",'LOI and Commissioning Master Sh'!$H:$H,AO$3) -> 0 | AP6: =AN6+AO6 -> 0 | AQ6: =COUNTIFS('LOI and Commissioning Master Sh'!$D:$D,Summary!$A6, 'LOI and Commissioning Master Sh'!$G:$G,AQ$1,'LOI and Commissioning Master Sh'!$X:$X,"Yes",'LOI and Commissioning Master Sh'!$H:$H,AQ$3,'LOI and Commissioning Master Sh'!$AC:$AC,"Yes") -> 0 | AR6: =COUNTIFS('LOI and Commissioning Master Sh'!$D:$D,Summary!$A6, 'LOI and Commissioning Master Sh'!$G:$G,AR$1,'LOI and Commissioning Master Sh'!$X:$X,"Yes",'LOI and Commissioning Master Sh'!$H:$H,AR$3,'LOI and Commissioning Master Sh'!$AC:$AC,"Yes") -> 0 | AS6: =AQ6+AR6 -> 0 | AT6: =COUNTIFS('LOI and Commissioning Master Sh'!$D:$D,Summary!$A6, 'LOI and Commissioning Master Sh'!$G:$G,AT$1,'LOI and Commissioning Master Sh'!$X:$X,"Yes",'LOI and Commissioning Master Sh'!$H:$H,AT$3,'LOI and Commissioning Master Sh'!$Y:$Y,"Yes") -> 0 | AU6: =COUNTIFS('LOI and Commissioning Master Sh'!$D:$D,Summary!$A6, 'LOI and Commissioning Master Sh'!$G:$G,AU$1,'LOI and Commissioning Master Sh'!$X:$X,"Yes",'LOI and Commissioning Master Sh'!$H:$H,AU$3,'LOI and Commissioning Master Sh'!$Y:$Y,"Yes") -> 0 | AV6: =AT6+AU6 -> 0 | AW6: =COUNTIFS('LOI and Commissioning Master Sh'!$D:$D,Summary!$A6, 'LOI and Commissioning Master Sh'!$G:$G,AW$1,'LOI and Commissioning Master Sh'!$X:$X,"Yes",'LOI and Commissioning Master Sh'!$H:$H,AW$3) -> 0 | AX6: =COUNTIFS('LOI and Commissioning Master Sh'!$D:$D,Summary!$A6, 'LOI and Commissioning Master Sh'!$G:$G,AX$1,'LOI and Commissioning Master Sh'!$X:$X,"Yes",'LOI and Commissioning Master Sh'!$H:$H,AX$3) -> 0 | AY6: =+AW6+AX6 -> 0 | AZ6: =COUNTIFS('LOI and Commissioning Master Sh'!$D:$D,Summary!$A6, 'LOI and Commissioning Master Sh'!$G:$G,AZ$1,'LOI and Commissioning Master Sh'!$X:$X,"Yes",'LOI and Commissioning Master Sh'!$H:$H,AZ$3,'LOI and Commissioning Master Sh'!$AC:$AC,"Yes") -> 0 | BA6: =COUNTIFS('LOI and Commissioning Master Sh'!$D:$D,Summary!$A6, 'LOI and Commissioning Master Sh'!$G:$G,BA$1,'LOI and Commissioning Master Sh'!$X:$X,"Yes",'LOI and Commissioning Master Sh'!$H:$H,BA$3,'LOI and Commissioning Master Sh'!$AC:$AC,"Yes") -> 0 | BB6: =+AZ6+BA6 -> 0 | BC6: =COUNTIFS('LOI and Commissioning Master Sh'!$D:$D,Summary!$A6, 'LOI and Commissioning Master Sh'!$G:$G,BC$1,'LOI and Commissioning Master Sh'!$X:$X,"Yes",'LOI and Commissioning Master Sh'!$H:$H,BC$3,'LOI and Commissioning Master Sh'!$Y:$Y,"Yes") -> 0 | BD6: =COUNTIFS('LOI and Commissioning Master Sh'!$D:$D,Summary!$A6, 'LOI and Commissioning Master Sh'!$G:$G,BD$1,'LOI and Commissioning Master Sh'!$X:$X,"Yes",'LOI and Commissioning Master Sh'!$H:$H,BD$3,'LOI and Commissioning Master Sh'!$Y:$Y,"Yes") -> 0 | BE6: =+BC6+BD6 -> 0 | BF6: =COUNTIFS('LOI and Commissioning Master Sh'!$D:$D,Summary!$A6,'LOI and Commissioning Master Sh'!$G:$G,Summary!BF$2,'LOI and Commissioning Master Sh'!$H:$H,Summary!BF$3,'LOI and Commissioning Master Sh'!$BW:$BW, "Commissioned") -> 0 | BG6: =COUNTIFS('LOI and Commissioning Master Sh'!$D:$D,Summary!$A6,'LOI and Commissioning Master Sh'!$G:$G,Summary!BG$2,'LOI and Commissioning Master Sh'!$H:$H,Summary!BG$3,'LOI and Commissioning Master Sh'!$BW:$BW, "Commissioned") -> 0 | BH6: =COUNTIFS('LOI and Commissioning Master Sh'!$D:$D,Summary!$A6,'LOI and Commissioning Master Sh'!$G:$G,Summary!BH$2,'LOI and Commissioning Master Sh'!$H:$H,Summary!BH$3,'LOI and Commissioning Master Sh'!$BW:$BW, "Commissioned") -> 0 | BI6: =COUNTIFS('LOI and Commissioning Master Sh'!$D:$D,Summary!$A6,'LOI and Commissioning Master Sh'!$G:$G,Summary!BI$2,'LOI and Commissioning Master Sh'!$H:$H,Summary!BI$3,'LOI and Commissioning Master Sh'!$BW:$BW, "Commissioned") -> 0 | BJ6: =COUNTIFS('LOI and Commissioning Master Sh'!$D:$D,Summary!$A6,'LOI and Commissioning Master Sh'!$G:$G,Summary!BJ$2,'LOI and Commissioning Master Sh'!$H:$H,Summary!BJ$3,'LOI and Commissioning Master Sh'!$BW:$BW, "Commissioned") -> 0 | BK6: =COUNTIFS('LOI and Commissioning Master Sh'!$D:$D,Summary!$A6,'LOI and Commissioning Master Sh'!$G:$G,Summary!BK$2,'LOI and Commissioning Master Sh'!$H:$H,Summary!BK$3,'LOI and Commissioning Master Sh'!$BW:$BW, "Commissioned") -> 0 | BL6: =COUNTIFS('LOI and Commissioning Master Sh'!$D:$D,Summary!$A6,'LOI and Commissioning Master Sh'!$G:$G,Summary!BL$2,'LOI and Commissioning Master Sh'!$H:$H,Summary!BL$3,'LOI and Commissioning Master Sh'!$BW:$BW, "Commissioned") -> 0 | BM6: =COUNTIFS('LOI and Commissioning Master Sh'!$D:$D,Summary!$A6,'LOI and Commissioning Master Sh'!$G:$G,Summary!BM$2,'LOI and Commissioning Master Sh'!$H:$H,Summary!BM$3,'LOI and Commissioning Master Sh'!$BW:$BW, "Commissioned") -> 0 | ... BQ6: =COUNTIFS('LOI and Commissioning Master Sh'!$D:$D,Summary!$A6,'LOI and Commissioning Master Sh'!$G:$G,Summary!BQ$2,'LOI and Commissioning Master Sh'!$H:$H,Summary!BQ$3,'LOI and Commissioning Master Sh'!$BW:$BW, "Commissioned") -> 0 | BR6: =+SUM(BF6:BQ6) -> 0
A7: Pimpri Chinchwad RSA | B7: =COUNTIFS('LOI and Commissioning Master Sh'!D:D,Summary!A7) -> 16 | C7: =COUNTIFS('LOI and Commissioning Master Sh'!$D:$D,Summary!$A7,'LOI and Commissioning Master Sh'!$X:$X,"Yes",'LOI and Commissioning Master Sh'!$H:$H,"A") -> 5 | D7: =COUNTIFS('LOI and Commissioning Master Sh'!$D:$D,Summary!$A7,'LOI and Commissioning Master Sh'!$X:$X,"Yes",'LOI and Commissioning Master Sh'!$H:$H,"B") -> 1 | E7: =C7+D7 -> 6 | F7: =+COUNTIFS('LOI and Commissioning Master Sh'!$D:$D,Summary!$A7,'LOI and Commissioning Master Sh'!$X:$X, "Yes",'LOI and Commissioning Master Sh'!$BK:$BK, "Yes") -> 5 | G7: =COUNTIFS('LOI and Commissioning Master Sh'!$D:$D,Summary!$A7,'LOI and Commissioning Master Sh'!$X:$X,"Yes",'LOI and Commissioning Master Sh'!$H:$H,"A",'LOI and Commissioning Master Sh'!$AC:$AC,"Yes") -> 1 | H7: =COUNTIFS('LOI and Commissioning Master Sh'!$D:$D,Summary!$A7,'LOI and Commissioning Master Sh'!$X:$X,"Yes",'LOI and Commissioning Master Sh'!$H:$H,"B",'LOI and Commissioning Master Sh'!$AC:$AC,"Yes") -> 0 | I7: =G7+H7 -> 1 | J7: =COUNTIFS('LOI and Commissioning Master Sh'!$D:$D,Summary!$A7,'LOI and Commissioning Master Sh'!$X:$X,"Yes",'LOI and Commissioning Master Sh'!$H:$H,"A",'LOI and Commissioning Master Sh'!$Y:$Y,"Yes") -> 2 | K7: =COUNTIFS('LOI and Commissioning Master Sh'!$D:$D,Summary!$A7,'LOI and Commissioning Master Sh'!$X:$X,"Yes",'LOI and Commissioning Master Sh'!$H:$H,"B",'LOI and Commissioning Master Sh'!$Y:$Y,"Yes") -> 1 | L7: =J7+K7 -> 3 | M7: =COUNTIFS('LOI and Commissioning Master Sh'!$D:$D,Summary!$A7, 'LOI and Commissioning Master Sh'!$G:$G,M$1,'LOI and Commissioning Master Sh'!$X:$X,"Yes",'LOI and Commissioning Master Sh'!$H:$H,M$3) -> 4 | N7: =COUNTIFS('LOI and Commissioning Master Sh'!$D:$D,Summary!$A7, 'LOI and Commissioning Master Sh'!$G:$G,N$1,'LOI and Commissioning Master Sh'!$X:$X,"Yes",'LOI and Commissioning Master Sh'!$H:$H,N$3) -> 1 | O7: =M7+N7 -> 5 | P7: =COUNTIFS('LOI and Commissioning Master Sh'!$D:$D,Summary!$A7, 'LOI and Commissioning Master Sh'!$G:$G,P$1,'LOI and Commissioning Master Sh'!$X:$X,"Yes",'LOI and Commissioning Master Sh'!$H:$H,P$3,'LOI and Commissioning Master Sh'!$AC:$AC,"Yes") -> 1 | Q7: =COUNTIFS('LOI and Commissioning Master Sh'!$D:$D,Summary!$A7, 'LOI and Commissioning Master Sh'!$G:$G,Q$1,'LOI and Commissioning Master Sh'!$X:$X,"Yes",'LOI and Commissioning Master Sh'!$H:$H,Q$3,'LOI and Commissioning Master Sh'!$AC:$AC,"Yes") -> 0 | R7: =P7+Q7 -> 1 | S7: =COUNTIFS('LOI and Commissioning Master Sh'!$D:$D,Summary!$A7, 'LOI and Commissioning Master Sh'!$G:$G,S$1,'LOI and Commissioning Master Sh'!$X:$X,"Yes",'LOI and Commissioning Master Sh'!$H:$H,S$3,'LOI and Commissioning Master Sh'!$Y:$Y,"Yes") -> 1 | T7: =COUNTIFS('LOI and Commissioning Master Sh'!$D:$D,Summary!$A7, 'LOI and Commissioning Master Sh'!$G:$G,T$1,'LOI and Commissioning Master Sh'!$X:$X,"Yes",'LOI and Commissioning Master Sh'!$H:$H,T$3,'LOI and Commissioning Master Sh'!$Y:$Y,"Yes") -> 1 | U7: =S7+T7 -> 2 | V7: =COUNTIFS('LOI and Commissioning Master Sh'!$D:$D,Summary!$A7, 'LOI and Commissioning Master Sh'!$G:$G,V$1,'LOI and Commissioning Master Sh'!$X:$X,"Yes",'LOI and Commissioning Master Sh'!$H:$H,V$3) -> 1 | W7: =COUNTIFS('LOI and Commissioning Master Sh'!$D:$D,Summary!$A7, 'LOI and Commissioning Master Sh'!$G:$G,W$1,'LOI and Commissioning Master Sh'!$X:$X,"Yes",'LOI and Commissioning Master Sh'!$H:$H,W$3) -> 0 | X7: =V7+W7 -> 1 | Y7: =COUNTIFS('LOI and Commissioning Master Sh'!$D:$D,Summary!$A7, 'LOI and Commissioning Master Sh'!$G:$G,Y$1,'LOI and Commissioning Master Sh'!$X:$X,"Yes",'LOI and Commissioning Master Sh'!$H:$H,Y$3,'LOI and Commissioning Master Sh'!$AC:$AC,"Yes") -> 0 | Z7: =COUNTIFS('LOI and Commissioning Master Sh'!$D:$D,Summary!$A7, 'LOI and Commissioning Master Sh'!$G:$G,Z$1,'LOI and Commissioning Master Sh'!$X:$X,"Yes",'LOI and Commissioning Master Sh'!$H:$H,Z$3,'LOI and Commissioning Master Sh'!$AC:$AC,"Yes") -> 0 | AA7: =Y7+Z7 -> 0 | AB7: =COUNTIFS('LOI and Commissioning Master Sh'!$D:$D,Summary!$A7, 'LOI and Commissioning Master Sh'!$G:$G,AB$1,'LOI and Commissioning Master Sh'!$X:$X,"Yes",'LOI and Commissioning Master Sh'!$H:$H,AB$3,'LOI and Commissioning Master Sh'!$Y:$Y,"Yes") -> 1 | AC7: =COUNTIFS('LOI and Commissioning Master Sh'!$D:$D,Summary!$A7, 'LOI and Commissioning Master Sh'!$G:$G,AC$1,'LOI and Commissioning Master Sh'!$X:$X,"Yes",'LOI and Commissioning Master Sh'!$H:$H,AC$3,'LOI and Commissioning Master Sh'!$Y:$Y,"Yes") -> 0 | AD7: =AB7+AC7 -> 1 | AE7: =COUNTIFS('LOI and Commissioning Master Sh'!$D:$D,Summary!$A7, 'LOI and Commissioning Master Sh'!$G:$G,AE$1,'LOI and Commissioning Master Sh'!$X:$X,"Yes",'LOI and Commissioning Master Sh'!$H:$H,AE$3) -> 0 | AF7: =COUNTIFS('LOI and Commissioning Master Sh'!$D:$D,Summary!$A7, 'LOI and Commissioning Master Sh'!$G:$G,AF$1,'LOI and Commissioning Master Sh'!$X:$X,"Yes",'LOI and Commissioning Master Sh'!$H:$H,AF$3) -> 0 | AG7: =AE7+AF7 -> 0 | AH7: =COUNTIFS('LOI and Commissioning Master Sh'!$D:$D,Summary!$A7, 'LOI and Commissioning Master Sh'!$G:$G,AH$1,'LOI and Commissioning Master Sh'!$X:$X,"Yes",'LOI and Commissioning Master Sh'!$H:$H,AH$3,'LOI and Commissioning Master Sh'!$AC:$AC,"Yes") -> 0 | AI7: =COUNTIFS('LOI and Commissioning Master Sh'!$D:$D,Summary!$A7, 'LOI and Commissioning Master Sh'!$G:$G,AI$1,'LOI and Commissioning Master Sh'!$X:$X,"Yes",'LOI and Commissioning Master Sh'!$H:$H,AI$3,'LOI and Commissioning Master Sh'!$AC:$AC,"Yes") -> 0 | AJ7: =AH7+AI7 -> 0 | AK7: =COUNTIFS('LOI and Commissioning Master Sh'!$D:$D,Summary!$A7, 'LOI and Commissioning Master Sh'!$G:$G,AK$1,'LOI and Commissioning Master Sh'!$X:$X,"Yes",'LOI and Commissioning Master Sh'!$H:$H,AK$3,'LOI and Commissioning Master Sh'!$Y:$Y,"Yes") -> 0 | AL7: =COUNTIFS('LOI and Commissioning Master Sh'!$D:$D,Summary!$A7, 'LOI and Commissioning Master Sh'!$G:$G,AL$1,'LOI and Commissioning Master Sh'!$X:$X,"Yes",'LOI and Commissioning Master Sh'!$H:$H,AL$3,'LOI and Commissioning Master Sh'!$Y:$Y,"Yes") -> 0 | AM7: =AK7+AL7 -> 0 | AN7: =COUNTIFS('LOI and Commissioning Master Sh'!$D:$D,Summary!$A7, 'LOI and Commissioning Master Sh'!$G:$G,AN$1,'LOI and Commissioning Master Sh'!$X:$X,"Yes",'LOI and Commissioning Master Sh'!$H:$H,AN$3) -> 0 | AO7: =COUNTIFS('LOI and Commissioning Master Sh'!$D:$D,Summary!$A7, 'LOI and Commissioning Master Sh'!$G:$G,AO$1,'LOI and Commissioning Master Sh'!$X:$X,"Yes",'LOI and Commissioning Master Sh'!$H:$H,AO$3) -> 0 | AP7: =AN7+AO7 -> 0 | AQ7: =COUNTIFS('LOI and Commissioning Master Sh'!$D:$D,Summary!$A7, 'LOI and Commissioning Master Sh'!$G:$G,AQ$1,'LOI and Commissioning Master Sh'!$X:$X,"Yes",'LOI and Commissioning Master Sh'!$H:$H,AQ$3,'LOI and Commissioning Master Sh'!$AC:$AC,"Yes") -> 0 | AR7: =COUNTIFS('LOI and Commissioning Master Sh'!$D:$D,Summary!$A7, 'LOI and Commissioning Master Sh'!$G:$G,AR$1,'LOI and Commissioning Master Sh'!$X:$X,"Yes",'LOI and Commissioning Master Sh'!$H:$H,AR$3,'LOI and Commissioning Master Sh'!$AC:$AC,"Yes") -> 0 | AS7: =AQ7+AR7 -> 0 | AT7: =COUNTIFS('LOI and Commissioning Master Sh'!$D:$D,Summary!$A7, 'LOI and Commissioning Master Sh'!$G:$G,AT$1,'LOI and Commissioning Master Sh'!$X:$X,"Yes",'LOI and Commissioning Master Sh'!$H:$H,AT$3,'LOI and Commissioning Master Sh'!$Y:$Y,"Yes") -> 0 | AU7: =COUNTIFS('LOI and Commissioning Master Sh'!$D:$D,Summary!$A7, 'LOI and Commissioning Master Sh'!$G:$G,AU$1,'LOI and Commissioning Master Sh'!$X:$X,"Yes",'LOI and Commissioning Master Sh'!$H:$H,AU$3,'LOI and Commissioning Master Sh'!$Y:$Y,"Yes") -> 0 | AV7: =AT7+AU7 -> 0 | AW7: =COUNTIFS('LOI and Commissioning Master Sh'!$D:$D,Summary!$A7, 'LOI and Commissioning Master Sh'!$G:$G,AW$1,'LOI and Commissioning Master Sh'!$X:$X,"Yes",'LOI and Commissioning Master Sh'!$H:$H,AW$3) -> 0 | AX7: =COUNTIFS('LOI and Commissioning Master Sh'!$D:$D,Summary!$A7, 'LOI and Commissioning Master Sh'!$G:$G,AX$1,'LOI and Commissioning Master Sh'!$X:$X,"Yes",'LOI and Commissioning Master Sh'!$H:$H,AX$3) -> 0 | AY7: =+AW7+AX7 -> 0 | AZ7: =COUNTIFS('LOI and Commissioning Master Sh'!$D:$D,Summary!$A7, 'LOI and Commissioning Master Sh'!$G:$G,AZ$1,'LOI and Commissioning Master Sh'!$X:$X,"Yes",'LOI and Commissioning Master Sh'!$H:$H,AZ$3,'LOI and Commissioning Master Sh'!$AC:$AC,"Yes") -> 0 | BA7: =COUNTIFS('LOI and Commissioning Master Sh'!$D:$D,Summary!$A7, 'LOI and Commissioning Master Sh'!$G:$G,BA$1,'LOI and Commissioning Master Sh'!$X:$X,"Yes",'LOI and Commissioning Master Sh'!$H:$H,BA$3,'LOI and Commissioning Master Sh'!$AC:$AC,"Yes") -> 0 | BB7: =+AZ7+BA7 -> 0 | BC7: =COUNTIFS('LOI and Commissioning Master Sh'!$D:$D,Summary!$A7, 'LOI and Commissioning Master Sh'!$G:$G,BC$1,'LOI and Commissioning Master Sh'!$X:$X,"Yes",'LOI and Commissioning Master Sh'!$H:$H,BC$3,'LOI and Commissioning Master Sh'!$Y:$Y,"Yes") -> 0 | BD7: =COUNTIFS('LOI and Commissioning Master Sh'!$D:$D,Summary!$A7, 'LOI and Commissioning Master Sh'!$G:$G,BD$1,'LOI and Commissioning Master Sh'!$X:$X,"Yes",'LOI and Commissioning Master Sh'!$H:$H,BD$3,'LOI and Commissioning Master Sh'!$Y:$Y,"Yes") -> 0 | BE7: =+BC7+BD7 -> 0 | BF7: =COUNTIFS('LOI and Commissioning Master Sh'!$D:$D,Summary!$A7,'LOI and Commissioning Master Sh'!$G:$G,Summary!BF$2,'LOI and Commissioning Master Sh'!$H:$H,Summary!BF$3,'LOI and Commissioning Master Sh'!$BW:$BW, "Commissioned") -> 1 | BG7: =COUNTIFS('LOI and Commissioning Master Sh'!$D:$D,Summary!$A7,'LOI and Commissioning Master Sh'!$G:$G,Summary!BG$2,'LOI and Commissioning Master Sh'!$H:$H,Summary!BG$3,'LOI and Commissioning Master Sh'!$BW:$BW, "Commissioned") -> 0 | BH7: =COUNTIFS('LOI and Commissioning Master Sh'!$D:$D,Summary!$A7,'LOI and Commissioning Master Sh'!$G:$G,Summary!BH$2,'LOI and Commissioning Master Sh'!$H:$H,Summary!BH$3,'LOI and Commissioning Master Sh'!$BW:$BW, "Commissioned") -> 0 | BI7: =COUNTIFS('LOI and Commissioning Master Sh'!$D:$D,Summary!$A7,'LOI and Commissioning Master Sh'!$G:$G,Summary!BI$2,'LOI and Commissioning Master Sh'!$H:$H,Summary!BI$3,'LOI and Commissioning Master Sh'!$BW:$BW, "Commissioned") -> 0 | BJ7: =COUNTIFS('LOI and Commissioning Master Sh'!$D:$D,Summary!$A7,'LOI and Commissioning Master Sh'!$G:$G,Summary!BJ$2,'LOI and Commissioning Master Sh'!$H:$H,Summary!BJ$3,'LOI and Commissioning Master Sh'!$BW:$BW, "Commissioned") -> 0 | BK7: =COUNTIFS('LOI and Commissioning Master Sh'!$D:$D,Summary!$A7,'LOI and Commissioning Master Sh'!$G:$G,Summary!BK$2,'LOI and Commissioning Master Sh'!$H:$H,Summary!BK$3,'LOI and Commissioning Master Sh'!$BW:$BW, "Commissioned") -> 0 | BL7: =COUNTIFS('LOI and Commissioning Master Sh'!$D:$D,Summary!$A7,'LOI and Commissioning Master Sh'!$G:$G,Summary!BL$2,'LOI and Commissioning Master Sh'!$H:$H,Summary!BL$3,'LOI and Commissioning Master Sh'!$BW:$BW, "Commissioned") -> 0 | BM7: =COUNTIFS('LOI and Commissioning Master Sh'!$D:$D,Summary!$A7,'LOI and Commissioning Master Sh'!$G:$G,Summary!BM$2,'LOI and Commissioning Master Sh'!$H:$H,Summary!BM$3,'LOI and Commissioning Master Sh'!$BW:$BW, "Commissioned") -> 0 | ... BQ7: =COUNTIFS('LOI and Commissioning Master Sh'!$D:$D,Summary!$A7,'LOI and Commissioning Master Sh'!$G:$G,Summary!BQ$2,'LOI and Commissioning Master Sh'!$H:$H,Summary!BQ$3,'LOI and Commissioning Master Sh'!$BW:$BW, "Commissioned") -> 0 | BR7: =+SUM(BF7:BQ7) -> 1
A8: Pune Saswad RSA | B8: =COUNTIFS('LOI and Commissioning Master Sh'!D:D,Summary!A8) -> 28 | C8: =COUNTIFS('LOI and Commissioning Master Sh'!$D:$D,Summary!$A8,'LOI and Commissioning Master Sh'!$X:$X,"Yes",'LOI and Commissioning Master Sh'!$H:$H,"A") -> 4 | D8: =COUNTIFS('LOI and Commissioning Master Sh'!$D:$D,Summary!$A8,'LOI and Commissioning Master Sh'!$X:$X,"Yes",'LOI and Commissioning Master Sh'!$H:$H,"B") -> 5 | E8: =C8+D8 -> 9 | F8: =+COUNTIFS('LOI and Commissioning Master Sh'!$D:$D,Summary!$A8,'LOI and Commissioning Master Sh'!$X:$X, "Yes",'LOI and Commissioning Master Sh'!$BK:$BK, "Yes") -> 9 | G8: =COUNTIFS('LOI and Commissioning Master Sh'!$D:$D,Summary!$A8,'LOI and Commissioning Master Sh'!$X:$X,"Yes",'LOI and Commissioning Master Sh'!$H:$H,"A",'LOI and Commissioning Master Sh'!$AC:$AC,"Yes") -> 1 | H8: =COUNTIFS('LOI and Commissioning Master Sh'!$D:$D,Summary!$A8,'LOI and Commissioning Master Sh'!$X:$X,"Yes",'LOI and Commissioning Master Sh'!$H:$H,"B",'LOI and Commissioning Master Sh'!$AC:$AC,"Yes") -> 1 | I8: =G8+H8 -> 2 | J8: =COUNTIFS('LOI and Commissioning Master Sh'!$D:$D,Summary!$A8,'LOI and Commissioning Master Sh'!$X:$X,"Yes",'LOI and Commissioning Master Sh'!$H:$H,"A",'LOI and Commissioning Master Sh'!$Y:$Y,"Yes") -> 2 | K8: =COUNTIFS('LOI and Commissioning Master Sh'!$D:$D,Summary!$A8,'LOI and Commissioning Master Sh'!$X:$X,"Yes",'LOI and Commissioning Master Sh'!$H:$H,"B",'LOI and Commissioning Master Sh'!$Y:$Y,"Yes") -> 1 | L8: =J8+K8 -> 3 | M8: =COUNTIFS('LOI and Commissioning Master Sh'!$D:$D,Summary!$A8, 'LOI and Commissioning Master Sh'!$G:$G,M$1,'LOI and Commissioning Master Sh'!$X:$X,"Yes",'LOI and Commissioning Master Sh'!$H:$H,M$3) -> 0 | N8: =COUNTIFS('LOI and Commissioning Master Sh'!$D:$D,Summary!$A8, 'LOI and Commissioning Master Sh'!$G:$G,N$1,'LOI and Commissioning Master Sh'!$X:$X,"Yes",'LOI and Commissioning Master Sh'!$H:$H,N$3) -> 0 | O8: =M8+N8 -> 0 | P8: =COUNTIFS('LOI and Commissioning Master Sh'!$D:$D,Summary!$A8, 'LOI and Commissioning Master Sh'!$G:$G,P$1,'LOI and Commissioning Master Sh'!$X:$X,"Yes",'LOI and Commissioning Master Sh'!$H:$H,P$3,'LOI and Commissioning Master Sh'!$AC:$AC,"Yes") -> 0 | Q8: =COUNTIFS('LOI and Commissioning Master Sh'!$D:$D,Summary!$A8, 'LOI and Commissioning Master Sh'!$G:$G,Q$1,'LOI and Commissioning Master Sh'!$X:$X,"Yes",'LOI and Commissioning Master Sh'!$H:$H,Q$3,'LOI and Commissioning Master Sh'!$AC:$AC,"Yes") -> 0 | R8: =P8+Q8 -> 0 | S8: =COUNTIFS('LOI and Commissioning Master Sh'!$D:$D,Summary!$A8, 'LOI and Commissioning Master Sh'!$G:$G,S$1,'LOI and Commissioning Master Sh'!$X:$X,"Yes",'LOI and Commissioning Master Sh'!$H:$H,S$3,'LOI and Commissioning Master Sh'!$Y:$Y,"Yes") -> 0 | T8: =COUNTIFS('LOI and Commissioning Master Sh'!$D:$D,Summary!$A8, 'LOI and Commissioning Master Sh'!$G:$G,T$1,'LOI and Commissioning Master Sh'!$X:$X,"Yes",'LOI and Commissioning Master Sh'!$H:$H,T$3,'LOI and Commissioning Master Sh'!$Y:$Y,"Yes") -> 0 | U8: =S8+T8 -> 0 | V8: =COUNTIFS('LOI and Commissioning Master Sh'!$D:$D,Summary!$A8, 'LOI and Commissioning Master Sh'!$G:$G,V$1,'LOI and Commissioning Master Sh'!$X:$X,"Yes",'LOI and Commissioning Master Sh'!$H:$H,V$3) -> 4 | W8: =COUNTIFS('LOI and Commissioning Master Sh'!$D:$D,Summary!$A8, 'LOI and Commissioning Master Sh'!$G:$G,W$1,'LOI and Commissioning Master Sh'!$X:$X,"Yes",'LOI and Commissioning Master Sh'!$H:$H,W$3) -> 3 | X8: =V8+W8 -> 7 | Y8: =COUNTIFS('LOI and Commissioning Master Sh'!$D:$D,Summary!$A8, 'LOI and Commissioning Master Sh'!$G:$G,Y$1,'LOI and Commissioning Master Sh'!$X:$X,"Yes",'LOI and Commissioning Master Sh'!$H:$H,Y$3,'LOI and Commissioning Master Sh'!$AC:$AC,"Yes") -> 1 | Z8: =COUNTIFS('LOI and Commissioning Master Sh'!$D:$D,Summary!$A8, 'LOI and Commissioning Master Sh'!$G:$G,Z$1,'LOI and Commissioning Master Sh'!$X:$X,"Yes",'LOI and Commissioning Master Sh'!$H:$H,Z$3,'LOI and Commissioning Master Sh'!$AC:$AC,"Yes") -> 0 | AA8: =Y8+Z8 -> 1 | AB8: =COUNTIFS('LOI and Commissioning Master Sh'!$D:$D,Summary!$A8, 'LOI and Commissioning Master Sh'!$G:$G,AB$1,'LOI and Commissioning Master Sh'!$X:$X,"Yes",'LOI and Commissioning Master Sh'!$H:$H,AB$3,'LOI and Commissioning Master Sh'!$Y:$Y,"Yes") -> 2 | AC8: =COUNTIFS('LOI and Commissioning Master Sh'!$D:$D,Summary!$A8, 'LOI and Commissioning Master Sh'!$G:$G,AC$1,'LOI and Commissioning Master Sh'!$X:$X,"Yes",'LOI and Commissioning Master Sh'!$H:$H,AC$3,'LOI and Commissioning Master Sh'!$Y:$Y,"Yes") -> 0 | AD8: =AB8+AC8 -> 2 | AE8: =COUNTIFS('LOI and Commissioning Master Sh'!$D:$D,Summary!$A8, 'LOI and Commissioning Master Sh'!$G:$G,AE$1,'LOI and Commissioning Master Sh'!$X:$X,"Yes",'LOI and Commissioning Master Sh'!$H:$H,AE$3) -> 0 | AF8: =COUNTIFS('LOI and Commissioning Master Sh'!$D:$D,Summary!$A8, 'LOI and Commissioning Master Sh'!$G:$G,AF$1,'LOI and Commissioning Master Sh'!$X:$X,"Yes",'LOI and Commissioning Master Sh'!$H:$H,AF$3) -> 0 | AG8: =AE8+AF8 -> 0 | AH8: =COUNTIFS('LOI and Commissioning Master Sh'!$D:$D,Summary!$A8, 'LOI and Commissioning Master Sh'!$G:$G,AH$1,'LOI and Commissioning Master Sh'!$X:$X,"Yes",'LOI and Commissioning Master Sh'!$H:$H,AH$3,'LOI and Commissioning Master Sh'!$AC:$AC,"Yes") -> 0 | AI8: =COUNTIFS('LOI and Commissioning Master Sh'!$D:$D,Summary!$A8, 'LOI and Commissioning Master Sh'!$G:$G,AI$1,'LOI and Commissioning Master Sh'!$X:$X,"Yes",'LOI and Commissioning Master Sh'!$H:$H,AI$3,'LOI and Commissioning Master Sh'!$AC:$AC,"Yes") -> 0 | AJ8: =AH8+AI8 -> 0 | AK8: =COUNTIFS('LOI and Commissioning Master Sh'!$D:$D,Summary!$A8, 'LOI and Commissioning Master Sh'!$G:$G,AK$1,'LOI and Commissioning Master Sh'!$X:$X,"Yes",'LOI and Commissioning Master Sh'!$H:$H,AK$3,'LOI and Commissioning Master Sh'!$Y:$Y,"Yes") -> 0 | AL8: =COUNTIFS('LOI and Commissioning Master Sh'!$D:$D,Summary!$A8, 'LOI and Commissioning Master Sh'!$G:$G,AL$1,'LOI and Commissioning Master Sh'!$X:$X,"Yes",'LOI and Commissioning Master Sh'!$H:$H,AL$3,'LOI and Commissioning Master Sh'!$Y:$Y,"Yes") -> 0 | AM8: =AK8+AL8 -> 0 | AN8: =COUNTIFS('LOI and Commissioning Master Sh'!$D:$D,Summary!$A8, 'LOI and Commissioning Master Sh'!$G:$G,AN$1,'LOI and Commissioning Master Sh'!$X:$X,"Yes",'LOI and Commissioning Master Sh'!$H:$H,AN$3) -> 0 | AO8: =COUNTIFS('LOI and Commissioning Master Sh'!$D:$D,Summary!$A8, 'LOI and Commissioning Master Sh'!$G:$G,AO$1,'LOI and Commissioning Master Sh'!$X:$X,"Yes",'LOI and Commissioning Master Sh'!$H:$H,AO$3) -> 0 | AP8: =AN8+AO8 -> 0 | AQ8: =COUNTIFS('LOI and Commissioning Master Sh'!$D:$D,Summary!$A8, 'LOI and Commissioning Master Sh'!$G:$G,AQ$1,'LOI and Commissioning Master Sh'!$X:$X,"Yes",'LOI and Commissioning Master Sh'!$H:$H,AQ$3,'LOI and Commissioning Master Sh'!$AC:$AC,"Yes") -> 0 | AR8: =COUNTIFS('LOI and Commissioning Master Sh'!$D:$D,Summary!$A8, 'LOI and Commissioning Master Sh'!$G:$G,AR$1,'LOI and Commissioning Master Sh'!$X:$X,"Yes",'LOI and Commissioning Master Sh'!$H:$H,AR$3,'LOI and Commissioning Master Sh'!$AC:$AC,"Yes") -> 0 | AS8: =AQ8+AR8 -> 0 | AT8: =COUNTIFS('LOI and Commissioning Master Sh'!$D:$D,Summary!$A8, 'LOI and Commissioning Master Sh'!$G:$G,AT$1,'LOI and Commissioning Master Sh'!$X:$X,"Yes",'LOI and Commissioning Master Sh'!$H:$H,AT$3,'LOI and Commissioning Master Sh'!$Y:$Y,"Yes") -> 0 | AU8: =COUNTIFS('LOI and Commissioning Master Sh'!$D:$D,Summary!$A8, 'LOI and Commissioning Master Sh'!$G:$G,AU$1,'LOI and Commissioning Master Sh'!$X:$X,"Yes",'LOI and Commissioning Master Sh'!$H:$H,AU$3,'LOI and Commissioning Master Sh'!$Y:$Y,"Yes") -> 0 | AV8: =AT8+AU8 -> 0 | AW8: =COUNTIFS('LOI and Commissioning Master Sh'!$D:$D,Summary!$A8, 'LOI and Commissioning Master Sh'!$G:$G,AW$1,'LOI and Commissioning Master Sh'!$X:$X,"Yes",'LOI and Commissioning Master Sh'!$H:$H,AW$3) -> 0 | AX8: =COUNTIFS('LOI and Commissioning Master Sh'!$D:$D,Summary!$A8, 'LOI and Commissioning Master Sh'!$G:$G,AX$1,'LOI and Commissioning Master Sh'!$X:$X,"Yes",'LOI and Commissioning Master Sh'!$H:$H,AX$3) -> 2 | AY8: =+AW8+AX8 -> 2 | AZ8: =COUNTIFS('LOI and Commissioning Master Sh'!$D:$D,Summary!$A8, 'LOI and Commissioning Master Sh'!$G:$G,AZ$1,'LOI and Commissioning Master Sh'!$X:$X,"Yes",'LOI and Commissioning Master Sh'!$H:$H,AZ$3,'LOI and Commissioning Master Sh'!$AC:$AC,"Yes") -> 0 | BA8: =COUNTIFS('LOI and Commissioning Master Sh'!$D:$D,Summary!$A8, 'LOI and Commissioning Master Sh'!$G:$G,BA$1,'LOI and Commissioning Master Sh'!$X:$X,"Yes",'LOI and Commissioning Master Sh'!$H:$H,BA$3,'LOI and Commissioning Master Sh'!$AC:$AC,"Yes") -> 1 | BB8: =+AZ8+BA8 -> 1 | BC8: =COUNTIFS('LOI and Commissioning Master Sh'!$D:$D,Summary!$A8, 'LOI and Commissioning Master Sh'!$G:$G,BC$1,'LOI and Commissioning Master Sh'!$X:$X,"Yes",'LOI and Commissioning Master Sh'!$H:$H,BC$3,'LOI and Commissioning Master Sh'!$Y:$Y,"Yes") -> 0 | BD8: =COUNTIFS('LOI and Commissioning Master Sh'!$D:$D,Summary!$A8, 'LOI and Commissioning Master Sh'!$G:$G,BD$1,'LOI and Commissioning Master Sh'!$X:$X,"Yes",'LOI and Commissioning Master Sh'!$H:$H,BD$3,'LOI and Commissioning Master Sh'!$Y:$Y,"Yes") -> 1 | BE8: =+BC8+BD8 -> 1 | BF8: =COUNTIFS('LOI and Commissioning Master Sh'!$D:$D,Summary!$A8,'LOI and Commissioning Master Sh'!$G:$G,Summary!BF$2,'LOI and Commissioning Master Sh'!$H:$H,Summary!BF$3,'LOI and Commissioning Master Sh'!$BW:$BW, "Commissioned") -> 0 | BG8: =COUNTIFS('LOI and Commissioning Master Sh'!$D:$D,Summary!$A8,'LOI and Commissioning Master Sh'!$G:$G,Summary!BG$2,'LOI and Commissioning Master Sh'!$H:$H,Summary!BG$3,'LOI and Commissioning Master Sh'!$BW:$BW, "Commissioned") -> 0 | BH8: =COUNTIFS('LOI and Commissioning Master Sh'!$D:$D,Summary!$A8,'LOI and Commissioning Master Sh'!$G:$G,Summary!BH$2,'LOI and Commissioning Master Sh'!$H:$H,Summary!BH$3,'LOI and Commissioning Master Sh'!$BW:$BW, "Commissioned") -> 0 | BI8: =COUNTIFS('LOI and Commissioning Master Sh'!$D:$D,Summary!$A8,'LOI and Commissioning Master Sh'!$G:$G,Summary!BI$2,'LOI and Commissioning Master Sh'!$H:$H,Summary!BI$3,'LOI and Commissioning Master Sh'!$BW:$BW, "Commissioned") -> 0 | BJ8: =COUNTIFS('LOI and Commissioning Master Sh'!$D:$D,Summary!$A8,'LOI and Commissioning Master Sh'!$G:$G,Summary!BJ$2,'LOI and Commissioning Master Sh'!$H:$H,Summary!BJ$3,'LOI and Commissioning Master Sh'!$BW:$BW, "Commissioned") -> 0 | BK8: =COUNTIFS('LOI and Commissioning Master Sh'!$D:$D,Summary!$A8,'LOI and Commissioning Master Sh'!$G:$G,Summary!BK$2,'LOI and Commissioning Master Sh'!$H:$H,Summary!BK$3,'LOI and Commissioning Master Sh'!$BW:$BW, "Commissioned") -> 0 | BL8: =COUNTIFS('LOI and Commissioning Master Sh'!$D:$D,Summary!$A8,'LOI and Commissioning Master Sh'!$G:$G,Summary!BL$2,'LOI and Commissioning Master Sh'!$H:$H,Summary!BL$3,'LOI and Commissioning Master Sh'!$BW:$BW, "Commissioned") -> 1 | BM8: =COUNTIFS('LOI and Commissioning Master Sh'!$D:$D,Summary!$A8,'LOI and Commissioning Master Sh'!$G:$G,Summary!BM$2,'LOI and Commissioning Master Sh'!$H:$H,Summary!BM$3,'LOI and Commissioning Master Sh'!$BW:$BW, "Commissioned") -> 0 | ... BQ8: =COUNTIFS('LOI and Commissioning Master Sh'!$D:$D,Summary!$A8,'LOI and Commissioning Master Sh'!$G:$G,Summary!BQ$2,'LOI and Commissioning Master Sh'!$H:$H,Summary!BQ$3,'LOI and Commissioning Master Sh'!$BW:$BW, "Commissioned") -> 1 | BR8: =+SUM(BF8:BQ8) -> 2
A9: Pune Wagholi RSA | B9: =COUNTIFS('LOI and Commissioning Master Sh'!D:D,Summary!A9) -> 34 | C9: =COUNTIFS('LOI and Commissioning Master Sh'!$D:$D,Summary!$A9,'LOI and Commissioning Master Sh'!$X:$X,"Yes",'LOI and Commissioning Master Sh'!$H:$H,"A") -> 2 | D9: =COUNTIFS('LOI and Commissioning Master Sh'!$D:$D,Summary!$A9,'LOI and Commissioning Master Sh'!$X:$X,"Yes",'LOI and Commissioning Master Sh'!$H:$H,"B") -> 6 | E9: =C9+D9 -> 8 | F9: =+COUNTIFS('LOI and Commissioning Master Sh'!$D:$D,Summary!$A9,'LOI and Commissioning Master Sh'!$X:$X, "Yes",'LOI and Commissioning Master Sh'!$BK:$BK, "Yes") -> 7 | G9: =COUNTIFS('LOI and Commissioning Master Sh'!$D:$D,Summary!$A9,'LOI and Commissioning Master Sh'!$X:$X,"Yes",'LOI and Commissioning Master Sh'!$H:$H,"A",'LOI and Commissioning Master Sh'!$AC:$AC,"Yes") -> 0 | H9: =COUNTIFS('LOI and Commissioning Master Sh'!$D:$D,Summary!$A9,'LOI and Commissioning Master Sh'!$X:$X,"Yes",'LOI and Commissioning Master Sh'!$H:$H,"B",'LOI and Commissioning Master Sh'!$AC:$AC,"Yes") -> 1 | I9: =G9+H9 -> 1 | J9: =COUNTIFS('LOI and Commissioning Master Sh'!$D:$D,Summary!$A9,'LOI and Commissioning Master Sh'!$X:$X,"Yes",'LOI and Commissioning Master Sh'!$H:$H,"A",'LOI and Commissioning Master Sh'!$Y:$Y,"Yes") -> 0 | K9: =COUNTIFS('LOI and Commissioning Master Sh'!$D:$D,Summary!$A9,'LOI and Commissioning Master Sh'!$X:$X,"Yes",'LOI and Commissioning Master Sh'!$H:$H,"B",'LOI and Commissioning Master Sh'!$Y:$Y,"Yes") -> 2 | L9: =J9+K9 -> 2 | M9: =COUNTIFS('LOI and Commissioning Master Sh'!$D:$D,Summary!$A9, 'LOI and Commissioning Master Sh'!$G:$G,M$1,'LOI and Commissioning Master Sh'!$X:$X,"Yes",'LOI and Commissioning Master Sh'!$H:$H,M$3) -> 0 | N9: =COUNTIFS('LOI and Commissioning Master Sh'!$D:$D,Summary!$A9, 'LOI and Commissioning Master Sh'!$G:$G,N$1,'LOI and Commissioning Master Sh'!$X:$X,"Yes",'LOI and Commissioning Master Sh'!$H:$H,N$3) -> 0 | O9: =M9+N9 -> 0 | P9: =COUNTIFS('LOI and Commissioning Master Sh'!$D:$D,Summary!$A9, 'LOI and Commissioning Master Sh'!$G:$G,P$1,'LOI and Commissioning Master Sh'!$X:$X,"Yes",'LOI and Commissioning Master Sh'!$H:$H,P$3,'LOI and Commissioning Master Sh'!$AC:$AC,"Yes") -> 0 | Q9: =COUNTIFS('LOI and Commissioning Master Sh'!$D:$D,Summary!$A9, 'LOI and Commissioning Master Sh'!$G:$G,Q$1,'LOI and Commissioning Master Sh'!$X:$X,"Yes",'LOI and Commissioning Master Sh'!$H:$H,Q$3,'LOI and Commissioning Master Sh'!$AC:$AC,"Yes") -> 0 | R9: =P9+Q9 -> 0 | S9: =COUNTIFS('LOI and Commissioning Master Sh'!$D:$D,Summary!$A9, 'LOI and Commissioning Master Sh'!$G:$G,S$1,'LOI and Commissioning Master Sh'!$X:$X,"Yes",'LOI and Commissioning Master Sh'!$H:$H,S$3,'LOI and Commissioning Master Sh'!$Y:$Y,"Yes") -> 0 | T9: =COUNTIFS('LOI and Commissioning Master Sh'!$D:$D,Summary!$A9, 'LOI and Commissioning Master Sh'!$G:$G,T$1,'LOI and Commissioning Master Sh'!$X:$X,"Yes",'LOI and Commissioning Master Sh'!$H:$H,T$3,'LOI and Commissioning Master Sh'!$Y:$Y,"Yes") -> 0 | U9: =S9+T9 -> 0 | V9: =COUNTIFS('LOI and Commissioning Master Sh'!$D:$D,Summary!$A9, 'LOI and Commissioning Master Sh'!$G:$G,V$1,'LOI and Commissioning Master Sh'!$X:$X,"Yes",'LOI and Commissioning Master Sh'!$H:$H,V$3) -> 1 | W9: =COUNTIFS('LOI and Commissioning Master Sh'!$D:$D,Summary!$A9, 'LOI and Commissioning Master Sh'!$G:$G,W$1,'LOI and Commissioning Master Sh'!$X:$X,"Yes",'LOI and Commissioning Master Sh'!$H:$H,W$3) -> 2 | X9: =V9+W9 -> 3 | Y9: =COUNTIFS('LOI and Commissioning Master Sh'!$D:$D,Summary!$A9, 'LOI and Commissioning Master Sh'!$G:$G,Y$1,'LOI and Commissioning Master Sh'!$X:$X,"Yes",'LOI and Commissioning Master Sh'!$H:$H,Y$3,'LOI and Commissioning Master Sh'!$AC:$AC,"Yes") -> 0 | Z9: =COUNTIFS('LOI and Commissioning Master Sh'!$D:$D,Summary!$A9, 'LOI and Commissioning Master Sh'!$G:$G,Z$1,'LOI and Commissioning Master Sh'!$X:$X,"Yes",'LOI and Commissioning Master Sh'!$H:$H,Z$3,'LOI and Commissioning Master Sh'!$AC:$AC,"Yes") -> 0 | AA9: =Y9+Z9 -> 0 | AB9: =COUNTIFS('LOI and Commissioning Master Sh'!$D:$D,Summary!$A9, 'LOI and Commissioning Master Sh'!$G:$G,AB$1,'LOI and Commissioning Master Sh'!$X:$X,"Yes",'LOI and Commissioning Master Sh'!$H:$H,AB$3,'LOI and Commissioning Master Sh'!$Y:$Y,"Yes") -> 0 | AC9: =COUNTIFS('LOI and Commissioning Master Sh'!$D:$D,Summary!$A9, 'LOI and Commissioning Master Sh'!$G:$G,AC$1,'LOI and Commissioning Master Sh'!$X:$X,"Yes",'LOI and Commissioning Master Sh'!$H:$H,AC$3,'LOI and Commissioning Master Sh'!$Y:$Y,"Yes") -> 1 | AD9: =AB9+AC9 -> 1 | AE9: =COUNTIFS('LOI and Commissioning Master Sh'!$D:$D,Summary!$A9, 'LOI and Commissioning Master Sh'!$G:$G,AE$1,'LOI and Commissioning Master Sh'!$X:$X,"Yes",'LOI and Commissioning Master Sh'!$H:$H,AE$3) -> 1 | AF9: =COUNTIFS('LOI and Commissioning Master Sh'!$D:$D,Summary!$A9, 'LOI and Commissioning Master Sh'!$G:$G,AF$1,'LOI and Commissioning Master Sh'!$X:$X,"Yes",'LOI and Commissioning Master Sh'!$H:$H,AF$3) -> 4 | AG9: =AE9+AF9 -> 5 | AH9: =COUNTIFS('LOI and Commissioning Master Sh'!$D:$D,Summary!$A9, 'LOI and Commissioning Master Sh'!$G:$G,AH$1,'LOI and Commissioning Master Sh'!$X:$X,"Yes",'LOI and Commissioning Master Sh'!$H:$H,AH$3,'LOI and Commissioning Master Sh'!$AC:$AC,"Yes") -> 0 | AI9: =COUNTIFS('LOI and Commissioning Master Sh'!$D:$D,Summary!$A9, 'LOI and Commissioning Master Sh'!$G:$G,AI$1,'LOI and Commissioning Master Sh'!$X:$X,"Yes",'LOI and Commissioning Master Sh'!$H:$H,AI$3,'LOI and Commissioning Master Sh'!$AC:$AC,"Yes") -> 1 | AJ9: =AH9+AI9 -> 1 | AK9: =COUNTIFS('LOI and Commissioning Master Sh'!$D:$D,Summary!$A9, 'LOI and Commissioning Master Sh'!$G:$G,AK$1,'LOI and Commissioning Master Sh'!$X:$X,"Yes",'LOI and Commissioning Master Sh'!$H:$H,AK$3,'LOI and Commissioning Master Sh'!$Y:$Y,"Yes") -> 0 | AL9: =COUNTIFS('LOI and Commissioning Master Sh'!$D:$D,Summary!$A9, 'LOI and Commissioning Master Sh'!$G:$G,AL$1,'LOI and Commissioning Master Sh'!$X:$X,"Yes",'LOI and Commissioning Master Sh'!$H:$H,AL$3,'LOI and Commissioning Master Sh'!$Y:$Y,"Yes") -> 1 | AM9: =AK9+AL9 -> 1 | AN9: =COUNTIFS('LOI and Commissioning Master Sh'!$D:$D,Summary!$A9, 'LOI and Commissioning Master Sh'!$G:$G,AN$1,'LOI and Commissioning Master Sh'!$X:$X,"Yes",'LOI and Commissioning Master Sh'!$H:$H,AN$3) -> 0 | AO9: =COUNTIFS('LOI and Commissioning Master Sh'!$D:$D,Summary!$A9, 'LOI and Commissioning Master Sh'!$G:$G,AO$1,'LOI and Commissioning Master Sh'!$X:$X,"Yes",'LOI and Commissioning Master Sh'!$H:$H,AO$3) -> 0 | AP9: =AN9+AO9 -> 0 | AQ9: =COUNTIFS('LOI and Commissioning Master Sh'!$D:$D,Summary!$A9, 'LOI and Commissioning Master Sh'!$G:$G,AQ$1,'LOI and Commissioning Master Sh'!$X:$X,"Yes",'LOI and Commissioning Master Sh'!$H:$H,AQ$3,'LOI and Commissioning Master Sh'!$AC:$AC,"Yes") -> 0 | AR9: =COUNTIFS('LOI and Commissioning Master Sh'!$D:$D,Summary!$A9, 'LOI and Commissioning Master Sh'!$G:$G,AR$1,'LOI and Commissioning Master Sh'!$X:$X,"Yes",'LOI and Commissioning Master Sh'!$H:$H,AR$3,'LOI and Commissioning Master Sh'!$AC:$AC,"Yes") -> 0 | AS9: =AQ9+AR9 -> 0 | AT9: =COUNTIFS('LOI and Commissioning Master Sh'!$D:$D,Summary!$A9, 'LOI and Commissioning Master Sh'!$G:$G,AT$1,'LOI and Commissioning Master Sh'!$X:$X,"Yes",'LOI and Commissioning Master Sh'!$H:$H,AT$3,'LOI and Commissioning Master Sh'!$Y:$Y,"Yes") -> 0 | AU9: =COUNTIFS('LOI and Commissioning Master Sh'!$D:$D,Summary!$A9, 'LOI and Commissioning Master Sh'!$G:$G,AU$1,'LOI and Commissioning Master Sh'!$X:$X,"Yes",'LOI and Commissioning Master Sh'!$H:$H,AU$3,'LOI and Commissioning Master Sh'!$Y:$Y,"Yes") -> 0 | AV9: =AT9+AU9 -> 0 | AW9: =COUNTIFS('LOI and Commissioning Master Sh'!$D:$D,Summary!$A9, 'LOI and Commissioning Master Sh'!$G:$G,AW$1,'LOI and Commissioning Master Sh'!$X:$X,"Yes",'LOI and Commissioning Master Sh'!$H:$H,AW$3) -> 0 | AX9: =COUNTIFS('LOI and Commissioning Master Sh'!$D:$D,Summary!$A9, 'LOI and Commissioning Master Sh'!$G:$G,AX$1,'LOI and Commissioning Master Sh'!$X:$X,"Yes",'LOI and Commissioning Master Sh'!$H:$H,AX$3) -> 0 | AY9: =+AW9+AX9 -> 0 | AZ9: =COUNTIFS('LOI and Commissioning Master Sh'!$D:$D,Summary!$A9, 'LOI and Commissioning Master Sh'!$G:$G,AZ$1,'LOI and Commissioning Master Sh'!$X:$X,"Yes",'LOI and Commissioning Master Sh'!$H:$H,AZ$3,'LOI and Commissioning Master Sh'!$AC:$AC,"Yes") -> 0 | BA9: =COUNTIFS('LOI and Commissioning Master Sh'!$D:$D,Summary!$A9, 'LOI and Commissioning Master Sh'!$G:$G,BA$1,'LOI and Commissioning Master Sh'!$X:$X,"Yes",'LOI and Commissioning Master Sh'!$H:$H,BA$3,'LOI and Commissioning Master Sh'!$AC:$AC,"Yes") -> 0 | BB9: =+AZ9+BA9 -> 0 | BC9: =COUNTIFS('LOI and Commissioning Master Sh'!$D:$D,Summary!$A9, 'LOI and Commissioning Master Sh'!$G:$G,BC$1,'LOI and Commissioning Master Sh'!$X:$X,"Yes",'LOI and Commissioning Master Sh'!$H:$H,BC$3,'LOI and Commissioning Master Sh'!$Y:$Y,"Yes") -> 0 | BD9: =COUNTIFS('LOI and Commissioning Master Sh'!$D:$D,Summary!$A9, 'LOI and Commissioning Master Sh'!$G:$G,BD$1,'LOI and Commissioning Master Sh'!$X:$X,"Yes",'LOI and Commissioning Master Sh'!$H:$H,BD$3,'LOI and Commissioning Master Sh'!$Y:$Y,"Yes") -> 0 | BE9: =+BC9+BD9 -> 0 | BF9: =COUNTIFS('LOI and Commissioning Master Sh'!$D:$D,Summary!$A9,'LOI and Commissioning Master Sh'!$G:$G,Summary!BF$2,'LOI and Commissioning Master Sh'!$H:$H,Summary!BF$3,'LOI and Commissioning Master Sh'!$BW:$BW, "Commissioned") -> 0 | BG9: =COUNTIFS('LOI and Commissioning Master Sh'!$D:$D,Summary!$A9,'LOI and Commissioning Master Sh'!$G:$G,Summary!BG$2,'LOI and Commissioning Master Sh'!$H:$H,Summary!BG$3,'LOI and Commissioning Master Sh'!$BW:$BW, "Commissioned") -> 0 | BH9: =COUNTIFS('LOI and Commissioning Master Sh'!$D:$D,Summary!$A9,'LOI and Commissioning Master Sh'!$G:$G,Summary!BH$2,'LOI and Commissioning Master Sh'!$H:$H,Summary!BH$3,'LOI and Commissioning Master Sh'!$BW:$BW, "Commissioned") -> 0 | BI9: =COUNTIFS('LOI and Commissioning Master Sh'!$D:$D,Summary!$A9,'LOI and Commissioning Master Sh'!$G:$G,Summary!BI$2,'LOI and Commissioning Master Sh'!$H:$H,Summary!BI$3,'LOI and Commissioning Master Sh'!$BW:$BW, "Commissioned") -> 0 | BJ9: =COUNTIFS('LOI and Commissioning Master Sh'!$D:$D,Summary!$A9,'LOI and Commissioning Master Sh'!$G:$G,Summary!BJ$2,'LOI and Commissioning Master Sh'!$H:$H,Summary!BJ$3,'LOI and Commissioning Master Sh'!$BW:$BW, "Commissioned") -> 0 | BK9: =COUNTIFS('LOI and Commissioning Master Sh'!$D:$D,Summary!$A9,'LOI and Commissioning Master Sh'!$G:$G,Summary!BK$2,'LOI and Commissioning Master Sh'!$H:$H,Summary!BK$3,'LOI and Commissioning Master Sh'!$BW:$BW, "Commissioned") -> 0 | BL9: =COUNTIFS('LOI and Commissioning Master Sh'!$D:$D,Summary!$A9,'LOI and Commissioning Master Sh'!$G:$G,Summary!BL$2,'LOI and Commissioning Master Sh'!$H:$H,Summary!BL$3,'LOI and Commissioning Master Sh'!$BW:$BW, "Commissioned") -> 0 | BM9: =COUNTIFS('LOI and Commissioning Master Sh'!$D:$D,Summary!$A9,'LOI and Commissioning Master Sh'!$G:$G,Summary!BM$2,'LOI and Commissioning Master Sh'!$H:$H,Summary!BM$3,'LOI and Commissioning Master Sh'!$BW:$BW, "Commissioned") -> 0 | ... BQ9: =COUNTIFS('LOI and Commissioning Master Sh'!$D:$D,Summary!$A9,'LOI and Commissioning Master Sh'!$G:$G,Summary!BQ$2,'LOI and Commissioning Master Sh'!$H:$H,Summary!BQ$3,'LOI and Commissioning Master Sh'!$BW:$BW, "Commissioned") -> 0 | BR9: =+SUM(BF9:BQ9) -> 0
